Compiled from "GitMoveDeleteHookTest.java"
public class org.eclipse.egit.core.GitMoveDeleteHookTest {
  org.eclipse.egit.core.test.TestUtils testUtils;

  org.eclipse.egit.core.test.TestRepository testRepository;

  org.eclipse.jgit.lib.Repository repository;

  java.util.Set<java.io.File> testDirs;

  java.io.File workspaceSupplement;

  java.io.File workspace;

  public org.eclipse.egit.core.GitMoveDeleteHookTest();
    Code:
       0: aload_0       
       1: invokespecial #21                 // Method java/lang/Object."<init>":()V
       4: aload_0       
       5: new           #23                 // class org/eclipse/egit/core/test/TestUtils
       8: dup           
       9: invokespecial #25                 // Method org/eclipse/egit/core/test/TestUtils."<init>":()V
      12: putfield      #26                 // Field testUtils:Lorg/eclipse/egit/core/test/TestUtils;
      15: aload_0       
      16: new           #28                 // class java/util/HashSet
      19: dup           
      20: invokespecial #30                 // Method java/util/HashSet."<init>":()V
      23: putfield      #31                 // Field testDirs:Ljava/util/Set;
      26: return        

  public void setUp() throws java.lang.Exception;
    Code:
       0: invokestatic  #43                 // Method org/eclipse/egit/core/Activator.getDefault:()Lorg/eclipse/egit/core/Activator;
       3: invokevirtual #49                 // Method org/eclipse/egit/core/Activator.getRepositoryCache:()Lorg/eclipse/egit/core/RepositoryCache;
       6: invokevirtual #53                 // Method org/eclipse/egit/core/RepositoryCache.clear:()V
       9: new           #58                 // class org/eclipse/jgit/junit/MockSystemReader
      12: dup           
      13: invokespecial #60                 // Method org/eclipse/jgit/junit/MockSystemReader."<init>":()V
      16: astore_1      
      17: aload_1       
      18: invokestatic  #61                 // Method org/eclipse/jgit/util/SystemReader.setInstance:(Lorg/eclipse/jgit/util/SystemReader;)V
      21: aload_1       
      22: ldc           #67                 // String GIT_CEILING_DIRECTORIES
      24: invokestatic  #69                 // Method org/eclipse/core/resources/ResourcesPlugin.getWorkspace:()Lorg/eclipse/core/resources/IWorkspace;
      27: invokeinterface #75,  1           // InterfaceMethod org/eclipse/core/resources/IWorkspace.getRoot:()Lorg/eclipse/core/resources/IWorkspaceRoot;
      32: invokeinterface #81,  1           // InterfaceMethod org/eclipse/core/resources/IWorkspaceRoot.getLocation:()Lorg/eclipse/core/runtime/IPath;
      37: invokeinterface #87,  1           // InterfaceMethod org/eclipse/core/runtime/IPath.toFile:()Ljava/io/File;
      42: invokevirtual #93                 // Method java/io/File.getParentFile:()Ljava/io/File;
      45: invokevirtual #98                 // Method java/io/File.getAbsoluteFile:()Ljava/io/File;
      48: invokevirtual #101                // Method java/io/File.toString:()Ljava/lang/String;
      51: invokevirtual #105                // Method org/eclipse/jgit/junit/MockSystemReader.setProperty:(Ljava/lang/String;Ljava/lang/String;)V
      54: aload_0       
      55: aload_0       
      56: getfield      #26                 // Field testUtils:Lorg/eclipse/egit/core/test/TestUtils;
      59: ldc           #109                // String wssupplement
      61: invokevirtual #111                // Method org/eclipse/egit/core/test/TestUtils.createTempDir:(Ljava/lang/String;)Ljava/io/File;
      64: putfield      #115                // Field workspaceSupplement:Ljava/io/File;
      67: aload_0       
      68: getfield      #31                 // Field testDirs:Ljava/util/Set;
      71: aload_0       
      72: getfield      #26                 // Field testUtils:Lorg/eclipse/egit/core/test/TestUtils;
      75: invokevirtual #117                // Method org/eclipse/egit/core/test/TestUtils.getBaseTempDir:()Ljava/io/File;
      78: invokeinterface #120,  2          // InterfaceMethod java/util/Set.add:(Ljava/lang/Object;)Z
      83: pop           
      84: aload_0       
      85: invokestatic  #69                 // Method org/eclipse/core/resources/ResourcesPlugin.getWorkspace:()Lorg/eclipse/core/resources/IWorkspace;
      88: invokeinterface #75,  1           // InterfaceMethod org/eclipse/core/resources/IWorkspace.getRoot:()Lorg/eclipse/core/resources/IWorkspaceRoot;
      93: invokeinterface #81,  1           // InterfaceMethod org/eclipse/core/resources/IWorkspaceRoot.getLocation:()Lorg/eclipse/core/runtime/IPath;
      98: invokeinterface #87,  1           // InterfaceMethod org/eclipse/core/runtime/IPath.toFile:()Ljava/io/File;
     103: invokevirtual #98                 // Method java/io/File.getAbsoluteFile:()Ljava/io/File;
     106: putfield      #126                // Field workspace:Ljava/io/File;
     109: return        

  public void tearDown() throws java.io.IOException, org.eclipse.core.runtime.CoreException;
    Code:
       0: invokestatic  #69                 // Method org/eclipse/core/resources/ResourcesPlugin.getWorkspace:()Lorg/eclipse/core/resources/IWorkspace;
       3: invokeinterface #75,  1           // InterfaceMethod org/eclipse/core/resources/IWorkspace.getRoot:()Lorg/eclipse/core/resources/IWorkspaceRoot;
       8: iconst_1      
       9: aconst_null   
      10: invokeinterface #136,  3          // InterfaceMethod org/eclipse/core/resources/IWorkspaceRoot.delete:(ILorg/eclipse/core/runtime/IProgressMonitor;)V
      15: aload_0       
      16: getfield      #140                // Field testRepository:Lorg/eclipse/egit/core/test/TestRepository;
      19: ifnull        29
      22: aload_0       
      23: getfield      #140                // Field testRepository:Lorg/eclipse/egit/core/test/TestRepository;
      26: invokevirtual #142                // Method org/eclipse/egit/core/test/TestRepository.dispose:()V
      29: aload_0       
      30: aconst_null   
      31: putfield      #147                // Field repository:Lorg/eclipse/jgit/lib/Repository;
      34: aload_0       
      35: getfield      #31                 // Field testDirs:Ljava/util/Set;
      38: invokeinterface #149,  1          // InterfaceMethod java/util/Set.iterator:()Ljava/util/Iterator;
      43: astore_2      
      44: goto          69
      47: aload_2       
      48: invokeinterface #153,  1          // InterfaceMethod java/util/Iterator.next:()Ljava/lang/Object;
      53: checkcast     #94                 // class java/io/File
      56: astore_1      
      57: aload_1       
      58: invokevirtual #159                // Method java/io/File.exists:()Z
      61: ifeq          69
      64: aload_1       
      65: iconst_3      
      66: invokestatic  #163                // Method org/eclipse/jgit/util/FileUtils.delete:(Ljava/io/File;I)V
      69: aload_2       
      70: invokeinterface #168,  1          // InterfaceMethod java/util/Iterator.hasNext:()Z
      75: ifne          47
      78: aconst_null   
      79: invokestatic  #61                 // Method org/eclipse/jgit/util/SystemReader.setInstance:(Lorg/eclipse/jgit/util/SystemReader;)V
      82: return        

  private org.eclipse.egit.core.test.TestProject initRepoInsideProjectInsideWorkspace() throws java.io.IOException, org.eclipse.core.runtime.CoreException;
    Code:
       0: new           #175                // class org/eclipse/egit/core/test/TestProject
       3: dup           
       4: iconst_1      
       5: ldc           #177                // String Project-1
       7: iconst_1      
       8: aload_0       
       9: getfield      #115                // Field workspaceSupplement:Ljava/io/File;
      12: invokespecial #179                // Method org/eclipse/egit/core/test/TestProject."<init>":(ZLjava/lang/String;ZLjava/io/File;)V
      15: astore_1      
      16: new           #94                 // class java/io/File
      19: dup           
      20: aload_1       
      21: invokevirtual #182                // Method org/eclipse/egit/core/test/TestProject.getProject:()Lorg/eclipse/core/resources/IProject;
      24: invokeinterface #186,  1          // InterfaceMethod org/eclipse/core/resources/IProject.getLocationURI:()Ljava/net/URI;
      29: invokevirtual #192                // Method java/net/URI.getPath:()Ljava/lang/String;
      32: ldc           #197                // String .git
      34: invokespecial #199                // Method java/io/File."<init>":(Ljava/lang/String;Ljava/lang/String;)V
      37: astore_2      
      38: aload_0       
      39: getfield      #31                 // Field testDirs:Ljava/util/Set;
      42: aload_2       
      43: invokeinterface #120,  2          // InterfaceMethod java/util/Set.add:(Ljava/lang/Object;)Z
      48: pop           
      49: aload_0       
      50: new           #143                // class org/eclipse/egit/core/test/TestRepository
      53: dup           
      54: aload_2       
      55: invokespecial #201                // Method org/eclipse/egit/core/test/TestRepository."<init>":(Ljava/io/File;)V
      58: putfield      #140                // Field testRepository:Lorg/eclipse/egit/core/test/TestRepository;
      61: aload_0       
      62: aload_0       
      63: getfield      #140                // Field testRepository:Lorg/eclipse/egit/core/test/TestRepository;
      66: invokevirtual #204                // Method org/eclipse/egit/core/test/TestRepository.getRepository:()Lorg/eclipse/jgit/lib/Repository;
      69: putfield      #147                // Field repository:Lorg/eclipse/jgit/lib/Repository;
      72: aload_0       
      73: getfield      #140                // Field testRepository:Lorg/eclipse/egit/core/test/TestRepository;
      76: aload_1       
      77: invokevirtual #182                // Method org/eclipse/egit/core/test/TestProject.getProject:()Lorg/eclipse/core/resources/IProject;
      80: invokevirtual #208                // Method org/eclipse/egit/core/test/TestRepository.connect:(Lorg/eclipse/core/resources/IProject;)V
      83: aload_0       
      84: ldc           #177                // String Project-1
      86: invokespecial #212                // Method registerWorkspaceRelativeTestDir:(Ljava/lang/String;)V
      89: aload_1       
      90: areturn       

  private org.eclipse.egit.core.test.TestProject initRepoInsideProjectOutsideWorkspace() throws java.io.IOException, org.eclipse.core.runtime.CoreException;
    Code:
       0: new           #175                // class org/eclipse/egit/core/test/TestProject
       3: dup           
       4: iconst_1      
       5: ldc           #177                // String Project-1
       7: iconst_0      
       8: aload_0       
       9: getfield      #115                // Field workspaceSupplement:Ljava/io/File;
      12: invokespecial #179                // Method org/eclipse/egit/core/test/TestProject."<init>":(ZLjava/lang/String;ZLjava/io/File;)V
      15: astore_1      
      16: new           #94                 // class java/io/File
      19: dup           
      20: aload_1       
      21: invokevirtual #182                // Method org/eclipse/egit/core/test/TestProject.getProject:()Lorg/eclipse/core/resources/IProject;
      24: invokeinterface #186,  1          // InterfaceMethod org/eclipse/core/resources/IProject.getLocationURI:()Ljava/net/URI;
      29: invokevirtual #192                // Method java/net/URI.getPath:()Ljava/lang/String;
      32: ldc           #197                // String .git
      34: invokespecial #199                // Method java/io/File."<init>":(Ljava/lang/String;Ljava/lang/String;)V
      37: astore_2      
      38: aload_0       
      39: getfield      #31                 // Field testDirs:Ljava/util/Set;
      42: aload_2       
      43: invokeinterface #120,  2          // InterfaceMethod java/util/Set.add:(Ljava/lang/Object;)Z
      48: pop           
      49: aload_0       
      50: new           #143                // class org/eclipse/egit/core/test/TestRepository
      53: dup           
      54: aload_2       
      55: invokespecial #201                // Method org/eclipse/egit/core/test/TestRepository."<init>":(Ljava/io/File;)V
      58: putfield      #140                // Field testRepository:Lorg/eclipse/egit/core/test/TestRepository;
      61: aload_0       
      62: aload_0       
      63: getfield      #140                // Field testRepository:Lorg/eclipse/egit/core/test/TestRepository;
      66: invokevirtual #204                // Method org/eclipse/egit/core/test/TestRepository.getRepository:()Lorg/eclipse/jgit/lib/Repository;
      69: putfield      #147                // Field repository:Lorg/eclipse/jgit/lib/Repository;
      72: aload_0       
      73: getfield      #140                // Field testRepository:Lorg/eclipse/egit/core/test/TestRepository;
      76: aload_1       
      77: invokevirtual #182                // Method org/eclipse/egit/core/test/TestProject.getProject:()Lorg/eclipse/core/resources/IProject;
      80: invokevirtual #208                // Method org/eclipse/egit/core/test/TestRepository.connect:(Lorg/eclipse/core/resources/IProject;)V
      83: aload_1       
      84: areturn       

  private org.eclipse.egit.core.test.TestProject initRepoAboveProjectInsideWs(java.lang.String, java.lang.String) throws java.io.IOException, org.eclipse.core.runtime.CoreException;
    Code:
       0: aload_0       
       1: aload_1       
       2: aload_2       
       3: iconst_1      
       4: invokespecial #222                // Method initRepoAboveProject:(Ljava/lang/String;Ljava/lang/String;Z)Lorg/eclipse/egit/core/test/TestProject;
       7: areturn       

  private org.eclipse.egit.core.test.TestProject initRepoAboveProject(java.lang.String, java.lang.String, boolean) throws java.io.IOException, org.eclipse.core.runtime.CoreException;
    Code:
       0: aload_0       
       1: aload_1       
       2: invokespecial #212                // Method registerWorkspaceRelativeTestDir:(Ljava/lang/String;)V
       5: new           #175                // class org/eclipse/egit/core/test/TestProject
       8: dup           
       9: iconst_1      
      10: new           #228                // class java/lang/StringBuilder
      13: dup           
      14: aload_1       
      15: invokestatic  #230                // Method java/lang/String.valueOf:(Ljava/lang/Object;)Ljava/lang/String;
      18: invokespecial #236                // Method java/lang/StringBuilder."<init>":(Ljava/lang/String;)V
      21: ldc           #177                // String Project-1
      23: invokevirtual #238                // Method java/lang/StringBuilder.append:(Ljava/lang/String;)Ljava/lang/StringBuilder;
      26: invokevirtual #242                // Method java/lang/StringBuilder.toString:()Ljava/lang/String;
      29: iload_3       
      30: aload_0       
      31: getfield      #115                // Field workspaceSupplement:Ljava/io/File;
      34: invokespecial #179                // Method org/eclipse/egit/core/test/TestProject."<init>":(ZLjava/lang/String;ZLjava/io/File;)V
      37: astore        4
      39: new           #94                 // class java/io/File
      42: dup           
      43: iload_3       
      44: ifeq          54
      47: aload_0       
      48: getfield      #126                // Field workspace:Ljava/io/File;
      51: goto          58
      54: aload_0       
      55: getfield      #115                // Field workspaceSupplement:Ljava/io/File;
      58: aload_2       
      59: invokespecial #243                // Method java/io/File."<init>":(Ljava/io/File;Ljava/lang/String;)V
      62: astore        5
      64: new           #94                 // class java/io/File
      67: dup           
      68: aload         5
      70: ldc           #197                // String .git
      72: invokespecial #243                // Method java/io/File."<init>":(Ljava/io/File;Ljava/lang/String;)V
      75: astore        6
      77: aload_0       
      78: getfield      #31                 // Field testDirs:Ljava/util/Set;
      81: aload         6
      83: invokeinterface #120,  2          // InterfaceMethod java/util/Set.add:(Ljava/lang/Object;)Z
      88: pop           
      89: aload_0       
      90: new           #143                // class org/eclipse/egit/core/test/TestRepository
      93: dup           
      94: aload         6
      96: invokespecial #201                // Method org/eclipse/egit/core/test/TestRepository."<init>":(Ljava/io/File;)V
      99: putfield      #140                // Field testRepository:Lorg/eclipse/egit/core/test/TestRepository;
     102: aload_0       
     103: aload_0       
     104: getfield      #140                // Field testRepository:Lorg/eclipse/egit/core/test/TestRepository;
     107: invokevirtual #204                // Method org/eclipse/egit/core/test/TestRepository.getRepository:()Lorg/eclipse/jgit/lib/Repository;
     110: putfield      #147                // Field repository:Lorg/eclipse/jgit/lib/Repository;
     113: aload_0       
     114: getfield      #140                // Field testRepository:Lorg/eclipse/egit/core/test/TestRepository;
     117: aload         4
     119: invokevirtual #182                // Method org/eclipse/egit/core/test/TestProject.getProject:()Lorg/eclipse/core/resources/IProject;
     122: invokevirtual #208                // Method org/eclipse/egit/core/test/TestRepository.connect:(Lorg/eclipse/core/resources/IProject;)V
     125: aload         4
     127: areturn       

  public void testDeleteFile() throws java.lang.Exception;
    Code:
       0: aload_0       
       1: invokespecial #251                // Method initRepoInsideProjectInsideWorkspace:()Lorg/eclipse/egit/core/test/TestProject;
       4: astore_1      
       5: aload_0       
       6: getfield      #26                 // Field testUtils:Lorg/eclipse/egit/core/test/TestUtils;
       9: aload_1       
      10: invokevirtual #182                // Method org/eclipse/egit/core/test/TestProject.getProject:()Lorg/eclipse/core/resources/IProject;
      13: ldc           #253                // String file.txt
      15: ldc           #255                // String some text
      17: invokevirtual #257                // Method org/eclipse/egit/core/test/TestUtils.addFileToProject:(Lorg/eclipse/core/resources/IProject;Ljava/lang/String;Ljava/lang/String;)Lorg/eclipse/core/resources/IFile;
      20: pop           
      21: aload_0       
      22: getfield      #26                 // Field testUtils:Lorg/eclipse/egit/core/test/TestUtils;
      25: aload_1       
      26: invokevirtual #182                // Method org/eclipse/egit/core/test/TestProject.getProject:()Lorg/eclipse/core/resources/IProject;
      29: ldc_w         #261                // String file2.txt
      32: ldc_w         #263                // String some  more text
      35: invokevirtual #257                // Method org/eclipse/egit/core/test/TestUtils.addFileToProject:(Lorg/eclipse/core/resources/IProject;Ljava/lang/String;Ljava/lang/String;)Lorg/eclipse/core/resources/IFile;
      38: pop           
      39: aload_1       
      40: invokevirtual #182                // Method org/eclipse/egit/core/test/TestProject.getProject:()Lorg/eclipse/core/resources/IProject;
      43: ldc           #253                // String file.txt
      45: invokeinterface #265,  2          // InterfaceMethod org/eclipse/core/resources/IProject.getFile:(Ljava/lang/String;)Lorg/eclipse/core/resources/IFile;
      50: astore_2      
      51: new           #269                // class org/eclipse/egit/core/op/AddToIndexOperation
      54: dup           
      55: iconst_2      
      56: anewarray     #271                // class org/eclipse/core/resources/IResource
      59: dup           
      60: iconst_0      
      61: aload_2       
      62: aastore       
      63: dup           
      64: iconst_1      
      65: aload_1       
      66: invokevirtual #182                // Method org/eclipse/egit/core/test/TestProject.getProject:()Lorg/eclipse/core/resources/IProject;
      69: ldc_w         #261                // String file2.txt
      72: invokeinterface #265,  2          // InterfaceMethod org/eclipse/core/resources/IProject.getFile:(Ljava/lang/String;)Lorg/eclipse/core/resources/IFile;
      77: aastore       
      78: invokespecial #273                // Method org/eclipse/egit/core/op/AddToIndexOperation."<init>":([Lorg/eclipse/core/resources/IResource;)V
      81: astore_3      
      82: aload_3       
      83: aconst_null   
      84: invokevirtual #276                // Method org/eclipse/egit/core/op/AddToIndexOperation.execute:(Lorg/eclipse/core/runtime/IProgressMonitor;)V
      87: aload_0       
      88: getfield      #147                // Field repository:Lorg/eclipse/jgit/lib/Repository;
      91: invokevirtual #280                // Method org/eclipse/jgit/lib/Repository.getIndexFile:()Ljava/io/File;
      94: getstatic     #285                // Field org/eclipse/jgit/util/FS.DETECTED:Lorg/eclipse/jgit/util/FS;
      97: invokestatic  #291                // Method org/eclipse/jgit/dircache/DirCache.read:(Ljava/io/File;Lorg/eclipse/jgit/util/FS;)Lorg/eclipse/jgit/dircache/DirCache;
     100: astore        4
     102: ldc2_w        #297                // long 2l
     105: aload         4
     107: invokevirtual #299                // Method org/eclipse/jgit/dircache/DirCache.getEntryCount:()I
     110: i2l           
     111: invokestatic  #303                // Method org/junit/Assert.assertEquals:(JJ)V
     114: aload         4
     116: ldc           #253                // String file.txt
     118: invokevirtual #309                // Method org/eclipse/jgit/dircache/DirCache.getEntry:(Ljava/lang/String;)Lorg/eclipse/jgit/dircache/DirCacheEntry;
     121: invokestatic  #313                // Method org/junit/Assert.assertNotNull:(Ljava/lang/Object;)V
     124: aload         4
     126: ldc_w         #261                // String file2.txt
     129: invokevirtual #309                // Method org/eclipse/jgit/dircache/DirCache.getEntry:(Ljava/lang/String;)Lorg/eclipse/jgit/dircache/DirCacheEntry;
     132: invokestatic  #313                // Method org/junit/Assert.assertNotNull:(Ljava/lang/Object;)V
     135: aload_0       
     136: getfield      #26                 // Field testUtils:Lorg/eclipse/egit/core/test/TestUtils;
     139: aload_1       
     140: invokevirtual #182                // Method org/eclipse/egit/core/test/TestProject.getProject:()Lorg/eclipse/core/resources/IProject;
     143: aload_2       
     144: ldc_w         #317                // String other text
     147: invokevirtual #319                // Method org/eclipse/egit/core/test/TestUtils.changeContentOfFile:(Lorg/eclipse/core/resources/IProject;Lorg/eclipse/core/resources/IFile;Ljava/lang/String;)Lorg/eclipse/core/resources/IFile;
     150: pop           
     151: aload_0       
     152: getfield      #26                 // Field testUtils:Lorg/eclipse/egit/core/test/TestUtils;
     155: ldc2_w        #323                // long 10000l
     158: ldc2_w        #325                // long 1000l
     161: getstatic     #327                // Field org/eclipse/egit/core/JobFamilies.INDEX_DIFF_CACHE_UPDATE:Ljava/lang/Object;
     164: invokevirtual #333                // Method org/eclipse/egit/core/test/TestUtils.waitForJobs:(JJLjava/lang/Object;)V
     167: aload_2       
     168: iconst_1      
     169: aconst_null   
     170: invokeinterface #337,  3          // InterfaceMethod org/eclipse/core/resources/IFile.delete:(ZLorg/eclipse/core/runtime/IProgressMonitor;)V
     175: aload_0       
     176: getfield      #26                 // Field testUtils:Lorg/eclipse/egit/core/test/TestUtils;
     179: ldc2_w        #323                // long 10000l
     182: ldc2_w        #325                // long 1000l
     185: getstatic     #327                // Field org/eclipse/egit/core/JobFamilies.INDEX_DIFF_CACHE_UPDATE:Ljava/lang/Object;
     188: invokevirtual #333                // Method org/eclipse/egit/core/test/TestUtils.waitForJobs:(JJLjava/lang/Object;)V
     191: aload         4
     193: invokevirtual #342                // Method org/eclipse/jgit/dircache/DirCache.read:()V
     196: lconst_1      
     197: aload         4
     199: invokevirtual #299                // Method org/eclipse/jgit/dircache/DirCache.getEntryCount:()I
     202: i2l           
     203: invokestatic  #303                // Method org/junit/Assert.assertEquals:(JJ)V
     206: aload         4
     208: ldc           #253                // String file.txt
     210: invokevirtual #309                // Method org/eclipse/jgit/dircache/DirCache.getEntry:(Ljava/lang/String;)Lorg/eclipse/jgit/dircache/DirCacheEntry;
     213: invokestatic  #344                // Method org/junit/Assert.assertNull:(Ljava/lang/Object;)V
     216: aload         4
     218: ldc_w         #261                // String file2.txt
     221: invokevirtual #309                // Method org/eclipse/jgit/dircache/DirCache.getEntry:(Ljava/lang/String;)Lorg/eclipse/jgit/dircache/DirCacheEntry;
     224: invokestatic  #313                // Method org/junit/Assert.assertNotNull:(Ljava/lang/Object;)V
     227: aload_2       
     228: invokeinterface #347,  1          // InterfaceMethod org/eclipse/core/resources/IFile.exists:()Z
     233: invokestatic  #348                // Method org/junit/Assert.assertFalse:(Z)V
     236: aload_1       
     237: invokevirtual #182                // Method org/eclipse/egit/core/test/TestProject.getProject:()Lorg/eclipse/core/resources/IProject;
     240: ldc_w         #261                // String file2.txt
     243: invokeinterface #265,  2          // InterfaceMethod org/eclipse/core/resources/IProject.getFile:(Ljava/lang/String;)Lorg/eclipse/core/resources/IFile;
     248: invokeinterface #347,  1          // InterfaceMethod org/eclipse/core/resources/IFile.exists:()Z
     253: invokestatic  #352                // Method org/junit/Assert.assertTrue:(Z)V
     256: return        

  public void testDeleteFolder() throws java.lang.Exception;
    Code:
       0: aload_0       
       1: invokespecial #251                // Method initRepoInsideProjectInsideWorkspace:()Lorg/eclipse/egit/core/test/TestProject;
       4: astore_1      
       5: aload_0       
       6: getfield      #26                 // Field testUtils:Lorg/eclipse/egit/core/test/TestUtils;
       9: aload_1       
      10: invokevirtual #182                // Method org/eclipse/egit/core/test/TestProject.getProject:()Lorg/eclipse/core/resources/IProject;
      13: ldc_w         #362                // String folder/file.txt
      16: ldc           #255                // String some text
      18: invokevirtual #257                // Method org/eclipse/egit/core/test/TestUtils.addFileToProject:(Lorg/eclipse/core/resources/IProject;Ljava/lang/String;Ljava/lang/String;)Lorg/eclipse/core/resources/IFile;
      21: pop           
      22: aload_0       
      23: getfield      #26                 // Field testUtils:Lorg/eclipse/egit/core/test/TestUtils;
      26: aload_1       
      27: invokevirtual #182                // Method org/eclipse/egit/core/test/TestProject.getProject:()Lorg/eclipse/core/resources/IProject;
      30: ldc_w         #364                // String folder2/file.txt
      33: ldc_w         #366                // String some other text
      36: invokevirtual #257                // Method org/eclipse/egit/core/test/TestUtils.addFileToProject:(Lorg/eclipse/core/resources/IProject;Ljava/lang/String;Ljava/lang/String;)Lorg/eclipse/core/resources/IFile;
      39: pop           
      40: new           #269                // class org/eclipse/egit/core/op/AddToIndexOperation
      43: dup           
      44: iconst_2      
      45: anewarray     #271                // class org/eclipse/core/resources/IResource
      48: dup           
      49: iconst_0      
      50: aload_1       
      51: invokevirtual #182                // Method org/eclipse/egit/core/test/TestProject.getProject:()Lorg/eclipse/core/resources/IProject;
      54: ldc_w         #362                // String folder/file.txt
      57: invokeinterface #265,  2          // InterfaceMethod org/eclipse/core/resources/IProject.getFile:(Ljava/lang/String;)Lorg/eclipse/core/resources/IFile;
      62: aastore       
      63: dup           
      64: iconst_1      
      65: aload_1       
      66: invokevirtual #182                // Method org/eclipse/egit/core/test/TestProject.getProject:()Lorg/eclipse/core/resources/IProject;
      69: ldc_w         #364                // String folder2/file.txt
      72: invokeinterface #265,  2          // InterfaceMethod org/eclipse/core/resources/IProject.getFile:(Ljava/lang/String;)Lorg/eclipse/core/resources/IFile;
      77: aastore       
      78: invokespecial #273                // Method org/eclipse/egit/core/op/AddToIndexOperation."<init>":([Lorg/eclipse/core/resources/IResource;)V
      81: astore_2      
      82: aload_2       
      83: aconst_null   
      84: invokevirtual #276                // Method org/eclipse/egit/core/op/AddToIndexOperation.execute:(Lorg/eclipse/core/runtime/IProgressMonitor;)V
      87: aload_0       
      88: getfield      #147                // Field repository:Lorg/eclipse/jgit/lib/Repository;
      91: invokevirtual #280                // Method org/eclipse/jgit/lib/Repository.getIndexFile:()Ljava/io/File;
      94: getstatic     #285                // Field org/eclipse/jgit/util/FS.DETECTED:Lorg/eclipse/jgit/util/FS;
      97: invokestatic  #291                // Method org/eclipse/jgit/dircache/DirCache.read:(Ljava/io/File;Lorg/eclipse/jgit/util/FS;)Lorg/eclipse/jgit/dircache/DirCache;
     100: astore_3      
     101: aload_3       
     102: ldc_w         #362                // String folder/file.txt
     105: invokevirtual #309                // Method org/eclipse/jgit/dircache/DirCache.getEntry:(Ljava/lang/String;)Lorg/eclipse/jgit/dircache/DirCacheEntry;
     108: invokestatic  #313                // Method org/junit/Assert.assertNotNull:(Ljava/lang/Object;)V
     111: aload_3       
     112: ldc_w         #364                // String folder2/file.txt
     115: invokevirtual #309                // Method org/eclipse/jgit/dircache/DirCache.getEntry:(Ljava/lang/String;)Lorg/eclipse/jgit/dircache/DirCacheEntry;
     118: invokestatic  #313                // Method org/junit/Assert.assertNotNull:(Ljava/lang/Object;)V
     121: aload_0       
     122: getfield      #26                 // Field testUtils:Lorg/eclipse/egit/core/test/TestUtils;
     125: aload_1       
     126: invokevirtual #182                // Method org/eclipse/egit/core/test/TestProject.getProject:()Lorg/eclipse/core/resources/IProject;
     129: aload_1       
     130: invokevirtual #182                // Method org/eclipse/egit/core/test/TestProject.getProject:()Lorg/eclipse/core/resources/IProject;
     133: ldc_w         #362                // String folder/file.txt
     136: invokeinterface #265,  2          // InterfaceMethod org/eclipse/core/resources/IProject.getFile:(Ljava/lang/String;)Lorg/eclipse/core/resources/IFile;
     141: ldc_w         #317                // String other text
     144: invokevirtual #319                // Method org/eclipse/egit/core/test/TestUtils.changeContentOfFile:(Lorg/eclipse/core/resources/IProject;Lorg/eclipse/core/resources/IFile;Ljava/lang/String;)Lorg/eclipse/core/resources/IFile;
     147: pop           
     148: aload_1       
     149: invokevirtual #182                // Method org/eclipse/egit/core/test/TestProject.getProject:()Lorg/eclipse/core/resources/IProject;
     152: ldc_w         #368                // String folder
     155: invokeinterface #370,  2          // InterfaceMethod org/eclipse/core/resources/IProject.getFolder:(Ljava/lang/String;)Lorg/eclipse/core/resources/IFolder;
     160: iconst_1      
     161: aconst_null   
     162: invokeinterface #374,  3          // InterfaceMethod org/eclipse/core/resources/IFolder.delete:(ZLorg/eclipse/core/runtime/IProgressMonitor;)V
     167: aload_3       
     168: invokevirtual #342                // Method org/eclipse/jgit/dircache/DirCache.read:()V
     171: aload_3       
     172: ldc_w         #362                // String folder/file.txt
     175: invokevirtual #309                // Method org/eclipse/jgit/dircache/DirCache.getEntry:(Ljava/lang/String;)Lorg/eclipse/jgit/dircache/DirCacheEntry;
     178: invokestatic  #313                // Method org/junit/Assert.assertNotNull:(Ljava/lang/Object;)V
     181: aload_3       
     182: ldc_w         #364                // String folder2/file.txt
     185: invokevirtual #309                // Method org/eclipse/jgit/dircache/DirCache.getEntry:(Ljava/lang/String;)Lorg/eclipse/jgit/dircache/DirCacheEntry;
     188: invokestatic  #313                // Method org/junit/Assert.assertNotNull:(Ljava/lang/Object;)V
     191: return        

  public void testDeleteProject() throws java.lang.Exception;
    Code:
       0: aload_0       
       1: ldc_w         #378                // String P/
       4: ldc_w         #380                // String 
       7: invokespecial #382                // Method initRepoAboveProjectInsideWs:(Ljava/lang/String;Ljava/lang/String;)Lorg/eclipse/egit/core/test/TestProject;
      10: astore_1      
      11: aload_0       
      12: getfield      #26                 // Field testUtils:Lorg/eclipse/egit/core/test/TestUtils;
      15: aload_1       
      16: invokevirtual #182                // Method org/eclipse/egit/core/test/TestProject.getProject:()Lorg/eclipse/core/resources/IProject;
      19: ldc           #253                // String file.txt
      21: ldc           #255                // String some text
      23: invokevirtual #257                // Method org/eclipse/egit/core/test/TestUtils.addFileToProject:(Lorg/eclipse/core/resources/IProject;Ljava/lang/String;Ljava/lang/String;)Lorg/eclipse/core/resources/IFile;
      26: pop           
      27: new           #269                // class org/eclipse/egit/core/op/AddToIndexOperation
      30: dup           
      31: iconst_1      
      32: anewarray     #271                // class org/eclipse/core/resources/IResource
      35: dup           
      36: iconst_0      
      37: aload_1       
      38: invokevirtual #182                // Method org/eclipse/egit/core/test/TestProject.getProject:()Lorg/eclipse/core/resources/IProject;
      41: ldc           #253                // String file.txt
      43: invokeinterface #265,  2          // InterfaceMethod org/eclipse/core/resources/IProject.getFile:(Ljava/lang/String;)Lorg/eclipse/core/resources/IFile;
      48: aastore       
      49: invokespecial #273                // Method org/eclipse/egit/core/op/AddToIndexOperation."<init>":([Lorg/eclipse/core/resources/IResource;)V
      52: astore_2      
      53: aload_2       
      54: aconst_null   
      55: invokevirtual #276                // Method org/eclipse/egit/core/op/AddToIndexOperation.execute:(Lorg/eclipse/core/runtime/IProgressMonitor;)V
      58: aload_1       
      59: invokevirtual #182                // Method org/eclipse/egit/core/test/TestProject.getProject:()Lorg/eclipse/core/resources/IProject;
      62: invokestatic  #384                // Method org/eclipse/egit/core/project/RepositoryMapping.getMapping:(Lorg/eclipse/core/resources/IProject;)Lorg/eclipse/egit/core/project/RepositoryMapping;
      65: astore_3      
      66: aload_3       
      67: invokevirtual #390                // Method org/eclipse/egit/core/project/RepositoryMapping.getGitDirAbsolutePath:()Lorg/eclipse/core/runtime/IPath;
      70: astore        4
      72: aload         4
      74: invokeinterface #87,  1           // InterfaceMethod org/eclipse/core/runtime/IPath.toFile:()Ljava/io/File;
      79: invokestatic  #393                // Method org/eclipse/jgit/storage/file/FileRepositoryBuilder.create:(Ljava/io/File;)Lorg/eclipse/jgit/lib/Repository;
      82: astore        5
      84: aload         5
      86: invokevirtual #280                // Method org/eclipse/jgit/lib/Repository.getIndexFile:()Ljava/io/File;
      89: aload         5
      91: invokevirtual #399                // Method org/eclipse/jgit/lib/Repository.getFS:()Lorg/eclipse/jgit/util/FS;
      94: invokestatic  #291                // Method org/eclipse/jgit/dircache/DirCache.read:(Ljava/io/File;Lorg/eclipse/jgit/util/FS;)Lorg/eclipse/jgit/dircache/DirCache;
      97: astore        6
      99: aload         6
     101: ldc_w         #403                // String P/Project-1/file.txt
     104: invokevirtual #309                // Method org/eclipse/jgit/dircache/DirCache.getEntry:(Ljava/lang/String;)Lorg/eclipse/jgit/dircache/DirCacheEntry;
     107: invokestatic  #313                // Method org/junit/Assert.assertNotNull:(Ljava/lang/Object;)V
     110: aload         5
     112: invokevirtual #405                // Method org/eclipse/jgit/lib/Repository.close:()V
     115: aconst_null   
     116: astore        5
     118: aload_1       
     119: invokevirtual #182                // Method org/eclipse/egit/core/test/TestProject.getProject:()Lorg/eclipse/core/resources/IProject;
     122: iconst_1      
     123: aconst_null   
     124: invokeinterface #408,  3          // InterfaceMethod org/eclipse/core/resources/IProject.delete:(ZLorg/eclipse/core/runtime/IProgressMonitor;)V
     129: aload_1       
     130: invokevirtual #182                // Method org/eclipse/egit/core/test/TestProject.getProject:()Lorg/eclipse/core/resources/IProject;
     133: invokestatic  #384                // Method org/eclipse/egit/core/project/RepositoryMapping.getMapping:(Lorg/eclipse/core/resources/IProject;)Lorg/eclipse/egit/core/project/RepositoryMapping;
     136: invokestatic  #344                // Method org/junit/Assert.assertNull:(Ljava/lang/Object;)V
     139: aload         4
     141: invokeinterface #409,  1          // InterfaceMethod org/eclipse/core/runtime/IPath.toString:()Ljava/lang/String;
     146: aload         4
     148: ldc_w         #410                // String HEAD
     151: invokeinterface #412,  2          // InterfaceMethod org/eclipse/core/runtime/IPath.append:(Ljava/lang/String;)Lorg/eclipse/core/runtime/IPath;
     156: invokeinterface #87,  1           // InterfaceMethod org/eclipse/core/runtime/IPath.toFile:()Ljava/io/File;
     161: invokevirtual #159                // Method java/io/File.exists:()Z
     164: invokestatic  #415                // Method org/junit/Assert.assertTrue:(Ljava/lang/String;Z)V
     167: aload         4
     169: invokeinterface #87,  1           // InterfaceMethod org/eclipse/core/runtime/IPath.toFile:()Ljava/io/File;
     174: invokestatic  #393                // Method org/eclipse/jgit/storage/file/FileRepositoryBuilder.create:(Ljava/io/File;)Lorg/eclipse/jgit/lib/Repository;
     177: astore        5
     179: aload         5
     181: invokevirtual #280                // Method org/eclipse/jgit/lib/Repository.getIndexFile:()Ljava/io/File;
     184: aload         5
     186: invokevirtual #399                // Method org/eclipse/jgit/lib/Repository.getFS:()Lorg/eclipse/jgit/util/FS;
     189: invokestatic  #291                // Method org/eclipse/jgit/dircache/DirCache.read:(Ljava/io/File;Lorg/eclipse/jgit/util/FS;)Lorg/eclipse/jgit/dircache/DirCache;
     192: astore        6
     194: aload         6
     196: ldc_w         #403                // String P/Project-1/file.txt
     199: invokevirtual #309                // Method org/eclipse/jgit/dircache/DirCache.getEntry:(Ljava/lang/String;)Lorg/eclipse/jgit/dircache/DirCacheEntry;
     202: invokestatic  #313                // Method org/junit/Assert.assertNotNull:(Ljava/lang/Object;)V
     205: aload         5
     207: invokevirtual #405                // Method org/eclipse/jgit/lib/Repository.close:()V
     210: return        

  public void testMoveFile() throws java.lang.Exception;
    Code:
       0: aload_0       
       1: invokespecial #251                // Method initRepoInsideProjectInsideWorkspace:()Lorg/eclipse/egit/core/test/TestProject;
       4: astore_1      
       5: aload_0       
       6: getfield      #26                 // Field testUtils:Lorg/eclipse/egit/core/test/TestUtils;
       9: aload_1       
      10: invokevirtual #182                // Method org/eclipse/egit/core/test/TestProject.getProject:()Lorg/eclipse/core/resources/IProject;
      13: ldc           #253                // String file.txt
      15: ldc           #255                // String some text
      17: invokevirtual #257                // Method org/eclipse/egit/core/test/TestUtils.addFileToProject:(Lorg/eclipse/core/resources/IProject;Ljava/lang/String;Ljava/lang/String;)Lorg/eclipse/core/resources/IFile;
      20: pop           
      21: aload_0       
      22: getfield      #26                 // Field testUtils:Lorg/eclipse/egit/core/test/TestUtils;
      25: aload_1       
      26: invokevirtual #182                // Method org/eclipse/egit/core/test/TestProject.getProject:()Lorg/eclipse/core/resources/IProject;
      29: ldc_w         #261                // String file2.txt
      32: ldc_w         #263                // String some  more text
      35: invokevirtual #257                // Method org/eclipse/egit/core/test/TestUtils.addFileToProject:(Lorg/eclipse/core/resources/IProject;Ljava/lang/String;Ljava/lang/String;)Lorg/eclipse/core/resources/IFile;
      38: pop           
      39: new           #269                // class org/eclipse/egit/core/op/AddToIndexOperation
      42: dup           
      43: iconst_2      
      44: anewarray     #271                // class org/eclipse/core/resources/IResource
      47: dup           
      48: iconst_0      
      49: aload_1       
      50: invokevirtual #182                // Method org/eclipse/egit/core/test/TestProject.getProject:()Lorg/eclipse/core/resources/IProject;
      53: ldc           #253                // String file.txt
      55: invokeinterface #265,  2          // InterfaceMethod org/eclipse/core/resources/IProject.getFile:(Ljava/lang/String;)Lorg/eclipse/core/resources/IFile;
      60: aastore       
      61: dup           
      62: iconst_1      
      63: aload_1       
      64: invokevirtual #182                // Method org/eclipse/egit/core/test/TestProject.getProject:()Lorg/eclipse/core/resources/IProject;
      67: ldc_w         #261                // String file2.txt
      70: invokeinterface #265,  2          // InterfaceMethod org/eclipse/core/resources/IProject.getFile:(Ljava/lang/String;)Lorg/eclipse/core/resources/IFile;
      75: aastore       
      76: invokespecial #273                // Method org/eclipse/egit/core/op/AddToIndexOperation."<init>":([Lorg/eclipse/core/resources/IResource;)V
      79: astore_2      
      80: aload_2       
      81: aconst_null   
      82: invokevirtual #276                // Method org/eclipse/egit/core/op/AddToIndexOperation.execute:(Lorg/eclipse/core/runtime/IProgressMonitor;)V
      85: aload_0       
      86: getfield      #147                // Field repository:Lorg/eclipse/jgit/lib/Repository;
      89: invokevirtual #280                // Method org/eclipse/jgit/lib/Repository.getIndexFile:()Ljava/io/File;
      92: getstatic     #285                // Field org/eclipse/jgit/util/FS.DETECTED:Lorg/eclipse/jgit/util/FS;
      95: invokestatic  #291                // Method org/eclipse/jgit/dircache/DirCache.read:(Ljava/io/File;Lorg/eclipse/jgit/util/FS;)Lorg/eclipse/jgit/dircache/DirCache;
      98: astore_3      
      99: aload_3       
     100: ldc           #253                // String file.txt
     102: invokevirtual #309                // Method org/eclipse/jgit/dircache/DirCache.getEntry:(Ljava/lang/String;)Lorg/eclipse/jgit/dircache/DirCacheEntry;
     105: invokestatic  #313                // Method org/junit/Assert.assertNotNull:(Ljava/lang/Object;)V
     108: aload_3       
     109: ldc_w         #261                // String file2.txt
     112: invokevirtual #309                // Method org/eclipse/jgit/dircache/DirCache.getEntry:(Ljava/lang/String;)Lorg/eclipse/jgit/dircache/DirCacheEntry;
     115: invokestatic  #313                // Method org/junit/Assert.assertNotNull:(Ljava/lang/Object;)V
     118: aload_3       
     119: ldc_w         #425                // String data.txt
     122: invokevirtual #309                // Method org/eclipse/jgit/dircache/DirCache.getEntry:(Ljava/lang/String;)Lorg/eclipse/jgit/dircache/DirCacheEntry;
     125: invokestatic  #344                // Method org/junit/Assert.assertNull:(Ljava/lang/Object;)V
     128: aload_1       
     129: invokevirtual #182                // Method org/eclipse/egit/core/test/TestProject.getProject:()Lorg/eclipse/core/resources/IProject;
     132: ldc_w         #425                // String data.txt
     135: invokeinterface #265,  2          // InterfaceMethod org/eclipse/core/resources/IProject.getFile:(Ljava/lang/String;)Lorg/eclipse/core/resources/IFile;
     140: invokeinterface #347,  1          // InterfaceMethod org/eclipse/core/resources/IFile.exists:()Z
     145: invokestatic  #348                // Method org/junit/Assert.assertFalse:(Z)V
     148: aload_3       
     149: ldc           #253                // String file.txt
     151: invokevirtual #309                // Method org/eclipse/jgit/dircache/DirCache.getEntry:(Ljava/lang/String;)Lorg/eclipse/jgit/dircache/DirCacheEntry;
     154: invokevirtual #427                // Method org/eclipse/jgit/dircache/DirCacheEntry.getObjectId:()Lorg/eclipse/jgit/lib/ObjectId;
     157: astore        4
     159: aload_0       
     160: getfield      #26                 // Field testUtils:Lorg/eclipse/egit/core/test/TestUtils;
     163: aload_1       
     164: invokevirtual #182                // Method org/eclipse/egit/core/test/TestProject.getProject:()Lorg/eclipse/core/resources/IProject;
     167: aload_1       
     168: invokevirtual #182                // Method org/eclipse/egit/core/test/TestProject.getProject:()Lorg/eclipse/core/resources/IProject;
     171: ldc           #253                // String file.txt
     173: invokeinterface #265,  2          // InterfaceMethod org/eclipse/core/resources/IProject.getFile:(Ljava/lang/String;)Lorg/eclipse/core/resources/IFile;
     178: ldc_w         #317                // String other text
     181: invokevirtual #319                // Method org/eclipse/egit/core/test/TestUtils.changeContentOfFile:(Lorg/eclipse/core/resources/IProject;Lorg/eclipse/core/resources/IFile;Ljava/lang/String;)Lorg/eclipse/core/resources/IFile;
     184: pop           
     185: aload_1       
     186: invokevirtual #182                // Method org/eclipse/egit/core/test/TestProject.getProject:()Lorg/eclipse/core/resources/IProject;
     189: ldc           #253                // String file.txt
     191: invokeinterface #265,  2          // InterfaceMethod org/eclipse/core/resources/IProject.getFile:(Ljava/lang/String;)Lorg/eclipse/core/resources/IFile;
     196: aload_1       
     197: invokevirtual #182                // Method org/eclipse/egit/core/test/TestProject.getProject:()Lorg/eclipse/core/resources/IProject;
     200: ldc_w         #425                // String data.txt
     203: invokeinterface #265,  2          // InterfaceMethod org/eclipse/core/resources/IProject.getFile:(Ljava/lang/String;)Lorg/eclipse/core/resources/IFile;
     208: invokeinterface #433,  1          // InterfaceMethod org/eclipse/core/resources/IFile.getFullPath:()Lorg/eclipse/core/runtime/IPath;
     213: iconst_0      
     214: aconst_null   
     215: invokeinterface #436,  4          // InterfaceMethod org/eclipse/core/resources/IFile.move:(Lorg/eclipse/core/runtime/IPath;ZLorg/eclipse/core/runtime/IProgressMonitor;)V
     220: aload_3       
     221: invokevirtual #342                // Method org/eclipse/jgit/dircache/DirCache.read:()V
     224: aload_1       
     225: invokevirtual #182                // Method org/eclipse/egit/core/test/TestProject.getProject:()Lorg/eclipse/core/resources/IProject;
     228: ldc_w         #425                // String data.txt
     231: invokeinterface #265,  2          // InterfaceMethod org/eclipse/core/resources/IProject.getFile:(Ljava/lang/String;)Lorg/eclipse/core/resources/IFile;
     236: invokeinterface #347,  1          // InterfaceMethod org/eclipse/core/resources/IFile.exists:()Z
     241: invokestatic  #352                // Method org/junit/Assert.assertTrue:(Z)V
     244: aload_3       
     245: ldc_w         #425                // String data.txt
     248: invokevirtual #309                // Method org/eclipse/jgit/dircache/DirCache.getEntry:(Ljava/lang/String;)Lorg/eclipse/jgit/dircache/DirCacheEntry;
     251: invokestatic  #313                // Method org/junit/Assert.assertNotNull:(Ljava/lang/Object;)V
     254: aload         4
     256: aload_3       
     257: ldc_w         #425                // String data.txt
     260: invokevirtual #309                // Method org/eclipse/jgit/dircache/DirCache.getEntry:(Ljava/lang/String;)Lorg/eclipse/jgit/dircache/DirCacheEntry;
     263: invokevirtual #427                // Method org/eclipse/jgit/dircache/DirCacheEntry.getObjectId:()Lorg/eclipse/jgit/lib/ObjectId;
     266: invokestatic  #440                // Method org/junit/Assert.assertEquals:(Ljava/lang/Object;Ljava/lang/Object;)V
     269: aload_3       
     270: ldc_w         #261                // String file2.txt
     273: invokevirtual #309                // Method org/eclipse/jgit/dircache/DirCache.getEntry:(Ljava/lang/String;)Lorg/eclipse/jgit/dircache/DirCacheEntry;
     276: invokestatic  #313                // Method org/junit/Assert.assertNotNull:(Ljava/lang/Object;)V
     279: return        

  public void testMoveFolder() throws java.lang.Exception;
    Code:
       0: aload_0       
       1: invokespecial #251                // Method initRepoInsideProjectInsideWorkspace:()Lorg/eclipse/egit/core/test/TestProject;
       4: astore_1      
       5: aload_0       
       6: getfield      #26                 // Field testUtils:Lorg/eclipse/egit/core/test/TestUtils;
       9: aload_1       
      10: invokevirtual #182                // Method org/eclipse/egit/core/test/TestProject.getProject:()Lorg/eclipse/core/resources/IProject;
      13: ldc_w         #362                // String folder/file.txt
      16: ldc           #255                // String some text
      18: invokevirtual #257                // Method org/eclipse/egit/core/test/TestUtils.addFileToProject:(Lorg/eclipse/core/resources/IProject;Ljava/lang/String;Ljava/lang/String;)Lorg/eclipse/core/resources/IFile;
      21: pop           
      22: aload_0       
      23: getfield      #26                 // Field testUtils:Lorg/eclipse/egit/core/test/TestUtils;
      26: aload_1       
      27: invokevirtual #182                // Method org/eclipse/egit/core/test/TestProject.getProject:()Lorg/eclipse/core/resources/IProject;
      30: ldc_w         #364                // String folder2/file.txt
      33: ldc_w         #366                // String some other text
      36: invokevirtual #257                // Method org/eclipse/egit/core/test/TestUtils.addFileToProject:(Lorg/eclipse/core/resources/IProject;Ljava/lang/String;Ljava/lang/String;)Lorg/eclipse/core/resources/IFile;
      39: pop           
      40: new           #269                // class org/eclipse/egit/core/op/AddToIndexOperation
      43: dup           
      44: iconst_2      
      45: anewarray     #271                // class org/eclipse/core/resources/IResource
      48: dup           
      49: iconst_0      
      50: aload_1       
      51: invokevirtual #182                // Method org/eclipse/egit/core/test/TestProject.getProject:()Lorg/eclipse/core/resources/IProject;
      54: ldc_w         #362                // String folder/file.txt
      57: invokeinterface #265,  2          // InterfaceMethod org/eclipse/core/resources/IProject.getFile:(Ljava/lang/String;)Lorg/eclipse/core/resources/IFile;
      62: aastore       
      63: dup           
      64: iconst_1      
      65: aload_1       
      66: invokevirtual #182                // Method org/eclipse/egit/core/test/TestProject.getProject:()Lorg/eclipse/core/resources/IProject;
      69: ldc_w         #364                // String folder2/file.txt
      72: invokeinterface #265,  2          // InterfaceMethod org/eclipse/core/resources/IProject.getFile:(Ljava/lang/String;)Lorg/eclipse/core/resources/IFile;
      77: aastore       
      78: invokespecial #273                // Method org/eclipse/egit/core/op/AddToIndexOperation."<init>":([Lorg/eclipse/core/resources/IResource;)V
      81: astore_2      
      82: aload_2       
      83: aconst_null   
      84: invokevirtual #276                // Method org/eclipse/egit/core/op/AddToIndexOperation.execute:(Lorg/eclipse/core/runtime/IProgressMonitor;)V
      87: aload_0       
      88: getfield      #147                // Field repository:Lorg/eclipse/jgit/lib/Repository;
      91: invokevirtual #280                // Method org/eclipse/jgit/lib/Repository.getIndexFile:()Ljava/io/File;
      94: getstatic     #285                // Field org/eclipse/jgit/util/FS.DETECTED:Lorg/eclipse/jgit/util/FS;
      97: invokestatic  #291                // Method org/eclipse/jgit/dircache/DirCache.read:(Ljava/io/File;Lorg/eclipse/jgit/util/FS;)Lorg/eclipse/jgit/dircache/DirCache;
     100: astore_3      
     101: aload_3       
     102: ldc_w         #362                // String folder/file.txt
     105: invokevirtual #309                // Method org/eclipse/jgit/dircache/DirCache.getEntry:(Ljava/lang/String;)Lorg/eclipse/jgit/dircache/DirCacheEntry;
     108: invokestatic  #313                // Method org/junit/Assert.assertNotNull:(Ljava/lang/Object;)V
     111: aload_3       
     112: ldc_w         #364                // String folder2/file.txt
     115: invokevirtual #309                // Method org/eclipse/jgit/dircache/DirCache.getEntry:(Ljava/lang/String;)Lorg/eclipse/jgit/dircache/DirCacheEntry;
     118: invokestatic  #313                // Method org/junit/Assert.assertNotNull:(Ljava/lang/Object;)V
     121: aload_3       
     122: ldc_w         #446                // String dir/file.txt
     125: invokevirtual #309                // Method org/eclipse/jgit/dircache/DirCache.getEntry:(Ljava/lang/String;)Lorg/eclipse/jgit/dircache/DirCacheEntry;
     128: invokestatic  #344                // Method org/junit/Assert.assertNull:(Ljava/lang/Object;)V
     131: aload_1       
     132: invokevirtual #182                // Method org/eclipse/egit/core/test/TestProject.getProject:()Lorg/eclipse/core/resources/IProject;
     135: ldc_w         #446                // String dir/file.txt
     138: invokeinterface #265,  2          // InterfaceMethod org/eclipse/core/resources/IProject.getFile:(Ljava/lang/String;)Lorg/eclipse/core/resources/IFile;
     143: invokeinterface #347,  1          // InterfaceMethod org/eclipse/core/resources/IFile.exists:()Z
     148: invokestatic  #348                // Method org/junit/Assert.assertFalse:(Z)V
     151: aload_3       
     152: ldc_w         #362                // String folder/file.txt
     155: invokevirtual #309                // Method org/eclipse/jgit/dircache/DirCache.getEntry:(Ljava/lang/String;)Lorg/eclipse/jgit/dircache/DirCacheEntry;
     158: invokevirtual #427                // Method org/eclipse/jgit/dircache/DirCacheEntry.getObjectId:()Lorg/eclipse/jgit/lib/ObjectId;
     161: astore        4
     163: aload_0       
     164: getfield      #26                 // Field testUtils:Lorg/eclipse/egit/core/test/TestUtils;
     167: aload_1       
     168: invokevirtual #182                // Method org/eclipse/egit/core/test/TestProject.getProject:()Lorg/eclipse/core/resources/IProject;
     171: aload_1       
     172: invokevirtual #182                // Method org/eclipse/egit/core/test/TestProject.getProject:()Lorg/eclipse/core/resources/IProject;
     175: ldc_w         #362                // String folder/file.txt
     178: invokeinterface #265,  2          // InterfaceMethod org/eclipse/core/resources/IProject.getFile:(Ljava/lang/String;)Lorg/eclipse/core/resources/IFile;
     183: ldc_w         #317                // String other text
     186: invokevirtual #319                // Method org/eclipse/egit/core/test/TestUtils.changeContentOfFile:(Lorg/eclipse/core/resources/IProject;Lorg/eclipse/core/resources/IFile;Ljava/lang/String;)Lorg/eclipse/core/resources/IFile;
     189: pop           
     190: aload_1       
     191: invokevirtual #182                // Method org/eclipse/egit/core/test/TestProject.getProject:()Lorg/eclipse/core/resources/IProject;
     194: ldc_w         #368                // String folder
     197: invokeinterface #370,  2          // InterfaceMethod org/eclipse/core/resources/IProject.getFolder:(Ljava/lang/String;)Lorg/eclipse/core/resources/IFolder;
     202: aload_1       
     203: invokevirtual #182                // Method org/eclipse/egit/core/test/TestProject.getProject:()Lorg/eclipse/core/resources/IProject;
     206: ldc_w         #448                // String dir
     209: invokeinterface #370,  2          // InterfaceMethod org/eclipse/core/resources/IProject.getFolder:(Ljava/lang/String;)Lorg/eclipse/core/resources/IFolder;
     214: invokeinterface #450,  1          // InterfaceMethod org/eclipse/core/resources/IFolder.getFullPath:()Lorg/eclipse/core/runtime/IPath;
     219: iconst_0      
     220: aconst_null   
     221: invokeinterface #451,  4          // InterfaceMethod org/eclipse/core/resources/IFolder.move:(Lorg/eclipse/core/runtime/IPath;ZLorg/eclipse/core/runtime/IProgressMonitor;)V
     226: aload_3       
     227: invokevirtual #342                // Method org/eclipse/jgit/dircache/DirCache.read:()V
     230: aload_1       
     231: invokevirtual #182                // Method org/eclipse/egit/core/test/TestProject.getProject:()Lorg/eclipse/core/resources/IProject;
     234: ldc_w         #446                // String dir/file.txt
     237: invokeinterface #265,  2          // InterfaceMethod org/eclipse/core/resources/IProject.getFile:(Ljava/lang/String;)Lorg/eclipse/core/resources/IFile;
     242: invokeinterface #347,  1          // InterfaceMethod org/eclipse/core/resources/IFile.exists:()Z
     247: invokestatic  #352                // Method org/junit/Assert.assertTrue:(Z)V
     250: aload_3       
     251: ldc_w         #362                // String folder/file.txt
     254: invokevirtual #309                // Method org/eclipse/jgit/dircache/DirCache.getEntry:(Ljava/lang/String;)Lorg/eclipse/jgit/dircache/DirCacheEntry;
     257: invokestatic  #344                // Method org/junit/Assert.assertNull:(Ljava/lang/Object;)V
     260: aload_3       
     261: ldc_w         #446                // String dir/file.txt
     264: invokevirtual #309                // Method org/eclipse/jgit/dircache/DirCache.getEntry:(Ljava/lang/String;)Lorg/eclipse/jgit/dircache/DirCacheEntry;
     267: invokestatic  #313                // Method org/junit/Assert.assertNotNull:(Ljava/lang/Object;)V
     270: aload         4
     272: aload_3       
     273: ldc_w         #446                // String dir/file.txt
     276: invokevirtual #309                // Method org/eclipse/jgit/dircache/DirCache.getEntry:(Ljava/lang/String;)Lorg/eclipse/jgit/dircache/DirCacheEntry;
     279: invokevirtual #427                // Method org/eclipse/jgit/dircache/DirCacheEntry.getObjectId:()Lorg/eclipse/jgit/lib/ObjectId;
     282: invokestatic  #440                // Method org/junit/Assert.assertEquals:(Ljava/lang/Object;Ljava/lang/Object;)V
     285: aload_3       
     286: ldc_w         #364                // String folder2/file.txt
     289: invokevirtual #309                // Method org/eclipse/jgit/dircache/DirCache.getEntry:(Ljava/lang/String;)Lorg/eclipse/jgit/dircache/DirCacheEntry;
     292: invokestatic  #313                // Method org/junit/Assert.assertNotNull:(Ljava/lang/Object;)V
     295: return        

  public void testMoveAndRenameProjectContainingGitRepo() throws java.lang.Exception;
    Code:
       0: invokestatic  #69                 // Method org/eclipse/core/resources/ResourcesPlugin.getWorkspace:()Lorg/eclipse/core/resources/IWorkspace;
       3: invokeinterface #75,  1           // InterfaceMethod org/eclipse/core/resources/IWorkspace.getRoot:()Lorg/eclipse/core/resources/IWorkspaceRoot;
       8: ldc           #177                // String Project-1
      10: invokeinterface #453,  2          // InterfaceMethod org/eclipse/core/resources/IWorkspaceRoot.getProject:(Ljava/lang/String;)Lorg/eclipse/core/resources/IProject;
      15: iconst_1      
      16: aconst_null   
      17: invokeinterface #408,  3          // InterfaceMethod org/eclipse/core/resources/IProject.delete:(ZLorg/eclipse/core/runtime/IProgressMonitor;)V
      22: invokestatic  #69                 // Method org/eclipse/core/resources/ResourcesPlugin.getWorkspace:()Lorg/eclipse/core/resources/IWorkspace;
      25: invokeinterface #75,  1           // InterfaceMethod org/eclipse/core/resources/IWorkspace.getRoot:()Lorg/eclipse/core/resources/IWorkspaceRoot;
      30: ldc_w         #456                // String P2
      33: invokeinterface #453,  2          // InterfaceMethod org/eclipse/core/resources/IWorkspaceRoot.getProject:(Ljava/lang/String;)Lorg/eclipse/core/resources/IProject;
      38: iconst_1      
      39: aconst_null   
      40: invokeinterface #408,  3          // InterfaceMethod org/eclipse/core/resources/IProject.delete:(ZLorg/eclipse/core/runtime/IProgressMonitor;)V
      45: aload_0       
      46: invokespecial #251                // Method initRepoInsideProjectInsideWorkspace:()Lorg/eclipse/egit/core/test/TestProject;
      49: astore_1      
      50: aload_0       
      51: getfield      #26                 // Field testUtils:Lorg/eclipse/egit/core/test/TestUtils;
      54: aload_1       
      55: invokevirtual #182                // Method org/eclipse/egit/core/test/TestProject.getProject:()Lorg/eclipse/core/resources/IProject;
      58: ldc           #253                // String file.txt
      60: ldc           #255                // String some text
      62: invokevirtual #257                // Method org/eclipse/egit/core/test/TestUtils.addFileToProject:(Lorg/eclipse/core/resources/IProject;Ljava/lang/String;Ljava/lang/String;)Lorg/eclipse/core/resources/IFile;
      65: pop           
      66: new           #269                // class org/eclipse/egit/core/op/AddToIndexOperation
      69: dup           
      70: iconst_1      
      71: anewarray     #271                // class org/eclipse/core/resources/IResource
      74: dup           
      75: iconst_0      
      76: aload_1       
      77: invokevirtual #182                // Method org/eclipse/egit/core/test/TestProject.getProject:()Lorg/eclipse/core/resources/IProject;
      80: ldc           #253                // String file.txt
      82: invokeinterface #265,  2          // InterfaceMethod org/eclipse/core/resources/IProject.getFile:(Ljava/lang/String;)Lorg/eclipse/core/resources/IFile;
      87: aastore       
      88: invokespecial #273                // Method org/eclipse/egit/core/op/AddToIndexOperation."<init>":([Lorg/eclipse/core/resources/IResource;)V
      91: astore_2      
      92: aload_2       
      93: aconst_null   
      94: invokevirtual #276                // Method org/eclipse/egit/core/op/AddToIndexOperation.execute:(Lorg/eclipse/core/runtime/IProgressMonitor;)V
      97: aload_1       
      98: invokevirtual #182                // Method org/eclipse/egit/core/test/TestProject.getProject:()Lorg/eclipse/core/resources/IProject;
     101: invokeinterface #458,  1          // InterfaceMethod org/eclipse/core/resources/IProject.getDescription:()Lorg/eclipse/core/resources/IProjectDescription;
     106: astore_3      
     107: aload_3       
     108: ldc_w         #456                // String P2
     111: invokeinterface #462,  2          // InterfaceMethod org/eclipse/core/resources/IProjectDescription.setName:(Ljava/lang/String;)V
     116: aload_0       
     117: ldc_w         #456                // String P2
     120: invokespecial #212                // Method registerWorkspaceRelativeTestDir:(Ljava/lang/String;)V
     123: aload_1       
     124: invokevirtual #182                // Method org/eclipse/egit/core/test/TestProject.getProject:()Lorg/eclipse/core/resources/IProject;
     127: aload_3       
     128: bipush        33
     130: aconst_null   
     131: invokeinterface #467,  4          // InterfaceMethod org/eclipse/core/resources/IProject.move:(Lorg/eclipse/core/resources/IProjectDescription;ILorg/eclipse/core/runtime/IProgressMonitor;)V
     136: invokestatic  #69                 // Method org/eclipse/core/resources/ResourcesPlugin.getWorkspace:()Lorg/eclipse/core/resources/IWorkspace;
     139: invokeinterface #75,  1           // InterfaceMethod org/eclipse/core/resources/IWorkspace.getRoot:()Lorg/eclipse/core/resources/IWorkspaceRoot;
     144: ldc_w         #456                // String P2
     147: invokeinterface #453,  2          // InterfaceMethod org/eclipse/core/resources/IWorkspaceRoot.getProject:(Ljava/lang/String;)Lorg/eclipse/core/resources/IProject;
     152: astore        4
     154: aload         4
     156: invokeinterface #470,  1          // InterfaceMethod org/eclipse/core/resources/IProject.getProject:()Lorg/eclipse/core/resources/IProject;
     161: invokestatic  #384                // Method org/eclipse/egit/core/project/RepositoryMapping.getMapping:(Lorg/eclipse/core/resources/IProject;)Lorg/eclipse/egit/core/project/RepositoryMapping;
     164: invokestatic  #313                // Method org/junit/Assert.assertNotNull:(Ljava/lang/Object;)V
     167: aload         4
     169: invokestatic  #384                // Method org/eclipse/egit/core/project/RepositoryMapping.getMapping:(Lorg/eclipse/core/resources/IProject;)Lorg/eclipse/egit/core/project/RepositoryMapping;
     172: invokevirtual #471                // Method org/eclipse/egit/core/project/RepositoryMapping.getRepository:()Lorg/eclipse/jgit/lib/Repository;
     175: astore        5
     177: ldc_w         #456                // String P2
     180: aload         5
     182: invokevirtual #472                // Method org/eclipse/jgit/lib/Repository.getDirectory:()Ljava/io/File;
     185: invokevirtual #93                 // Method java/io/File.getParentFile:()Ljava/io/File;
     188: invokevirtual #475                // Method java/io/File.getName:()Ljava/lang/String;
     191: invokestatic  #440                // Method org/junit/Assert.assertEquals:(Ljava/lang/Object;Ljava/lang/Object;)V
     194: aload         5
     196: invokevirtual #478                // Method org/eclipse/jgit/lib/Repository.readDirCache:()Lorg/eclipse/jgit/dircache/DirCache;
     199: astore        6
     201: lconst_1      
     202: aload         6
     204: invokevirtual #299                // Method org/eclipse/jgit/dircache/DirCache.getEntryCount:()I
     207: i2l           
     208: invokestatic  #303                // Method org/junit/Assert.assertEquals:(JJ)V
     211: ldc           #253                // String file.txt
     213: aload         6
     215: iconst_0      
     216: invokevirtual #482                // Method org/eclipse/jgit/dircache/DirCache.getEntry:(I)Lorg/eclipse/jgit/dircache/DirCacheEntry;
     219: invokevirtual #485                // Method org/eclipse/jgit/dircache/DirCacheEntry.getPathString:()Ljava/lang/String;
     222: invokestatic  #440                // Method org/junit/Assert.assertEquals:(Ljava/lang/Object;Ljava/lang/Object;)V
     225: invokestatic  #69                 // Method org/eclipse/core/resources/ResourcesPlugin.getWorkspace:()Lorg/eclipse/core/resources/IWorkspace;
     228: invokeinterface #75,  1           // InterfaceMethod org/eclipse/core/resources/IWorkspace.getRoot:()Lorg/eclipse/core/resources/IWorkspaceRoot;
     233: ldc           #177                // String Project-1
     235: invokeinterface #453,  2          // InterfaceMethod org/eclipse/core/resources/IWorkspaceRoot.getProject:(Ljava/lang/String;)Lorg/eclipse/core/resources/IProject;
     240: invokeinterface #488,  1          // InterfaceMethod org/eclipse/core/resources/IProject.exists:()Z
     245: invokestatic  #348                // Method org/junit/Assert.assertFalse:(Z)V
     248: return        

  public void testRenameProjectOutsideWorkspaceContainingGitRepo() throws java.lang.Exception;
    Code:
       0: invokestatic  #69                 // Method org/eclipse/core/resources/ResourcesPlugin.getWorkspace:()Lorg/eclipse/core/resources/IWorkspace;
       3: invokeinterface #75,  1           // InterfaceMethod org/eclipse/core/resources/IWorkspace.getRoot:()Lorg/eclipse/core/resources/IWorkspaceRoot;
       8: ldc           #177                // String Project-1
      10: invokeinterface #453,  2          // InterfaceMethod org/eclipse/core/resources/IWorkspaceRoot.getProject:(Ljava/lang/String;)Lorg/eclipse/core/resources/IProject;
      15: iconst_1      
      16: aconst_null   
      17: invokeinterface #408,  3          // InterfaceMethod org/eclipse/core/resources/IProject.delete:(ZLorg/eclipse/core/runtime/IProgressMonitor;)V
      22: invokestatic  #69                 // Method org/eclipse/core/resources/ResourcesPlugin.getWorkspace:()Lorg/eclipse/core/resources/IWorkspace;
      25: invokeinterface #75,  1           // InterfaceMethod org/eclipse/core/resources/IWorkspace.getRoot:()Lorg/eclipse/core/resources/IWorkspaceRoot;
      30: ldc_w         #456                // String P2
      33: invokeinterface #453,  2          // InterfaceMethod org/eclipse/core/resources/IWorkspaceRoot.getProject:(Ljava/lang/String;)Lorg/eclipse/core/resources/IProject;
      38: iconst_1      
      39: aconst_null   
      40: invokeinterface #408,  3          // InterfaceMethod org/eclipse/core/resources/IProject.delete:(ZLorg/eclipse/core/runtime/IProgressMonitor;)V
      45: aload_0       
      46: invokespecial #496                // Method initRepoInsideProjectOutsideWorkspace:()Lorg/eclipse/egit/core/test/TestProject;
      49: astore_1      
      50: aload_0       
      51: getfield      #26                 // Field testUtils:Lorg/eclipse/egit/core/test/TestUtils;
      54: aload_1       
      55: invokevirtual #182                // Method org/eclipse/egit/core/test/TestProject.getProject:()Lorg/eclipse/core/resources/IProject;
      58: ldc           #253                // String file.txt
      60: ldc           #255                // String some text
      62: invokevirtual #257                // Method org/eclipse/egit/core/test/TestUtils.addFileToProject:(Lorg/eclipse/core/resources/IProject;Ljava/lang/String;Ljava/lang/String;)Lorg/eclipse/core/resources/IFile;
      65: pop           
      66: new           #269                // class org/eclipse/egit/core/op/AddToIndexOperation
      69: dup           
      70: iconst_1      
      71: anewarray     #271                // class org/eclipse/core/resources/IResource
      74: dup           
      75: iconst_0      
      76: aload_1       
      77: invokevirtual #182                // Method org/eclipse/egit/core/test/TestProject.getProject:()Lorg/eclipse/core/resources/IProject;
      80: ldc           #253                // String file.txt
      82: invokeinterface #265,  2          // InterfaceMethod org/eclipse/core/resources/IProject.getFile:(Ljava/lang/String;)Lorg/eclipse/core/resources/IFile;
      87: aastore       
      88: invokespecial #273                // Method org/eclipse/egit/core/op/AddToIndexOperation."<init>":([Lorg/eclipse/core/resources/IResource;)V
      91: astore_2      
      92: aload_2       
      93: aconst_null   
      94: invokevirtual #276                // Method org/eclipse/egit/core/op/AddToIndexOperation.execute:(Lorg/eclipse/core/runtime/IProgressMonitor;)V
      97: aload_1       
      98: invokevirtual #182                // Method org/eclipse/egit/core/test/TestProject.getProject:()Lorg/eclipse/core/resources/IProject;
     101: invokeinterface #458,  1          // InterfaceMethod org/eclipse/core/resources/IProject.getDescription:()Lorg/eclipse/core/resources/IProjectDescription;
     106: astore_3      
     107: aload_3       
     108: ldc_w         #456                // String P2
     111: invokeinterface #462,  2          // InterfaceMethod org/eclipse/core/resources/IProjectDescription.setName:(Ljava/lang/String;)V
     116: aload_1       
     117: invokevirtual #182                // Method org/eclipse/egit/core/test/TestProject.getProject:()Lorg/eclipse/core/resources/IProject;
     120: aload_3       
     121: bipush        33
     123: aconst_null   
     124: invokeinterface #467,  4          // InterfaceMethod org/eclipse/core/resources/IProject.move:(Lorg/eclipse/core/resources/IProjectDescription;ILorg/eclipse/core/runtime/IProgressMonitor;)V
     129: invokestatic  #69                 // Method org/eclipse/core/resources/ResourcesPlugin.getWorkspace:()Lorg/eclipse/core/resources/IWorkspace;
     132: invokeinterface #75,  1           // InterfaceMethod org/eclipse/core/resources/IWorkspace.getRoot:()Lorg/eclipse/core/resources/IWorkspaceRoot;
     137: ldc_w         #456                // String P2
     140: invokeinterface #453,  2          // InterfaceMethod org/eclipse/core/resources/IWorkspaceRoot.getProject:(Ljava/lang/String;)Lorg/eclipse/core/resources/IProject;
     145: astore        4
     147: aload         4
     149: invokeinterface #470,  1          // InterfaceMethod org/eclipse/core/resources/IProject.getProject:()Lorg/eclipse/core/resources/IProject;
     154: invokestatic  #384                // Method org/eclipse/egit/core/project/RepositoryMapping.getMapping:(Lorg/eclipse/core/resources/IProject;)Lorg/eclipse/egit/core/project/RepositoryMapping;
     157: invokestatic  #313                // Method org/junit/Assert.assertNotNull:(Ljava/lang/Object;)V
     160: aload         4
     162: invokestatic  #384                // Method org/eclipse/egit/core/project/RepositoryMapping.getMapping:(Lorg/eclipse/core/resources/IProject;)Lorg/eclipse/egit/core/project/RepositoryMapping;
     165: invokevirtual #471                // Method org/eclipse/egit/core/project/RepositoryMapping.getRepository:()Lorg/eclipse/jgit/lib/Repository;
     168: astore        5
     170: ldc           #177                // String Project-1
     172: aload         5
     174: invokevirtual #472                // Method org/eclipse/jgit/lib/Repository.getDirectory:()Ljava/io/File;
     177: invokevirtual #93                 // Method java/io/File.getParentFile:()Ljava/io/File;
     180: invokevirtual #475                // Method java/io/File.getName:()Ljava/lang/String;
     183: invokestatic  #440                // Method org/junit/Assert.assertEquals:(Ljava/lang/Object;Ljava/lang/Object;)V
     186: aload         5
     188: invokevirtual #478                // Method org/eclipse/jgit/lib/Repository.readDirCache:()Lorg/eclipse/jgit/dircache/DirCache;
     191: astore        6
     193: lconst_1      
     194: aload         6
     196: invokevirtual #299                // Method org/eclipse/jgit/dircache/DirCache.getEntryCount:()I
     199: i2l           
     200: invokestatic  #303                // Method org/junit/Assert.assertEquals:(JJ)V
     203: ldc           #253                // String file.txt
     205: aload         6
     207: iconst_0      
     208: invokevirtual #482                // Method org/eclipse/jgit/dircache/DirCache.getEntry:(I)Lorg/eclipse/jgit/dircache/DirCacheEntry;
     211: invokevirtual #485                // Method org/eclipse/jgit/dircache/DirCacheEntry.getPathString:()Ljava/lang/String;
     214: invokestatic  #440                // Method org/junit/Assert.assertEquals:(Ljava/lang/Object;Ljava/lang/Object;)V
     217: invokestatic  #69                 // Method org/eclipse/core/resources/ResourcesPlugin.getWorkspace:()Lorg/eclipse/core/resources/IWorkspace;
     220: invokeinterface #75,  1           // InterfaceMethod org/eclipse/core/resources/IWorkspace.getRoot:()Lorg/eclipse/core/resources/IWorkspaceRoot;
     225: ldc           #177                // String Project-1
     227: invokeinterface #453,  2          // InterfaceMethod org/eclipse/core/resources/IWorkspaceRoot.getProject:(Ljava/lang/String;)Lorg/eclipse/core/resources/IProject;
     232: invokeinterface #488,  1          // InterfaceMethod org/eclipse/core/resources/IProject.exists:()Z
     237: invokestatic  #348                // Method org/junit/Assert.assertFalse:(Z)V
     240: return        

  public void testMoveButDoNotRenameProjectOutsideWorkspaceContainingGitRepo() throws java.lang.Exception;
    Code:
       0: invokestatic  #69                 // Method org/eclipse/core/resources/ResourcesPlugin.getWorkspace:()Lorg/eclipse/core/resources/IWorkspace;
       3: invokeinterface #75,  1           // InterfaceMethod org/eclipse/core/resources/IWorkspace.getRoot:()Lorg/eclipse/core/resources/IWorkspaceRoot;
       8: ldc           #177                // String Project-1
      10: invokeinterface #453,  2          // InterfaceMethod org/eclipse/core/resources/IWorkspaceRoot.getProject:(Ljava/lang/String;)Lorg/eclipse/core/resources/IProject;
      15: iconst_1      
      16: aconst_null   
      17: invokeinterface #408,  3          // InterfaceMethod org/eclipse/core/resources/IProject.delete:(ZLorg/eclipse/core/runtime/IProgressMonitor;)V
      22: invokestatic  #69                 // Method org/eclipse/core/resources/ResourcesPlugin.getWorkspace:()Lorg/eclipse/core/resources/IWorkspace;
      25: invokeinterface #75,  1           // InterfaceMethod org/eclipse/core/resources/IWorkspace.getRoot:()Lorg/eclipse/core/resources/IWorkspaceRoot;
      30: ldc_w         #456                // String P2
      33: invokeinterface #453,  2          // InterfaceMethod org/eclipse/core/resources/IWorkspaceRoot.getProject:(Ljava/lang/String;)Lorg/eclipse/core/resources/IProject;
      38: iconst_1      
      39: aconst_null   
      40: invokeinterface #408,  3          // InterfaceMethod org/eclipse/core/resources/IProject.delete:(ZLorg/eclipse/core/runtime/IProgressMonitor;)V
      45: aload_0       
      46: invokespecial #496                // Method initRepoInsideProjectOutsideWorkspace:()Lorg/eclipse/egit/core/test/TestProject;
      49: astore_1      
      50: aload_0       
      51: getfield      #26                 // Field testUtils:Lorg/eclipse/egit/core/test/TestUtils;
      54: aload_1       
      55: invokevirtual #182                // Method org/eclipse/egit/core/test/TestProject.getProject:()Lorg/eclipse/core/resources/IProject;
      58: ldc           #253                // String file.txt
      60: ldc           #255                // String some text
      62: invokevirtual #257                // Method org/eclipse/egit/core/test/TestUtils.addFileToProject:(Lorg/eclipse/core/resources/IProject;Ljava/lang/String;Ljava/lang/String;)Lorg/eclipse/core/resources/IFile;
      65: pop           
      66: new           #269                // class org/eclipse/egit/core/op/AddToIndexOperation
      69: dup           
      70: iconst_1      
      71: anewarray     #271                // class org/eclipse/core/resources/IResource
      74: dup           
      75: iconst_0      
      76: aload_1       
      77: invokevirtual #182                // Method org/eclipse/egit/core/test/TestProject.getProject:()Lorg/eclipse/core/resources/IProject;
      80: ldc           #253                // String file.txt
      82: invokeinterface #265,  2          // InterfaceMethod org/eclipse/core/resources/IProject.getFile:(Ljava/lang/String;)Lorg/eclipse/core/resources/IFile;
      87: aastore       
      88: invokespecial #273                // Method org/eclipse/egit/core/op/AddToIndexOperation."<init>":([Lorg/eclipse/core/resources/IResource;)V
      91: astore_2      
      92: aload_2       
      93: aconst_null   
      94: invokevirtual #276                // Method org/eclipse/egit/core/op/AddToIndexOperation.execute:(Lorg/eclipse/core/runtime/IProgressMonitor;)V
      97: aload_1       
      98: invokevirtual #182                // Method org/eclipse/egit/core/test/TestProject.getProject:()Lorg/eclipse/core/resources/IProject;
     101: invokeinterface #458,  1          // InterfaceMethod org/eclipse/core/resources/IProject.getDescription:()Lorg/eclipse/core/resources/IProjectDescription;
     106: astore_3      
     107: aload_3       
     108: new           #499                // class org/eclipse/core/runtime/Path
     111: dup           
     112: new           #94                 // class java/io/File
     115: dup           
     116: aload_1       
     117: invokevirtual #501                // Method org/eclipse/egit/core/test/TestProject.getWorkspaceSupplement:()Ljava/io/File;
     120: ldc_w         #456                // String P2
     123: invokespecial #243                // Method java/io/File."<init>":(Ljava/io/File;Ljava/lang/String;)V
     126: invokevirtual #504                // Method java/io/File.getAbsolutePath:()Ljava/lang/String;
     129: invokespecial #507                // Method org/eclipse/core/runtime/Path."<init>":(Ljava/lang/String;)V
     132: invokestatic  #508                // Method org/eclipse/core/filesystem/URIUtil.toURI:(Lorg/eclipse/core/runtime/IPath;)Ljava/net/URI;
     135: invokeinterface #514,  2          // InterfaceMethod org/eclipse/core/resources/IProjectDescription.setLocationURI:(Ljava/net/URI;)V
     140: aload_1       
     141: invokevirtual #182                // Method org/eclipse/egit/core/test/TestProject.getProject:()Lorg/eclipse/core/resources/IProject;
     144: aload_3       
     145: bipush        33
     147: aconst_null   
     148: invokeinterface #467,  4          // InterfaceMethod org/eclipse/core/resources/IProject.move:(Lorg/eclipse/core/resources/IProjectDescription;ILorg/eclipse/core/runtime/IProgressMonitor;)V
     153: invokestatic  #69                 // Method org/eclipse/core/resources/ResourcesPlugin.getWorkspace:()Lorg/eclipse/core/resources/IWorkspace;
     156: invokeinterface #75,  1           // InterfaceMethod org/eclipse/core/resources/IWorkspace.getRoot:()Lorg/eclipse/core/resources/IWorkspaceRoot;
     161: ldc           #177                // String Project-1
     163: invokeinterface #453,  2          // InterfaceMethod org/eclipse/core/resources/IWorkspaceRoot.getProject:(Ljava/lang/String;)Lorg/eclipse/core/resources/IProject;
     168: astore        4
     170: aload         4
     172: invokeinterface #470,  1          // InterfaceMethod org/eclipse/core/resources/IProject.getProject:()Lorg/eclipse/core/resources/IProject;
     177: invokestatic  #384                // Method org/eclipse/egit/core/project/RepositoryMapping.getMapping:(Lorg/eclipse/core/resources/IProject;)Lorg/eclipse/egit/core/project/RepositoryMapping;
     180: invokestatic  #313                // Method org/junit/Assert.assertNotNull:(Ljava/lang/Object;)V
     183: aload         4
     185: invokestatic  #384                // Method org/eclipse/egit/core/project/RepositoryMapping.getMapping:(Lorg/eclipse/core/resources/IProject;)Lorg/eclipse/egit/core/project/RepositoryMapping;
     188: invokevirtual #471                // Method org/eclipse/egit/core/project/RepositoryMapping.getRepository:()Lorg/eclipse/jgit/lib/Repository;
     191: astore        5
     193: ldc_w         #456                // String P2
     196: aload         5
     198: invokevirtual #472                // Method org/eclipse/jgit/lib/Repository.getDirectory:()Ljava/io/File;
     201: invokevirtual #93                 // Method java/io/File.getParentFile:()Ljava/io/File;
     204: invokevirtual #475                // Method java/io/File.getName:()Ljava/lang/String;
     207: invokestatic  #440                // Method org/junit/Assert.assertEquals:(Ljava/lang/Object;Ljava/lang/Object;)V
     210: aload         5
     212: invokevirtual #478                // Method org/eclipse/jgit/lib/Repository.readDirCache:()Lorg/eclipse/jgit/dircache/DirCache;
     215: astore        6
     217: lconst_1      
     218: aload         6
     220: invokevirtual #299                // Method org/eclipse/jgit/dircache/DirCache.getEntryCount:()I
     223: i2l           
     224: invokestatic  #303                // Method org/junit/Assert.assertEquals:(JJ)V
     227: ldc           #253                // String file.txt
     229: aload         6
     231: iconst_0      
     232: invokevirtual #482                // Method org/eclipse/jgit/dircache/DirCache.getEntry:(I)Lorg/eclipse/jgit/dircache/DirCacheEntry;
     235: invokevirtual #485                // Method org/eclipse/jgit/dircache/DirCacheEntry.getPathString:()Ljava/lang/String;
     238: invokestatic  #440                // Method org/junit/Assert.assertEquals:(Ljava/lang/Object;Ljava/lang/Object;)V
     241: invokestatic  #69                 // Method org/eclipse/core/resources/ResourcesPlugin.getWorkspace:()Lorg/eclipse/core/resources/IWorkspace;
     244: invokeinterface #75,  1           // InterfaceMethod org/eclipse/core/resources/IWorkspace.getRoot:()Lorg/eclipse/core/resources/IWorkspaceRoot;
     249: ldc_w         #456                // String P2
     252: invokeinterface #453,  2          // InterfaceMethod org/eclipse/core/resources/IWorkspaceRoot.getProject:(Ljava/lang/String;)Lorg/eclipse/core/resources/IProject;
     257: invokeinterface #488,  1          // InterfaceMethod org/eclipse/core/resources/IProject.exists:()Z
     262: invokestatic  #348                // Method org/junit/Assert.assertFalse:(Z)V
     265: return        

  public void testMoveProjectWithinGitRepoMoveAtSameTopLevel() throws java.lang.Exception;
    Code:
       0: aload_0       
       1: ldc_w         #380                // String 
       4: ldc           #177                // String Project-1
       6: ldc_w         #380                // String 
       9: ldc_w         #456                // String P2
      12: ldc_w         #380                // String 
      15: invokespecial #519                // Method dotestMoveProjectWithinRepoWithinWorkspace:(Ljava/lang/String;Ljava/lang/String;Ljava/lang/String;Ljava/lang/String;Ljava/lang/String;)V
      18: return        

  public void testMoveProjectWithinGitRepoMoveFromTopOneLevelDown() throws java.lang.Exception;
    Code:
       0: aload_0       
       1: ldc_w         #380                // String 
       4: ldc           #177                // String Project-1
       6: ldc_w         #524                // String X/
       9: ldc_w         #456                // String P2
      12: ldc_w         #380                // String 
      15: invokespecial #519                // Method dotestMoveProjectWithinRepoWithinWorkspace:(Ljava/lang/String;Ljava/lang/String;Ljava/lang/String;Ljava/lang/String;Ljava/lang/String;)V
      18: return        

  public void testMoveProjectWithinGitRepoMoveFromOneLevelDownToTop() throws java.lang.Exception;
    Code:
       0: aload_0       
       1: ldc_w         #378                // String P/
       4: ldc           #177                // String Project-1
       6: ldc_w         #380                // String 
       9: ldc_w         #456                // String P2
      12: ldc_w         #380                // String 
      15: invokespecial #519                // Method dotestMoveProjectWithinRepoWithinWorkspace:(Ljava/lang/String;Ljava/lang/String;Ljava/lang/String;Ljava/lang/String;Ljava/lang/String;)V
      18: return        

  public void testMoveProjectWithinGitRepoMoveFromOneLevelDownToSameDepth() throws java.lang.Exception;
    Code:
       0: aload_0       
       1: ldc_w         #378                // String P/
       4: ldc           #177                // String Project-1
       6: ldc_w         #524                // String X/
       9: ldc_w         #456                // String P2
      12: ldc_w         #380                // String 
      15: invokespecial #519                // Method dotestMoveProjectWithinRepoWithinWorkspace:(Ljava/lang/String;Ljava/lang/String;Ljava/lang/String;Ljava/lang/String;Ljava/lang/String;)V
      18: return        

  public void testMoveProjectWithinGitRepoMoveFromOneLevelDownOutsideTheRepo() throws java.lang.Exception;
    Code:
       0: aload_0       
       1: ldc_w         #378                // String P/
       4: ldc           #177                // String Project-1
       6: ldc_w         #378                // String P/
       9: ldc_w         #456                // String P2
      12: ldc_w         #378                // String P/
      15: invokespecial #519                // Method dotestMoveProjectWithinRepoWithinWorkspace:(Ljava/lang/String;Ljava/lang/String;Ljava/lang/String;Ljava/lang/String;Ljava/lang/String;)V
      18: return        

  public void testMoveProjectWithinGitOutsideWorkspaceRepoMoveAtSameTopLevel() throws java.lang.Exception;
    Code:
       0: aload_0       
       1: ldc_w         #380                // String 
       4: ldc           #177                // String Project-1
       6: ldc_w         #380                // String 
       9: ldc_w         #456                // String P2
      12: ldc_w         #380                // String 
      15: invokespecial #530                // Method dotestMoveProjectWithinRepoOutsideWorkspace:(Ljava/lang/String;Ljava/lang/String;Ljava/lang/String;Ljava/lang/String;Ljava/lang/String;)V
      18: return        

  public void testMoveProjectWithinGitOutsideWorkspaceRepoMoveFromTopOneLevelDown() throws java.lang.Exception;
    Code:
       0: aload_0       
       1: ldc_w         #380                // String 
       4: ldc           #177                // String Project-1
       6: ldc_w         #524                // String X/
       9: ldc_w         #456                // String P2
      12: ldc_w         #380                // String 
      15: invokespecial #530                // Method dotestMoveProjectWithinRepoOutsideWorkspace:(Ljava/lang/String;Ljava/lang/String;Ljava/lang/String;Ljava/lang/String;Ljava/lang/String;)V
      18: return        

  public void testMoveProjectWithinGitOutsideWorkspaceRepoMoveFromOneLevelDownToTop() throws java.lang.Exception;
    Code:
       0: aload_0       
       1: ldc_w         #378                // String P/
       4: ldc           #177                // String Project-1
       6: ldc_w         #380                // String 
       9: ldc_w         #456                // String P2
      12: ldc_w         #380                // String 
      15: invokespecial #530                // Method dotestMoveProjectWithinRepoOutsideWorkspace:(Ljava/lang/String;Ljava/lang/String;Ljava/lang/String;Ljava/lang/String;Ljava/lang/String;)V
      18: return        

  public void testMoveProjectWithinGitOutsideWorkspaceRepoMoveFromOneLevelDownToSameDepth() throws java.lang.Exception;
    Code:
       0: aload_0       
       1: ldc_w         #378                // String P/
       4: ldc           #177                // String Project-1
       6: ldc_w         #524                // String X/
       9: ldc_w         #456                // String P2
      12: ldc_w         #380                // String 
      15: invokespecial #530                // Method dotestMoveProjectWithinRepoOutsideWorkspace:(Ljava/lang/String;Ljava/lang/String;Ljava/lang/String;Ljava/lang/String;Ljava/lang/String;)V
      18: return        

  public void testMoveProjectWithinGitOutsideWorkspaceRepoMoveFromOneLevelDownOutsideTheRepo() throws java.lang.Exception;
    Code:
       0: aload_0       
       1: ldc_w         #378                // String P/
       4: ldc           #177                // String Project-1
       6: ldc_w         #378                // String P/
       9: ldc_w         #456                // String P2
      12: ldc_w         #378                // String P/
      15: invokespecial #530                // Method dotestMoveProjectWithinRepoOutsideWorkspace:(Ljava/lang/String;Ljava/lang/String;Ljava/lang/String;Ljava/lang/String;Ljava/lang/String;)V
      18: return        

  public void testMoveProjectWithinGitRepoMoveFromLevelZeroDownOne() throws java.lang.Exception;
    Code:
       0: aload_0       
       1: ldc_w         #378                // String P/
       4: ldc           #177                // String Project-1
       6: ldc_w         #538                // String P/Project-1/
       9: ldc_w         #456                // String P2
      12: ldc_w         #538                // String P/Project-1/
      15: invokespecial #519                // Method dotestMoveProjectWithinRepoWithinWorkspace:(Ljava/lang/String;Ljava/lang/String;Ljava/lang/String;Ljava/lang/String;Ljava/lang/String;)V
      18: ldc_w         #540                // String true
      21: ldc_w         #542                // String egit.assume_307140_fixed
      24: invokestatic  #544                // Method java/lang/System.getProperty:(Ljava/lang/String;)Ljava/lang/String;
      27: invokevirtual #550                // Method java/lang/String.equals:(Ljava/lang/Object;)Z
      30: ifne          60
      33: ldc_w         #553                // String ResourceException expected, core functionality dangerously broken and therefore forbidden
      36: invokestatic  #555                // Method org/junit/Assert.fail:(Ljava/lang/String;)V
      39: goto          60
      42: astore_1      
      43: ldc_w         #540                // String true
      46: ldc_w         #542                // String egit.assume_307140_fixed
      49: invokestatic  #544                // Method java/lang/System.getProperty:(Ljava/lang/String;)Ljava/lang/String;
      52: invokevirtual #550                // Method java/lang/String.equals:(Ljava/lang/Object;)Z
      55: ifeq          60
      58: aload_1       
      59: athrow        
      60: return        
    Exception table:
       from    to  target type
           0    39    42   Class org/eclipse/core/runtime/CoreException

  public void testMoveFileWithConflictsShouldBeCanceled() throws java.lang.Exception;
    Code:
       0: aload_0       
       1: invokespecial #251                // Method initRepoInsideProjectInsideWorkspace:()Lorg/eclipse/egit/core/test/TestProject;
       4: astore_1      
       5: ldc           #253                // String file.txt
       7: astore_2      
       8: aload_0       
       9: getfield      #26                 // Field testUtils:Lorg/eclipse/egit/core/test/TestUtils;
      12: aload_1       
      13: invokevirtual #182                // Method org/eclipse/egit/core/test/TestProject.getProject:()Lorg/eclipse/core/resources/IProject;
      16: aload_2       
      17: ldc           #255                // String some text
      19: invokevirtual #257                // Method org/eclipse/egit/core/test/TestUtils.addFileToProject:(Lorg/eclipse/core/resources/IProject;Ljava/lang/String;Ljava/lang/String;)Lorg/eclipse/core/resources/IFile;
      22: astore_3      
      23: aload_0       
      24: getfield      #140                // Field testRepository:Lorg/eclipse/egit/core/test/TestRepository;
      27: invokevirtual #204                // Method org/eclipse/egit/core/test/TestRepository.getRepository:()Lorg/eclipse/jgit/lib/Repository;
      30: astore        4
      32: aload         4
      34: invokevirtual #561                // Method org/eclipse/jgit/lib/Repository.lockDirCache:()Lorg/eclipse/jgit/dircache/DirCache;
      37: astore        5
      39: aload         5
      41: invokevirtual #564                // Method org/eclipse/jgit/dircache/DirCache.builder:()Lorg/eclipse/jgit/dircache/DirCacheBuilder;
      44: astore        6
      46: aload_2       
      47: aload         6
      49: invokestatic  #568                // Method addUnmergedEntry:(Ljava/lang/String;Lorg/eclipse/jgit/dircache/DirCacheBuilder;)V
      52: aload         6
      54: invokevirtual #572                // Method org/eclipse/jgit/dircache/DirCacheBuilder.commit:()Z
      57: pop           
      58: aload_3       
      59: new           #499                // class org/eclipse/core/runtime/Path
      62: dup           
      63: ldc_w         #577                // String destination.txt
      66: invokespecial #507                // Method org/eclipse/core/runtime/Path."<init>":(Ljava/lang/String;)V
      69: iconst_0      
      70: aconst_null   
      71: invokeinterface #436,  4          // InterfaceMethod org/eclipse/core/resources/IFile.move:(Lorg/eclipse/core/runtime/IPath;ZLorg/eclipse/core/runtime/IProgressMonitor;)V
      76: ldc_w         #579                // String Expected move of file with conflicts to fail.
      79: invokestatic  #555                // Method org/junit/Assert.fail:(Ljava/lang/String;)V
      82: goto          113
      85: astore        7
      87: aload         7
      89: invokevirtual #581                // Method org/eclipse/core/runtime/CoreException.getStatus:()Lorg/eclipse/core/runtime/IStatus;
      92: astore        8
      94: aload         8
      96: invokestatic  #313                // Method org/junit/Assert.assertNotNull:(Ljava/lang/Object;)V
      99: ldc2_w        #297                // long 2l
     102: aload         8
     104: invokeinterface #585,  1          // InterfaceMethod org/eclipse/core/runtime/IStatus.getSeverity:()I
     109: i2l           
     110: invokestatic  #303                // Method org/junit/Assert.assertEquals:(JJ)V
     113: ldc_w         #590                // String File should still exist at old location
     116: aload_3       
     117: invokeinterface #347,  1          // InterfaceMethod org/eclipse/core/resources/IFile.exists:()Z
     122: invokestatic  #415                // Method org/junit/Assert.assertTrue:(Ljava/lang/String;Z)V
     125: aload         4
     127: invokevirtual #478                // Method org/eclipse/jgit/lib/Repository.readDirCache:()Lorg/eclipse/jgit/dircache/DirCache;
     130: astore        7
     132: aload         7
     134: aload_2       
     135: invokevirtual #309                // Method org/eclipse/jgit/dircache/DirCache.getEntry:(Ljava/lang/String;)Lorg/eclipse/jgit/dircache/DirCacheEntry;
     138: astore        8
     140: ldc_w         #592                // String Expected entry to still be in non-zero (conflict) stage
     143: lconst_1      
     144: aload         8
     146: invokevirtual #594                // Method org/eclipse/jgit/dircache/DirCacheEntry.getStage:()I
     149: i2l           
     150: invokestatic  #597                // Method org/junit/Assert.assertEquals:(Ljava/lang/String;JJ)V
     153: return        
    Exception table:
       from    to  target type
          58    82    85   Class org/eclipse/core/runtime/CoreException

  public void testMoveFolderWithFileWithConflictsShouldBeCanceled() throws java.lang.Exception;
    Code:
       0: aload_0       
       1: invokespecial #251                // Method initRepoInsideProjectInsideWorkspace:()Lorg/eclipse/egit/core/test/TestProject;
       4: astore_1      
       5: ldc_w         #362                // String folder/file.txt
       8: astore_2      
       9: aload_0       
      10: getfield      #26                 // Field testUtils:Lorg/eclipse/egit/core/test/TestUtils;
      13: aload_1       
      14: invokevirtual #182                // Method org/eclipse/egit/core/test/TestProject.getProject:()Lorg/eclipse/core/resources/IProject;
      17: aload_2       
      18: ldc           #255                // String some text
      20: invokevirtual #257                // Method org/eclipse/egit/core/test/TestUtils.addFileToProject:(Lorg/eclipse/core/resources/IProject;Ljava/lang/String;Ljava/lang/String;)Lorg/eclipse/core/resources/IFile;
      23: astore_3      
      24: aload_0       
      25: getfield      #140                // Field testRepository:Lorg/eclipse/egit/core/test/TestRepository;
      28: invokevirtual #204                // Method org/eclipse/egit/core/test/TestRepository.getRepository:()Lorg/eclipse/jgit/lib/Repository;
      31: astore        4
      33: aload         4
      35: invokevirtual #561                // Method org/eclipse/jgit/lib/Repository.lockDirCache:()Lorg/eclipse/jgit/dircache/DirCache;
      38: astore        5
      40: aload         5
      42: invokevirtual #564                // Method org/eclipse/jgit/dircache/DirCache.builder:()Lorg/eclipse/jgit/dircache/DirCacheBuilder;
      45: astore        6
      47: aload_2       
      48: aload         6
      50: invokestatic  #568                // Method addUnmergedEntry:(Ljava/lang/String;Lorg/eclipse/jgit/dircache/DirCacheBuilder;)V
      53: aload         6
      55: invokevirtual #572                // Method org/eclipse/jgit/dircache/DirCacheBuilder.commit:()Z
      58: pop           
      59: aload_1       
      60: invokevirtual #182                // Method org/eclipse/egit/core/test/TestProject.getProject:()Lorg/eclipse/core/resources/IProject;
      63: ldc_w         #368                // String folder
      66: invokeinterface #370,  2          // InterfaceMethod org/eclipse/core/resources/IProject.getFolder:(Ljava/lang/String;)Lorg/eclipse/core/resources/IFolder;
      71: aload_1       
      72: invokevirtual #182                // Method org/eclipse/egit/core/test/TestProject.getProject:()Lorg/eclipse/core/resources/IProject;
      75: ldc_w         #609                // String newfolder
      78: invokeinterface #370,  2          // InterfaceMethod org/eclipse/core/resources/IProject.getFolder:(Ljava/lang/String;)Lorg/eclipse/core/resources/IFolder;
      83: invokeinterface #450,  1          // InterfaceMethod org/eclipse/core/resources/IFolder.getFullPath:()Lorg/eclipse/core/runtime/IPath;
      88: iconst_0      
      89: aconst_null   
      90: invokeinterface #451,  4          // InterfaceMethod org/eclipse/core/resources/IFolder.move:(Lorg/eclipse/core/runtime/IPath;ZLorg/eclipse/core/runtime/IProgressMonitor;)V
      95: ldc_w         #611                // String Expected move of folder with file with conflicts to fail.
      98: invokestatic  #555                // Method org/junit/Assert.fail:(Ljava/lang/String;)V
     101: goto          132
     104: astore        7
     106: aload         7
     108: invokevirtual #581                // Method org/eclipse/core/runtime/CoreException.getStatus:()Lorg/eclipse/core/runtime/IStatus;
     111: astore        8
     113: aload         8
     115: invokestatic  #313                // Method org/junit/Assert.assertNotNull:(Ljava/lang/Object;)V
     118: ldc2_w        #297                // long 2l
     121: aload         8
     123: invokeinterface #585,  1          // InterfaceMethod org/eclipse/core/runtime/IStatus.getSeverity:()I
     128: i2l           
     129: invokestatic  #303                // Method org/junit/Assert.assertEquals:(JJ)V
     132: ldc_w         #590                // String File should still exist at old location
     135: aload_3       
     136: invokeinterface #347,  1          // InterfaceMethod org/eclipse/core/resources/IFile.exists:()Z
     141: invokestatic  #415                // Method org/junit/Assert.assertTrue:(Ljava/lang/String;Z)V
     144: aload         4
     146: invokevirtual #478                // Method org/eclipse/jgit/lib/Repository.readDirCache:()Lorg/eclipse/jgit/dircache/DirCache;
     149: astore        7
     151: aload         7
     153: aload_2       
     154: invokevirtual #309                // Method org/eclipse/jgit/dircache/DirCache.getEntry:(Ljava/lang/String;)Lorg/eclipse/jgit/dircache/DirCacheEntry;
     157: astore        8
     159: ldc_w         #592                // String Expected entry to still be in non-zero (conflict) stage
     162: lconst_1      
     163: aload         8
     165: invokevirtual #594                // Method org/eclipse/jgit/dircache/DirCacheEntry.getStage:()I
     168: i2l           
     169: invokestatic  #597                // Method org/junit/Assert.assertEquals:(Ljava/lang/String;JJ)V
     172: return        
    Exception table:
       from    to  target type
          59   101   104   Class org/eclipse/core/runtime/CoreException

  private static void addUnmergedEntry(java.lang.String, org.eclipse.jgit.dircache.DirCacheBuilder);
    Code:
       0: new           #428                // class org/eclipse/jgit/dircache/DirCacheEntry
       3: dup           
       4: aload_0       
       5: iconst_1      
       6: invokespecial #613                // Method org/eclipse/jgit/dircache/DirCacheEntry."<init>":(Ljava/lang/String;I)V
       9: astore_2      
      10: new           #428                // class org/eclipse/jgit/dircache/DirCacheEntry
      13: dup           
      14: aload_0       
      15: iconst_2      
      16: invokespecial #613                // Method org/eclipse/jgit/dircache/DirCacheEntry."<init>":(Ljava/lang/String;I)V
      19: astore_3      
      20: new           #428                // class org/eclipse/jgit/dircache/DirCacheEntry
      23: dup           
      24: aload_0       
      25: iconst_3      
      26: invokespecial #613                // Method org/eclipse/jgit/dircache/DirCacheEntry."<init>":(Ljava/lang/String;I)V
      29: astore        4
      31: aload_2       
      32: getstatic     #616                // Field org/eclipse/jgit/lib/FileMode.REGULAR_FILE:Lorg/eclipse/jgit/lib/FileMode;
      35: invokevirtual #622                // Method org/eclipse/jgit/dircache/DirCacheEntry.setFileMode:(Lorg/eclipse/jgit/lib/FileMode;)V
      38: aload_3       
      39: getstatic     #616                // Field org/eclipse/jgit/lib/FileMode.REGULAR_FILE:Lorg/eclipse/jgit/lib/FileMode;
      42: invokevirtual #622                // Method org/eclipse/jgit/dircache/DirCacheEntry.setFileMode:(Lorg/eclipse/jgit/lib/FileMode;)V
      45: aload         4
      47: getstatic     #616                // Field org/eclipse/jgit/lib/FileMode.REGULAR_FILE:Lorg/eclipse/jgit/lib/FileMode;
      50: invokevirtual #622                // Method org/eclipse/jgit/dircache/DirCacheEntry.setFileMode:(Lorg/eclipse/jgit/lib/FileMode;)V
      53: aload_1       
      54: aload_2       
      55: invokevirtual #626                // Method org/eclipse/jgit/dircache/DirCacheBuilder.add:(Lorg/eclipse/jgit/dircache/DirCacheEntry;)V
      58: aload_1       
      59: aload_3       
      60: invokevirtual #626                // Method org/eclipse/jgit/dircache/DirCacheBuilder.add:(Lorg/eclipse/jgit/dircache/DirCacheEntry;)V
      63: aload_1       
      64: aload         4
      66: invokevirtual #626                // Method org/eclipse/jgit/dircache/DirCacheBuilder.add:(Lorg/eclipse/jgit/dircache/DirCacheEntry;)V
      69: return        

  private void dotestMoveProjectWithinRepoWithinWorkspace(java.lang.String, java.lang.String, java.lang.String, java.lang.String, java.lang.String) throws org.eclipse.core.runtime.CoreException, java.io.IOException, java.lang.Exception, org.eclipse.jgit.errors.CorruptObjectException;
    Code:
       0: aload_0       
       1: aload_1       
       2: aload_2       
       3: aload_3       
       4: aload         4
       6: aload         5
       8: iconst_1      
       9: invokespecial #634                // Method dotestMoveProjectWithinRepo:(Ljava/lang/String;Ljava/lang/String;Ljava/lang/String;Ljava/lang/String;Ljava/lang/String;Z)V
      12: return        

  private void dotestMoveProjectWithinRepoOutsideWorkspace(java.lang.String, java.lang.String, java.lang.String, java.lang.String, java.lang.String) throws org.eclipse.core.runtime.CoreException, java.io.IOException, java.lang.Exception, org.eclipse.jgit.errors.CorruptObjectException;
    Code:
       0: aload_0       
       1: aload_1       
       2: aload_2       
       3: aload_3       
       4: aload         4
       6: aload         5
       8: iconst_0      
       9: invokespecial #634                // Method dotestMoveProjectWithinRepo:(Ljava/lang/String;Ljava/lang/String;Ljava/lang/String;Ljava/lang/String;Ljava/lang/String;Z)V
      12: return        

  private void dotestMoveProjectWithinRepo(java.lang.String, java.lang.String, java.lang.String, java.lang.String, java.lang.String, boolean) throws java.io.IOException, org.eclipse.core.runtime.CoreException;
    Code:
       0: new           #228                // class java/lang/StringBuilder
       3: dup           
       4: aload_1       
       5: invokestatic  #230                // Method java/lang/String.valueOf:(Ljava/lang/Object;)Ljava/lang/String;
       8: invokespecial #236                // Method java/lang/StringBuilder."<init>":(Ljava/lang/String;)V
      11: aload_2       
      12: invokevirtual #238                // Method java/lang/StringBuilder.append:(Ljava/lang/String;)Ljava/lang/StringBuilder;
      15: ldc_w         #641                // String /
      18: invokevirtual #238                // Method java/lang/StringBuilder.append:(Ljava/lang/String;)Ljava/lang/StringBuilder;
      21: invokevirtual #242                // Method java/lang/StringBuilder.toString:()Ljava/lang/String;
      24: astore        7
      26: aload         7
      28: aload         5
      30: invokevirtual #643                // Method java/lang/String.startsWith:(Ljava/lang/String;)Z
      33: ifeq          48
      36: aload         7
      38: aload         5
      40: invokevirtual #647                // Method java/lang/String.length:()I
      43: invokevirtual #650                // Method java/lang/String.substring:(I)Ljava/lang/String;
      46: astore        7
      48: aload_0       
      49: getfield      #31                 // Field testDirs:Ljava/util/Set;
      52: new           #94                 // class java/io/File
      55: dup           
      56: aload_3       
      57: invokespecial #654                // Method java/io/File."<init>":(Ljava/lang/String;)V
      60: invokeinterface #120,  2          // InterfaceMethod java/util/Set.add:(Ljava/lang/Object;)Z
      65: pop           
      66: new           #228                // class java/lang/StringBuilder
      69: dup           
      70: aload_3       
      71: invokestatic  #230                // Method java/lang/String.valueOf:(Ljava/lang/Object;)Ljava/lang/String;
      74: invokespecial #236                // Method java/lang/StringBuilder."<init>":(Ljava/lang/String;)V
      77: aload         4
      79: invokevirtual #238                // Method java/lang/StringBuilder.append:(Ljava/lang/String;)Ljava/lang/StringBuilder;
      82: ldc_w         #641                // String /
      85: invokevirtual #238                // Method java/lang/StringBuilder.append:(Ljava/lang/String;)Ljava/lang/StringBuilder;
      88: invokevirtual #242                // Method java/lang/StringBuilder.toString:()Ljava/lang/String;
      91: astore        8
      93: aload         8
      95: aload         5
      97: invokevirtual #643                // Method java/lang/String.startsWith:(Ljava/lang/String;)Z
     100: ifeq          115
     103: aload         8
     105: aload         5
     107: invokevirtual #647                // Method java/lang/String.length:()I
     110: invokevirtual #650                // Method java/lang/String.substring:(I)Ljava/lang/String;
     113: astore        8
     115: aload_0       
     116: aload_1       
     117: aload_2       
     118: invokespecial #655                // Method registerWorkspaceRelativeTestDirProject:(Ljava/lang/String;Ljava/lang/String;)V
     121: aload_0       
     122: aload_3       
     123: aload         4
     125: invokespecial #655                // Method registerWorkspaceRelativeTestDirProject:(Ljava/lang/String;Ljava/lang/String;)V
     128: aload_0       
     129: aload_1       
     130: aload         5
     132: iload         6
     134: invokespecial #222                // Method initRepoAboveProject:(Ljava/lang/String;Ljava/lang/String;Z)Lorg/eclipse/egit/core/test/TestProject;
     137: astore        9
     139: aload         9
     141: invokevirtual #182                // Method org/eclipse/egit/core/test/TestProject.getProject:()Lorg/eclipse/core/resources/IProject;
     144: invokeinterface #658,  1          // InterfaceMethod org/eclipse/core/resources/IProject.getWorkspace:()Lorg/eclipse/core/resources/IWorkspace;
     149: invokeinterface #75,  1           // InterfaceMethod org/eclipse/core/resources/IWorkspace.getRoot:()Lorg/eclipse/core/resources/IWorkspaceRoot;
     154: aload         4
     156: invokeinterface #453,  2          // InterfaceMethod org/eclipse/core/resources/IWorkspaceRoot.getProject:(Ljava/lang/String;)Lorg/eclipse/core/resources/IProject;
     161: astore        10
     163: aload         10
     165: iconst_1      
     166: aconst_null   
     167: invokeinterface #408,  3          // InterfaceMethod org/eclipse/core/resources/IProject.delete:(ZLorg/eclipse/core/runtime/IProgressMonitor;)V
     172: aload_0       
     173: getfield      #26                 // Field testUtils:Lorg/eclipse/egit/core/test/TestUtils;
     176: aload         9
     178: invokevirtual #182                // Method org/eclipse/egit/core/test/TestProject.getProject:()Lorg/eclipse/core/resources/IProject;
     181: ldc           #253                // String file.txt
     183: ldc           #255                // String some text
     185: invokevirtual #257                // Method org/eclipse/egit/core/test/TestUtils.addFileToProject:(Lorg/eclipse/core/resources/IProject;Ljava/lang/String;Ljava/lang/String;)Lorg/eclipse/core/resources/IFile;
     188: pop           
     189: new           #269                // class org/eclipse/egit/core/op/AddToIndexOperation
     192: dup           
     193: iconst_1      
     194: anewarray     #271                // class org/eclipse/core/resources/IResource
     197: dup           
     198: iconst_0      
     199: aload         9
     201: invokevirtual #182                // Method org/eclipse/egit/core/test/TestProject.getProject:()Lorg/eclipse/core/resources/IProject;
     204: ldc           #253                // String file.txt
     206: invokeinterface #265,  2          // InterfaceMethod org/eclipse/core/resources/IProject.getFile:(Ljava/lang/String;)Lorg/eclipse/core/resources/IFile;
     211: aastore       
     212: invokespecial #273                // Method org/eclipse/egit/core/op/AddToIndexOperation."<init>":([Lorg/eclipse/core/resources/IResource;)V
     215: astore        11
     217: aload         11
     219: aconst_null   
     220: invokevirtual #276                // Method org/eclipse/egit/core/op/AddToIndexOperation.execute:(Lorg/eclipse/core/runtime/IProgressMonitor;)V
     223: aload_0       
     224: getfield      #147                // Field repository:Lorg/eclipse/jgit/lib/Repository;
     227: invokevirtual #280                // Method org/eclipse/jgit/lib/Repository.getIndexFile:()Ljava/io/File;
     230: getstatic     #285                // Field org/eclipse/jgit/util/FS.DETECTED:Lorg/eclipse/jgit/util/FS;
     233: invokestatic  #291                // Method org/eclipse/jgit/dircache/DirCache.read:(Ljava/io/File;Lorg/eclipse/jgit/util/FS;)Lorg/eclipse/jgit/dircache/DirCache;
     236: astore        12
     238: aload         12
     240: new           #228                // class java/lang/StringBuilder
     243: dup           
     244: aload         7
     246: invokestatic  #230                // Method java/lang/String.valueOf:(Ljava/lang/Object;)Ljava/lang/String;
     249: invokespecial #236                // Method java/lang/StringBuilder."<init>":(Ljava/lang/String;)V
     252: ldc           #253                // String file.txt
     254: invokevirtual #238                // Method java/lang/StringBuilder.append:(Ljava/lang/String;)Ljava/lang/StringBuilder;
     257: invokevirtual #242                // Method java/lang/StringBuilder.toString:()Ljava/lang/String;
     260: invokevirtual #309                // Method org/eclipse/jgit/dircache/DirCache.getEntry:(Ljava/lang/String;)Lorg/eclipse/jgit/dircache/DirCacheEntry;
     263: invokestatic  #313                // Method org/junit/Assert.assertNotNull:(Ljava/lang/Object;)V
     266: aload         12
     268: new           #228                // class java/lang/StringBuilder
     271: dup           
     272: aload         7
     274: invokestatic  #230                // Method java/lang/String.valueOf:(Ljava/lang/Object;)Ljava/lang/String;
     277: invokespecial #236                // Method java/lang/StringBuilder."<init>":(Ljava/lang/String;)V
     280: ldc           #253                // String file.txt
     282: invokevirtual #238                // Method java/lang/StringBuilder.append:(Ljava/lang/String;)Ljava/lang/StringBuilder;
     285: invokevirtual #242                // Method java/lang/StringBuilder.toString:()Ljava/lang/String;
     288: invokevirtual #309                // Method org/eclipse/jgit/dircache/DirCache.getEntry:(Ljava/lang/String;)Lorg/eclipse/jgit/dircache/DirCacheEntry;
     291: invokevirtual #427                // Method org/eclipse/jgit/dircache/DirCacheEntry.getObjectId:()Lorg/eclipse/jgit/lib/ObjectId;
     294: astore        13
     296: aload_0       
     297: getfield      #26                 // Field testUtils:Lorg/eclipse/egit/core/test/TestUtils;
     300: aload         9
     302: invokevirtual #182                // Method org/eclipse/egit/core/test/TestProject.getProject:()Lorg/eclipse/core/resources/IProject;
     305: aload         9
     307: invokevirtual #182                // Method org/eclipse/egit/core/test/TestProject.getProject:()Lorg/eclipse/core/resources/IProject;
     310: ldc           #253                // String file.txt
     312: invokeinterface #265,  2          // InterfaceMethod org/eclipse/core/resources/IProject.getFile:(Ljava/lang/String;)Lorg/eclipse/core/resources/IFile;
     317: ldc_w         #317                // String other text
     320: invokevirtual #319                // Method org/eclipse/egit/core/test/TestUtils.changeContentOfFile:(Lorg/eclipse/core/resources/IProject;Lorg/eclipse/core/resources/IFile;Ljava/lang/String;)Lorg/eclipse/core/resources/IFile;
     323: pop           
     324: aload         9
     326: invokevirtual #182                // Method org/eclipse/egit/core/test/TestProject.getProject:()Lorg/eclipse/core/resources/IProject;
     329: invokeinterface #458,  1          // InterfaceMethod org/eclipse/core/resources/IProject.getDescription:()Lorg/eclipse/core/resources/IProjectDescription;
     334: astore        14
     336: aload         14
     338: aload         4
     340: invokeinterface #462,  2          // InterfaceMethod org/eclipse/core/resources/IProjectDescription.setName:(Ljava/lang/String;)V
     345: iload         6
     347: ifeq          425
     350: aload_3       
     351: invokevirtual #647                // Method java/lang/String.length:()I
     354: ifle          414
     357: aload         14
     359: aload         9
     361: invokevirtual #182                // Method org/eclipse/egit/core/test/TestProject.getProject:()Lorg/eclipse/core/resources/IProject;
     364: invokeinterface #658,  1          // InterfaceMethod org/eclipse/core/resources/IProject.getWorkspace:()Lorg/eclipse/core/resources/IWorkspace;
     369: invokeinterface #75,  1           // InterfaceMethod org/eclipse/core/resources/IWorkspace.getRoot:()Lorg/eclipse/core/resources/IWorkspaceRoot;
     374: invokeinterface #81,  1           // InterfaceMethod org/eclipse/core/resources/IWorkspaceRoot.getLocation:()Lorg/eclipse/core/runtime/IPath;
     379: new           #228                // class java/lang/StringBuilder
     382: dup           
     383: aload_3       
     384: invokestatic  #230                // Method java/lang/String.valueOf:(Ljava/lang/Object;)Ljava/lang/String;
     387: invokespecial #236                // Method java/lang/StringBuilder."<init>":(Ljava/lang/String;)V
     390: aload         4
     392: invokevirtual #238                // Method java/lang/StringBuilder.append:(Ljava/lang/String;)Ljava/lang/StringBuilder;
     395: invokevirtual #242                // Method java/lang/StringBuilder.toString:()Ljava/lang/String;
     398: invokeinterface #412,  2          // InterfaceMethod org/eclipse/core/runtime/IPath.append:(Ljava/lang/String;)Lorg/eclipse/core/runtime/IPath;
     403: invokestatic  #508                // Method org/eclipse/core/filesystem/URIUtil.toURI:(Lorg/eclipse/core/runtime/IPath;)Ljava/net/URI;
     406: invokeinterface #514,  2          // InterfaceMethod org/eclipse/core/resources/IProjectDescription.setLocationURI:(Ljava/net/URI;)V
     411: goto          480
     414: aload         14
     416: aconst_null   
     417: invokeinterface #514,  2          // InterfaceMethod org/eclipse/core/resources/IProjectDescription.setLocationURI:(Ljava/net/URI;)V
     422: goto          480
     425: aload         14
     427: new           #499                // class org/eclipse/core/runtime/Path
     430: dup           
     431: new           #228                // class java/lang/StringBuilder
     434: dup           
     435: invokespecial #659                // Method java/lang/StringBuilder."<init>":()V
     438: aload_0       
     439: getfield      #115                // Field workspaceSupplement:Ljava/io/File;
     442: invokevirtual #660                // Method java/lang/StringBuilder.append:(Ljava/lang/Object;)Ljava/lang/StringBuilder;
     445: ldc_w         #641                // String /
     448: invokevirtual #238                // Method java/lang/StringBuilder.append:(Ljava/lang/String;)Ljava/lang/StringBuilder;
     451: aload_3       
     452: invokevirtual #238                // Method java/lang/StringBuilder.append:(Ljava/lang/String;)Ljava/lang/StringBuilder;
     455: ldc_w         #641                // String /
     458: invokevirtual #238                // Method java/lang/StringBuilder.append:(Ljava/lang/String;)Ljava/lang/StringBuilder;
     461: aload         4
     463: invokevirtual #238                // Method java/lang/StringBuilder.append:(Ljava/lang/String;)Ljava/lang/StringBuilder;
     466: invokevirtual #242                // Method java/lang/StringBuilder.toString:()Ljava/lang/String;
     469: invokespecial #507                // Method org/eclipse/core/runtime/Path."<init>":(Ljava/lang/String;)V
     472: invokestatic  #508                // Method org/eclipse/core/filesystem/URIUtil.toURI:(Lorg/eclipse/core/runtime/IPath;)Ljava/net/URI;
     475: invokeinterface #514,  2          // InterfaceMethod org/eclipse/core/resources/IProjectDescription.setLocationURI:(Ljava/net/URI;)V
     480: aload         9
     482: invokevirtual #182                // Method org/eclipse/egit/core/test/TestProject.getProject:()Lorg/eclipse/core/resources/IProject;
     485: aload         14
     487: bipush        33
     489: aconst_null   
     490: invokeinterface #467,  4          // InterfaceMethod org/eclipse/core/resources/IProject.move:(Lorg/eclipse/core/resources/IProjectDescription;ILorg/eclipse/core/runtime/IProgressMonitor;)V
     495: aload         9
     497: invokevirtual #182                // Method org/eclipse/egit/core/test/TestProject.getProject:()Lorg/eclipse/core/resources/IProject;
     500: invokeinterface #658,  1          // InterfaceMethod org/eclipse/core/resources/IProject.getWorkspace:()Lorg/eclipse/core/resources/IWorkspace;
     505: invokeinterface #75,  1           // InterfaceMethod org/eclipse/core/resources/IWorkspace.getRoot:()Lorg/eclipse/core/resources/IWorkspaceRoot;
     510: aload         4
     512: invokeinterface #453,  2          // InterfaceMethod org/eclipse/core/resources/IWorkspaceRoot.getProject:(Ljava/lang/String;)Lorg/eclipse/core/resources/IProject;
     517: astore        15
     519: aload         15
     521: invokeinterface #488,  1          // InterfaceMethod org/eclipse/core/resources/IProject.exists:()Z
     526: invokestatic  #352                // Method org/junit/Assert.assertTrue:(Z)V
     529: aload         15
     531: invokestatic  #384                // Method org/eclipse/egit/core/project/RepositoryMapping.getMapping:(Lorg/eclipse/core/resources/IProject;)Lorg/eclipse/egit/core/project/RepositoryMapping;
     534: invokestatic  #313                // Method org/junit/Assert.assertNotNull:(Ljava/lang/Object;)V
     537: aload         12
     539: invokevirtual #342                // Method org/eclipse/jgit/dircache/DirCache.read:()V
     542: aload         15
     544: ldc           #253                // String file.txt
     546: invokeinterface #265,  2          // InterfaceMethod org/eclipse/core/resources/IProject.getFile:(Ljava/lang/String;)Lorg/eclipse/core/resources/IFile;
     551: invokeinterface #347,  1          // InterfaceMethod org/eclipse/core/resources/IFile.exists:()Z
     556: invokestatic  #352                // Method org/junit/Assert.assertTrue:(Z)V
     559: aload         12
     561: new           #228                // class java/lang/StringBuilder
     564: dup           
     565: aload         8
     567: invokestatic  #230                // Method java/lang/String.valueOf:(Ljava/lang/Object;)Ljava/lang/String;
     570: invokespecial #236                // Method java/lang/StringBuilder."<init>":(Ljava/lang/String;)V
     573: ldc           #253                // String file.txt
     575: invokevirtual #238                // Method java/lang/StringBuilder.append:(Ljava/lang/String;)Ljava/lang/StringBuilder;
     578: invokevirtual #242                // Method java/lang/StringBuilder.toString:()Ljava/lang/String;
     581: invokevirtual #309                // Method org/eclipse/jgit/dircache/DirCache.getEntry:(Ljava/lang/String;)Lorg/eclipse/jgit/dircache/DirCacheEntry;
     584: invokestatic  #313                // Method org/junit/Assert.assertNotNull:(Ljava/lang/Object;)V
     587: aload         13
     589: aload         12
     591: new           #228                // class java/lang/StringBuilder
     594: dup           
     595: aload         8
     597: invokestatic  #230                // Method java/lang/String.valueOf:(Ljava/lang/Object;)Ljava/lang/String;
     600: invokespecial #236                // Method java/lang/StringBuilder."<init>":(Ljava/lang/String;)V
     603: ldc           #253                // String file.txt
     605: invokevirtual #238                // Method java/lang/StringBuilder.append:(Ljava/lang/String;)Ljava/lang/StringBuilder;
     608: invokevirtual #242                // Method java/lang/StringBuilder.toString:()Ljava/lang/String;
     611: invokevirtual #309                // Method org/eclipse/jgit/dircache/DirCache.getEntry:(Ljava/lang/String;)Lorg/eclipse/jgit/dircache/DirCacheEntry;
     614: invokevirtual #427                // Method org/eclipse/jgit/dircache/DirCacheEntry.getObjectId:()Lorg/eclipse/jgit/lib/ObjectId;
     617: invokestatic  #440                // Method org/junit/Assert.assertEquals:(Ljava/lang/Object;Ljava/lang/Object;)V
     620: return        

  private void registerWorkspaceRelativeTestDirProject(java.lang.String, java.lang.String);
    Code:
       0: aload_1       
       1: ifnull        22
       4: aload_1       
       5: ldc_w         #380                // String 
       8: invokevirtual #550                // Method java/lang/String.equals:(Ljava/lang/Object;)Z
      11: ifne          22
      14: aload_0       
      15: aload_1       
      16: invokespecial #212                // Method registerWorkspaceRelativeTestDir:(Ljava/lang/String;)V
      19: goto          27
      22: aload_0       
      23: aload_2       
      24: invokespecial #212                // Method registerWorkspaceRelativeTestDir:(Ljava/lang/String;)V
      27: return        

  private void registerWorkspaceRelativeTestDir(java.lang.String);
    Code:
       0: aload_1       
       1: ifnull        38
       4: aload_1       
       5: ldc_w         #380                // String 
       8: invokevirtual #550                // Method java/lang/String.equals:(Ljava/lang/Object;)Z
      11: ifne          38
      14: new           #94                 // class java/io/File
      17: dup           
      18: aload_0       
      19: getfield      #126                // Field workspace:Ljava/io/File;
      22: aload_1       
      23: invokespecial #243                // Method java/io/File."<init>":(Ljava/io/File;Ljava/lang/String;)V
      26: astore_2      
      27: aload_0       
      28: getfield      #31                 // Field testDirs:Ljava/util/Set;
      31: aload_2       
      32: invokeinterface #120,  2          // InterfaceMethod java/util/Set.add:(Ljava/lang/Object;)Z
      37: pop           
      38: return        
}
