Compiled from "GitTestCase.java"
public abstract class org.eclipse.egit.core.test.GitTestCase {
  protected final org.eclipse.egit.core.test.TestUtils testUtils;

  protected org.eclipse.egit.core.test.TestProject project;

  protected java.io.File gitDir;

  public org.eclipse.egit.core.test.GitTestCase();
    Code:
       0: aload_0       
       1: invokespecial #14                 // Method java/lang/Object."<init>":()V
       4: aload_0       
       5: new           #16                 // class org/eclipse/egit/core/test/TestUtils
       8: dup           
       9: invokespecial #18                 // Method org/eclipse/egit/core/test/TestUtils."<init>":()V
      12: putfield      #19                 // Field testUtils:Lorg/eclipse/egit/core/test/TestUtils;
      15: return        

  public static void setUpClass();
    Code:
       0: getstatic     #28                 // Field org/eclipse/core/runtime/preferences/InstanceScope.INSTANCE:Lorg/eclipse/core/runtime/preferences/IScopeContext;
       3: invokestatic  #34                 // Method org/eclipse/egit/core/Activator.getPluginId:()Ljava/lang/String;
       6: invokeinterface #40,  2           // InterfaceMethod org/eclipse/core/runtime/preferences/IScopeContext.getNode:(Ljava/lang/String;)Lorg/eclipse/core/runtime/preferences/IEclipsePreferences;
      11: astore_0      
      12: aload_0       
      13: ldc           #46                 // String core_autoIgnoreDerivedResources
      15: iconst_0      
      16: invokeinterface #48,  3           // InterfaceMethod org/eclipse/core/runtime/preferences/IEclipsePreferences.putBoolean:(Ljava/lang/String;Z)V
      21: aload_0       
      22: ldc           #54                 // String core_autoShareProjects
      24: iconst_0      
      25: invokeinterface #48,  3           // InterfaceMethod org/eclipse/core/runtime/preferences/IEclipsePreferences.putBoolean:(Ljava/lang/String;Z)V
      30: return        

  public void setUp() throws java.lang.Exception;
    Code:
       0: invokestatic  #63                 // Method org/eclipse/egit/core/Activator.getDefault:()Lorg/eclipse/egit/core/Activator;
       3: invokevirtual #67                 // Method org/eclipse/egit/core/Activator.getRepositoryCache:()Lorg/eclipse/egit/core/RepositoryCache;
       6: invokevirtual #71                 // Method org/eclipse/egit/core/RepositoryCache.clear:()V
       9: new           #76                 // class org/eclipse/jgit/junit/MockSystemReader
      12: dup           
      13: invokespecial #78                 // Method org/eclipse/jgit/junit/MockSystemReader."<init>":()V
      16: astore_1      
      17: aload_1       
      18: invokestatic  #79                 // Method org/eclipse/jgit/util/SystemReader.setInstance:(Lorg/eclipse/jgit/util/SystemReader;)V
      21: aload_1       
      22: ldc           #85                 // String GIT_CEILING_DIRECTORIES
      24: invokestatic  #87                 // Method org/eclipse/core/resources/ResourcesPlugin.getWorkspace:()Lorg/eclipse/core/resources/IWorkspace;
      27: invokeinterface #93,  1           // InterfaceMethod org/eclipse/core/resources/IWorkspace.getRoot:()Lorg/eclipse/core/resources/IWorkspaceRoot;
      32: invokeinterface #99,  1           // InterfaceMethod org/eclipse/core/resources/IWorkspaceRoot.getLocation:()Lorg/eclipse/core/runtime/IPath;
      37: invokeinterface #105,  1          // InterfaceMethod org/eclipse/core/runtime/IPath.toFile:()Ljava/io/File;
      42: invokevirtual #111                // Method java/io/File.getParentFile:()Ljava/io/File;
      45: invokevirtual #116                // Method java/io/File.getAbsoluteFile:()Ljava/io/File;
      48: invokevirtual #119                // Method java/io/File.toString:()Ljava/lang/String;
      51: invokevirtual #122                // Method org/eclipse/jgit/junit/MockSystemReader.setProperty:(Ljava/lang/String;Ljava/lang/String;)V
      54: aload_0       
      55: new           #126                // class org/eclipse/egit/core/test/TestProject
      58: dup           
      59: iconst_1      
      60: invokespecial #128                // Method org/eclipse/egit/core/test/TestProject."<init>":(Z)V
      63: putfield      #131                // Field project:Lorg/eclipse/egit/core/test/TestProject;
      66: aload_0       
      67: new           #112                // class java/io/File
      70: dup           
      71: aload_0       
      72: getfield      #131                // Field project:Lorg/eclipse/egit/core/test/TestProject;
      75: invokevirtual #133                // Method org/eclipse/egit/core/test/TestProject.getProject:()Lorg/eclipse/core/resources/IProject;
      78: invokeinterface #137,  1          // InterfaceMethod org/eclipse/core/resources/IProject.getWorkspace:()Lorg/eclipse/core/resources/IWorkspace;
      83: invokeinterface #93,  1           // InterfaceMethod org/eclipse/core/resources/IWorkspace.getRoot:()Lorg/eclipse/core/resources/IWorkspaceRoot;
      88: invokeinterface #140,  1          // InterfaceMethod org/eclipse/core/resources/IWorkspaceRoot.getRawLocation:()Lorg/eclipse/core/runtime/IPath;
      93: invokeinterface #105,  1          // InterfaceMethod org/eclipse/core/runtime/IPath.toFile:()Ljava/io/File;
      98: ldc           #143                // String .git
     100: invokespecial #145                // Method java/io/File."<init>":(Ljava/io/File;Ljava/lang/String;)V
     103: putfield      #148                // Field gitDir:Ljava/io/File;
     106: aload_0       
     107: getfield      #148                // Field gitDir:Ljava/io/File;
     110: invokevirtual #150                // Method java/io/File.exists:()Z
     113: ifeq          124
     116: aload_0       
     117: getfield      #148                // Field gitDir:Ljava/io/File;
     120: iconst_3      
     121: invokestatic  #154                // Method org/eclipse/jgit/util/FileUtils.delete:(Ljava/io/File;I)V
     124: return        

  public void tearDown() throws java.lang.Exception;
    Code:
       0: aload_0       
       1: getfield      #131                // Field project:Lorg/eclipse/egit/core/test/TestProject;
       4: invokevirtual #165                // Method org/eclipse/egit/core/test/TestProject.dispose:()V
       7: invokestatic  #63                 // Method org/eclipse/egit/core/Activator.getDefault:()Lorg/eclipse/egit/core/Activator;
      10: invokevirtual #67                 // Method org/eclipse/egit/core/Activator.getRepositoryCache:()Lorg/eclipse/egit/core/RepositoryCache;
      13: invokevirtual #71                 // Method org/eclipse/egit/core/RepositoryCache.clear:()V
      16: aload_0       
      17: getfield      #148                // Field gitDir:Ljava/io/File;
      20: invokevirtual #150                // Method java/io/File.exists:()Z
      23: ifeq          34
      26: aload_0       
      27: getfield      #148                // Field gitDir:Ljava/io/File;
      30: iconst_3      
      31: invokestatic  #154                // Method org/eclipse/jgit/util/FileUtils.delete:(Ljava/io/File;I)V
      34: aconst_null   
      35: invokestatic  #79                 // Method org/eclipse/jgit/util/SystemReader.setInstance:(Lorg/eclipse/jgit/util/SystemReader;)V
      38: return        

  protected org.eclipse.jgit.lib.ObjectId createFile(org.eclipse.jgit.lib.Repository, org.eclipse.core.resources.IProject, java.lang.String, java.lang.String) throws java.io.IOException;
    Code:
       0: new           #112                // class java/io/File
       3: dup           
       4: aload_2       
       5: invokeinterface #172,  1          // InterfaceMethod org/eclipse/core/resources/IProject.getProject:()Lorg/eclipse/core/resources/IProject;
      10: invokeinterface #173,  1          // InterfaceMethod org/eclipse/core/resources/IProject.getLocation:()Lorg/eclipse/core/runtime/IPath;
      15: invokeinterface #105,  1          // InterfaceMethod org/eclipse/core/runtime/IPath.toFile:()Ljava/io/File;
      20: aload_3       
      21: invokespecial #145                // Method java/io/File."<init>":(Ljava/io/File;Ljava/lang/String;)V
      24: astore        5
      26: new           #174                // class java/io/OutputStreamWriter
      29: dup           
      30: new           #176                // class java/io/FileOutputStream
      33: dup           
      34: aload         5
      36: invokespecial #178                // Method java/io/FileOutputStream."<init>":(Ljava/io/File;)V
      39: ldc           #181                // String UTF-8
      41: invokespecial #183                // Method java/io/OutputStreamWriter."<init>":(Ljava/io/OutputStream;Ljava/lang/String;)V
      44: astore        6
      46: aload         6
      48: aload         4
      50: invokevirtual #186                // Method java/io/Writer.write:(Ljava/lang/String;)V
      53: aload         6
      55: invokevirtual #192                // Method java/io/Writer.close:()V
      58: aload         5
      60: invokestatic  #195                // Method org/eclipse/jgit/util/IO.readFully:(Ljava/io/File;)[B
      63: astore        7
      65: aconst_null   
      66: astore        8
      68: aconst_null   
      69: astore        9
      71: aload_1       
      72: invokevirtual #201                // Method org/eclipse/jgit/lib/Repository.newObjectInserter:()Lorg/eclipse/jgit/lib/ObjectInserter;
      75: astore        10
      77: aload         10
      79: iconst_3      
      80: aload         7
      82: invokevirtual #207                // Method org/eclipse/jgit/lib/ObjectInserter.insert:(I[B)Lorg/eclipse/jgit/lib/ObjectId;
      85: astore        11
      87: aload         10
      89: invokevirtual #213                // Method org/eclipse/jgit/lib/ObjectInserter.flush:()V
      92: aload         11
      94: aload         10
      96: ifnull        104
      99: aload         10
     101: invokevirtual #216                // Method org/eclipse/jgit/lib/ObjectInserter.close:()V
     104: areturn       
     105: astore        8
     107: aload         10
     109: ifnull        117
     112: aload         10
     114: invokevirtual #216                // Method org/eclipse/jgit/lib/ObjectInserter.close:()V
     117: aload         8
     119: athrow        
     120: astore        9
     122: aload         8
     124: ifnonnull     134
     127: aload         9
     129: astore        8
     131: goto          148
     134: aload         8
     136: aload         9
     138: if_acmpeq     148
     141: aload         8
     143: aload         9
     145: invokevirtual #217                // Method java/lang/Throwable.addSuppressed:(Ljava/lang/Throwable;)V
     148: aload         8
     150: athrow        
    Exception table:
       from    to  target type
          77    94   105   any
         104   105   105   any
          71   120   120   any

  protected org.eclipse.jgit.lib.ObjectId createFileCorruptShort(org.eclipse.jgit.lib.Repository, org.eclipse.core.resources.IProject, java.lang.String, java.lang.String) throws java.io.IOException;
    Code:
       0: aload_0       
       1: aload_1       
       2: aload_2       
       3: aload_3       
       4: aload         4
       6: invokevirtual #245                // Method createFile:(Lorg/eclipse/jgit/lib/Repository;Lorg/eclipse/core/resources/IProject;Ljava/lang/String;Ljava/lang/String;)Lorg/eclipse/jgit/lib/ObjectId;
       9: astore        5
      11: new           #112                // class java/io/File
      14: dup           
      15: aload_1       
      16: invokevirtual #247                // Method org/eclipse/jgit/lib/Repository.getDirectory:()Ljava/io/File;
      19: new           #250                // class java/lang/StringBuilder
      22: dup           
      23: ldc           #252                // String objects/
      25: invokespecial #254                // Method java/lang/StringBuilder."<init>":(Ljava/lang/String;)V
      28: aload         5
      30: invokevirtual #256                // Method org/eclipse/jgit/lib/ObjectId.name:()Ljava/lang/String;
      33: iconst_0      
      34: iconst_2      
      35: invokevirtual #258                // Method java/lang/String.substring:(II)Ljava/lang/String;
      38: invokevirtual #262                // Method java/lang/StringBuilder.append:(Ljava/lang/String;)Ljava/lang/StringBuilder;
      41: ldc_w         #266                // String /
      44: invokevirtual #262                // Method java/lang/StringBuilder.append:(Ljava/lang/String;)Ljava/lang/StringBuilder;
      47: aload         5
      49: invokevirtual #256                // Method org/eclipse/jgit/lib/ObjectId.name:()Ljava/lang/String;
      52: iconst_2      
      53: invokevirtual #268                // Method java/lang/String.substring:(I)Ljava/lang/String;
      56: invokevirtual #262                // Method java/lang/StringBuilder.append:(Ljava/lang/String;)Ljava/lang/StringBuilder;
      59: invokevirtual #271                // Method java/lang/StringBuilder.toString:()Ljava/lang/String;
      62: invokespecial #145                // Method java/io/File."<init>":(Ljava/io/File;Ljava/lang/String;)V
      65: astore        6
      67: aload         6
      69: invokestatic  #195                // Method org/eclipse/jgit/util/IO.readFully:(Ljava/io/File;)[B
      72: astore        7
      74: aload         6
      76: invokestatic  #272                // Method org/eclipse/jgit/util/FileUtils.delete:(Ljava/io/File;)V
      79: new           #176                // class java/io/FileOutputStream
      82: dup           
      83: aload         6
      85: invokespecial #178                // Method java/io/FileOutputStream."<init>":(Ljava/io/File;)V
      88: astore        8
      90: aload         7
      92: arraylength   
      93: iconst_1      
      94: isub          
      95: newarray       byte
      97: astore        9
      99: aload         7
     101: iconst_0      
     102: aload         9
     104: iconst_0      
     105: aload         9
     107: arraylength   
     108: invokestatic  #274                // Method java/lang/System.arraycopy:(Ljava/lang/Object;ILjava/lang/Object;II)V
     111: aload         8
     113: aload         9
     115: invokevirtual #280                // Method java/io/FileOutputStream.write:([B)V
     118: goto          131
     121: astore        10
     123: aload         8
     125: invokevirtual #283                // Method java/io/FileOutputStream.close:()V
     128: aload         10
     130: athrow        
     131: aload         8
     133: invokevirtual #283                // Method java/io/FileOutputStream.close:()V
     136: aload         5
     138: areturn       
    Exception table:
       from    to  target type
          90   121   121   any
}
