Compiled from "AddOperationTest.java"
public class org.eclipse.egit.core.test.op.AddOperationTest extends org.eclipse.egit.core.test.GitTestCase {
  private java.util.List<org.eclipse.core.resources.IResource> resources;

  org.eclipse.egit.core.test.TestRepository testRepository;

  public org.eclipse.egit.core.test.op.AddOperationTest();
    Code:
       0: aload_0       
       1: invokespecial #14                 // Method org/eclipse/egit/core/test/GitTestCase."<init>":()V
       4: aload_0       
       5: new           #16                 // class java/util/ArrayList
       8: dup           
       9: invokespecial #18                 // Method java/util/ArrayList."<init>":()V
      12: putfield      #19                 // Field resources:Ljava/util/List;
      15: return        

  public void setUp() throws java.lang.Exception;
    Code:
       0: aload_0       
       1: invokespecial #31                 // Method org/eclipse/egit/core/test/GitTestCase.setUp:()V
       4: aload_0       
       5: new           #33                 // class java/io/File
       8: dup           
       9: aload_0       
      10: getfield      #35                 // Field project:Lorg/eclipse/egit/core/test/TestProject;
      13: invokevirtual #39                 // Method org/eclipse/egit/core/test/TestProject.getProject:()Lorg/eclipse/core/resources/IProject;
      16: invokeinterface #45,  1           // InterfaceMethod org/eclipse/core/resources/IProject.getLocationURI:()Ljava/net/URI;
      21: invokevirtual #51                 // Method java/net/URI.getPath:()Ljava/lang/String;
      24: ldc           #57                 // String .git
      26: invokespecial #59                 // Method java/io/File."<init>":(Ljava/lang/String;Ljava/lang/String;)V
      29: putfield      #62                 // Field gitDir:Ljava/io/File;
      32: aload_0       
      33: new           #66                 // class org/eclipse/egit/core/test/TestRepository
      36: dup           
      37: aload_0       
      38: getfield      #62                 // Field gitDir:Ljava/io/File;
      41: invokespecial #68                 // Method org/eclipse/egit/core/test/TestRepository."<init>":(Ljava/io/File;)V
      44: putfield      #71                 // Field testRepository:Lorg/eclipse/egit/core/test/TestRepository;
      47: aload_0       
      48: getfield      #71                 // Field testRepository:Lorg/eclipse/egit/core/test/TestRepository;
      51: aload_0       
      52: getfield      #35                 // Field project:Lorg/eclipse/egit/core/test/TestProject;
      55: invokevirtual #39                 // Method org/eclipse/egit/core/test/TestProject.getProject:()Lorg/eclipse/core/resources/IProject;
      58: invokevirtual #73                 // Method org/eclipse/egit/core/test/TestRepository.connect:(Lorg/eclipse/core/resources/IProject;)V
      61: return        

  public void tearDown() throws java.lang.Exception;
    Code:
       0: aload_0       
       1: getfield      #71                 // Field testRepository:Lorg/eclipse/egit/core/test/TestRepository;
       4: invokevirtual #79                 // Method org/eclipse/egit/core/test/TestRepository.dispose:()V
       7: aload_0       
       8: invokespecial #82                 // Method org/eclipse/egit/core/test/GitTestCase.tearDown:()V
      11: return        

  public void testTrackFile() throws java.lang.Exception;
    Code:
       0: aload_0       
       1: getfield      #86                 // Field testUtils:Lorg/eclipse/egit/core/test/TestUtils;
       4: aload_0       
       5: getfield      #35                 // Field project:Lorg/eclipse/egit/core/test/TestProject;
       8: invokevirtual #39                 // Method org/eclipse/egit/core/test/TestProject.getProject:()Lorg/eclipse/core/resources/IProject;
      11: ldc           #90                 // String a.txt
      13: ldc           #92                 // String some text
      15: invokevirtual #94                 // Method org/eclipse/egit/core/test/TestUtils.addFileToProject:(Lorg/eclipse/core/resources/IProject;Ljava/lang/String;Ljava/lang/String;)Lorg/eclipse/core/resources/IFile;
      18: astore_1      
      19: aload_0       
      20: getfield      #71                 // Field testRepository:Lorg/eclipse/egit/core/test/TestRepository;
      23: aload_1       
      24: invokeinterface #100,  1          // InterfaceMethod org/eclipse/core/resources/IFile.getLocation:()Lorg/eclipse/core/runtime/IPath;
      29: invokeinterface #106,  1          // InterfaceMethod org/eclipse/core/runtime/IPath.toPortableString:()Ljava/lang/String;
      34: invokevirtual #111                // Method org/eclipse/egit/core/test/TestRepository.inIndex:(Ljava/lang/String;)Z
      37: invokestatic  #115                // Method org/junit/Assert.assertFalse:(Z)V
      40: aload_0       
      41: getfield      #19                 // Field resources:Ljava/util/List;
      44: aload_1       
      45: invokeinterface #121,  2          // InterfaceMethod java/util/List.add:(Ljava/lang/Object;)Z
      50: pop           
      51: new           #127                // class org/eclipse/egit/core/op/AddToIndexOperation
      54: dup           
      55: aload_0       
      56: getfield      #19                 // Field resources:Ljava/util/List;
      59: invokespecial #129                // Method org/eclipse/egit/core/op/AddToIndexOperation."<init>":(Ljava/util/Collection;)V
      62: aconst_null   
      63: invokevirtual #132                // Method org/eclipse/egit/core/op/AddToIndexOperation.execute:(Lorg/eclipse/core/runtime/IProgressMonitor;)V
      66: aload_0       
      67: getfield      #71                 // Field testRepository:Lorg/eclipse/egit/core/test/TestRepository;
      70: aload_1       
      71: invokeinterface #100,  1          // InterfaceMethod org/eclipse/core/resources/IFile.getLocation:()Lorg/eclipse/core/runtime/IPath;
      76: invokeinterface #106,  1          // InterfaceMethod org/eclipse/core/runtime/IPath.toPortableString:()Ljava/lang/String;
      81: invokevirtual #111                // Method org/eclipse/egit/core/test/TestRepository.inIndex:(Ljava/lang/String;)Z
      84: invokestatic  #136                // Method org/junit/Assert.assertTrue:(Z)V
      87: return        

  public void testTrackFilesInFolder() throws java.lang.Exception;
    Code:
       0: aload_0       
       1: getfield      #86                 // Field testUtils:Lorg/eclipse/egit/core/test/TestUtils;
       4: aload_0       
       5: getfield      #35                 // Field project:Lorg/eclipse/egit/core/test/TestProject;
       8: invokevirtual #39                 // Method org/eclipse/egit/core/test/TestProject.getProject:()Lorg/eclipse/core/resources/IProject;
      11: ldc           #142                // String sub/a.txt
      13: ldc           #92                 // String some text
      15: invokevirtual #94                 // Method org/eclipse/egit/core/test/TestUtils.addFileToProject:(Lorg/eclipse/core/resources/IProject;Ljava/lang/String;Ljava/lang/String;)Lorg/eclipse/core/resources/IFile;
      18: astore_1      
      19: aload_0       
      20: getfield      #86                 // Field testUtils:Lorg/eclipse/egit/core/test/TestUtils;
      23: aload_0       
      24: getfield      #35                 // Field project:Lorg/eclipse/egit/core/test/TestProject;
      27: invokevirtual #39                 // Method org/eclipse/egit/core/test/TestProject.getProject:()Lorg/eclipse/core/resources/IProject;
      30: ldc           #144                // String sub/b.txt
      32: ldc           #92                 // String some text
      34: invokevirtual #94                 // Method org/eclipse/egit/core/test/TestUtils.addFileToProject:(Lorg/eclipse/core/resources/IProject;Ljava/lang/String;Ljava/lang/String;)Lorg/eclipse/core/resources/IFile;
      37: astore_2      
      38: aload_0       
      39: getfield      #71                 // Field testRepository:Lorg/eclipse/egit/core/test/TestRepository;
      42: aload_1       
      43: invokeinterface #100,  1          // InterfaceMethod org/eclipse/core/resources/IFile.getLocation:()Lorg/eclipse/core/runtime/IPath;
      48: invokeinterface #106,  1          // InterfaceMethod org/eclipse/core/runtime/IPath.toPortableString:()Ljava/lang/String;
      53: invokevirtual #111                // Method org/eclipse/egit/core/test/TestRepository.inIndex:(Ljava/lang/String;)Z
      56: invokestatic  #115                // Method org/junit/Assert.assertFalse:(Z)V
      59: aload_0       
      60: getfield      #71                 // Field testRepository:Lorg/eclipse/egit/core/test/TestRepository;
      63: aload_2       
      64: invokeinterface #100,  1          // InterfaceMethod org/eclipse/core/resources/IFile.getLocation:()Lorg/eclipse/core/runtime/IPath;
      69: invokeinterface #106,  1          // InterfaceMethod org/eclipse/core/runtime/IPath.toPortableString:()Ljava/lang/String;
      74: invokevirtual #111                // Method org/eclipse/egit/core/test/TestRepository.inIndex:(Ljava/lang/String;)Z
      77: invokestatic  #115                // Method org/junit/Assert.assertFalse:(Z)V
      80: aload_0       
      81: getfield      #19                 // Field resources:Ljava/util/List;
      84: aload_0       
      85: getfield      #35                 // Field project:Lorg/eclipse/egit/core/test/TestProject;
      88: invokevirtual #39                 // Method org/eclipse/egit/core/test/TestProject.getProject:()Lorg/eclipse/core/resources/IProject;
      91: ldc           #146                // String sub
      93: invokeinterface #148,  2          // InterfaceMethod org/eclipse/core/resources/IProject.getFolder:(Ljava/lang/String;)Lorg/eclipse/core/resources/IFolder;
      98: invokeinterface #121,  2          // InterfaceMethod java/util/List.add:(Ljava/lang/Object;)Z
     103: pop           
     104: new           #127                // class org/eclipse/egit/core/op/AddToIndexOperation
     107: dup           
     108: aload_0       
     109: getfield      #19                 // Field resources:Ljava/util/List;
     112: invokespecial #129                // Method org/eclipse/egit/core/op/AddToIndexOperation."<init>":(Ljava/util/Collection;)V
     115: aconst_null   
     116: invokevirtual #132                // Method org/eclipse/egit/core/op/AddToIndexOperation.execute:(Lorg/eclipse/core/runtime/IProgressMonitor;)V
     119: aload_0       
     120: getfield      #71                 // Field testRepository:Lorg/eclipse/egit/core/test/TestRepository;
     123: aload_1       
     124: invokeinterface #100,  1          // InterfaceMethod org/eclipse/core/resources/IFile.getLocation:()Lorg/eclipse/core/runtime/IPath;
     129: invokeinterface #106,  1          // InterfaceMethod org/eclipse/core/runtime/IPath.toPortableString:()Ljava/lang/String;
     134: invokevirtual #111                // Method org/eclipse/egit/core/test/TestRepository.inIndex:(Ljava/lang/String;)Z
     137: invokestatic  #136                // Method org/junit/Assert.assertTrue:(Z)V
     140: aload_0       
     141: getfield      #71                 // Field testRepository:Lorg/eclipse/egit/core/test/TestRepository;
     144: aload_2       
     145: invokeinterface #100,  1          // InterfaceMethod org/eclipse/core/resources/IFile.getLocation:()Lorg/eclipse/core/runtime/IPath;
     150: invokeinterface #106,  1          // InterfaceMethod org/eclipse/core/runtime/IPath.toPortableString:()Ljava/lang/String;
     155: invokevirtual #111                // Method org/eclipse/egit/core/test/TestRepository.inIndex:(Ljava/lang/String;)Z
     158: invokestatic  #136                // Method org/junit/Assert.assertTrue:(Z)V
     161: return        

  public void testAddFile() throws java.lang.Exception;
    Code:
       0: aload_0       
       1: getfield      #86                 // Field testUtils:Lorg/eclipse/egit/core/test/TestUtils;
       4: aload_0       
       5: getfield      #35                 // Field project:Lorg/eclipse/egit/core/test/TestProject;
       8: invokevirtual #39                 // Method org/eclipse/egit/core/test/TestProject.getProject:()Lorg/eclipse/core/resources/IProject;
      11: ldc           #90                 // String a.txt
      13: ldc           #92                 // String some text
      15: invokevirtual #94                 // Method org/eclipse/egit/core/test/TestUtils.addFileToProject:(Lorg/eclipse/core/resources/IProject;Ljava/lang/String;Ljava/lang/String;)Lorg/eclipse/core/resources/IFile;
      18: astore_1      
      19: aload_0       
      20: getfield      #19                 // Field resources:Ljava/util/List;
      23: aload_1       
      24: invokeinterface #121,  2          // InterfaceMethod java/util/List.add:(Ljava/lang/Object;)Z
      29: pop           
      30: new           #127                // class org/eclipse/egit/core/op/AddToIndexOperation
      33: dup           
      34: aload_0       
      35: getfield      #19                 // Field resources:Ljava/util/List;
      38: invokespecial #129                // Method org/eclipse/egit/core/op/AddToIndexOperation."<init>":(Ljava/util/Collection;)V
      41: aconst_null   
      42: invokevirtual #132                // Method org/eclipse/egit/core/op/AddToIndexOperation.execute:(Lorg/eclipse/core/runtime/IProgressMonitor;)V
      45: aload_0       
      46: getfield      #71                 // Field testRepository:Lorg/eclipse/egit/core/test/TestRepository;
      49: ldc           #154                // String first commit
      51: invokevirtual #156                // Method org/eclipse/egit/core/test/TestRepository.commit:(Ljava/lang/String;)Lorg/eclipse/jgit/revwalk/RevCommit;
      54: pop           
      55: aload_1       
      56: invokeinterface #160,  1          // InterfaceMethod org/eclipse/core/resources/IFile.getLocalTimeStamp:()J
      61: ldc2_w        #164                // long 1000l
      64: ldiv          
      65: aload_0       
      66: getfield      #71                 // Field testRepository:Lorg/eclipse/egit/core/test/TestRepository;
      69: aload_1       
      70: invokeinterface #100,  1          // InterfaceMethod org/eclipse/core/resources/IFile.getLocation:()Lorg/eclipse/core/runtime/IPath;
      75: invokeinterface #106,  1          // InterfaceMethod org/eclipse/core/runtime/IPath.toPortableString:()Ljava/lang/String;
      80: invokevirtual #166                // Method org/eclipse/egit/core/test/TestRepository.lastModifiedInIndex:(Ljava/lang/String;)J
      83: ldc2_w        #164                // long 1000l
      86: ldiv          
      87: invokestatic  #170                // Method org/junit/Assert.assertEquals:(JJ)V
      90: ldc2_w        #164                // long 1000l
      93: invokestatic  #174                // Method java/lang/Thread.sleep:(J)V
      96: aload_1       
      97: new           #180                // class java/io/ByteArrayInputStream
     100: dup           
     101: ldc           #182                // String other text
     103: aload_0       
     104: getfield      #35                 // Field project:Lorg/eclipse/egit/core/test/TestProject;
     107: getfield      #184                // Field org/eclipse/egit/core/test/TestProject.project:Lorg/eclipse/core/resources/IProject;
     110: invokeinterface #187,  1          // InterfaceMethod org/eclipse/core/resources/IProject.getDefaultCharset:()Ljava/lang/String;
     115: invokevirtual #190                // Method java/lang/String.getBytes:(Ljava/lang/String;)[B
     118: invokespecial #196                // Method java/io/ByteArrayInputStream."<init>":([B)V
     121: iconst_0      
     122: aconst_null   
     123: invokeinterface #199,  4          // InterfaceMethod org/eclipse/core/resources/IFile.setContents:(Ljava/io/InputStream;ILorg/eclipse/core/runtime/IProgressMonitor;)V
     128: aload_1       
     129: invokeinterface #160,  1          // InterfaceMethod org/eclipse/core/resources/IFile.getLocalTimeStamp:()J
     134: ldc2_w        #164                // long 1000l
     137: ldiv          
     138: aload_0       
     139: getfield      #71                 // Field testRepository:Lorg/eclipse/egit/core/test/TestRepository;
     142: aload_1       
     143: invokeinterface #100,  1          // InterfaceMethod org/eclipse/core/resources/IFile.getLocation:()Lorg/eclipse/core/runtime/IPath;
     148: invokeinterface #106,  1          // InterfaceMethod org/eclipse/core/runtime/IPath.toPortableString:()Ljava/lang/String;
     153: invokevirtual #166                // Method org/eclipse/egit/core/test/TestRepository.lastModifiedInIndex:(Ljava/lang/String;)J
     156: ldc2_w        #164                // long 1000l
     159: ldiv          
     160: lcmp          
     161: ifne          168
     164: iconst_1      
     165: goto          169
     168: iconst_0      
     169: invokestatic  #115                // Method org/junit/Assert.assertFalse:(Z)V
     172: new           #127                // class org/eclipse/egit/core/op/AddToIndexOperation
     175: dup           
     176: aload_0       
     177: getfield      #19                 // Field resources:Ljava/util/List;
     180: invokespecial #129                // Method org/eclipse/egit/core/op/AddToIndexOperation."<init>":(Ljava/util/Collection;)V
     183: aconst_null   
     184: invokevirtual #132                // Method org/eclipse/egit/core/op/AddToIndexOperation.execute:(Lorg/eclipse/core/runtime/IProgressMonitor;)V
     187: aload_0       
     188: getfield      #71                 // Field testRepository:Lorg/eclipse/egit/core/test/TestRepository;
     191: aload_1       
     192: invokeinterface #100,  1          // InterfaceMethod org/eclipse/core/resources/IFile.getLocation:()Lorg/eclipse/core/runtime/IPath;
     197: invokeinterface #106,  1          // InterfaceMethod org/eclipse/core/runtime/IPath.toPortableString:()Ljava/lang/String;
     202: invokevirtual #111                // Method org/eclipse/egit/core/test/TestRepository.inIndex:(Ljava/lang/String;)Z
     205: invokestatic  #136                // Method org/junit/Assert.assertTrue:(Z)V
     208: aload_1       
     209: invokeinterface #160,  1          // InterfaceMethod org/eclipse/core/resources/IFile.getLocalTimeStamp:()J
     214: ldc2_w        #164                // long 1000l
     217: ldiv          
     218: aload_0       
     219: getfield      #71                 // Field testRepository:Lorg/eclipse/egit/core/test/TestRepository;
     222: aload_1       
     223: invokeinterface #100,  1          // InterfaceMethod org/eclipse/core/resources/IFile.getLocation:()Lorg/eclipse/core/runtime/IPath;
     228: invokeinterface #106,  1          // InterfaceMethod org/eclipse/core/runtime/IPath.toPortableString:()Ljava/lang/String;
     233: invokevirtual #166                // Method org/eclipse/egit/core/test/TestRepository.lastModifiedInIndex:(Ljava/lang/String;)J
     236: ldc2_w        #164                // long 1000l
     239: ldiv          
     240: invokestatic  #170                // Method org/junit/Assert.assertEquals:(JJ)V
     243: return        

  public void testAddFilesInFolder() throws java.lang.Exception;
    Code:
       0: aload_0       
       1: getfield      #86                 // Field testUtils:Lorg/eclipse/egit/core/test/TestUtils;
       4: aload_0       
       5: getfield      #35                 // Field project:Lorg/eclipse/egit/core/test/TestProject;
       8: invokevirtual #39                 // Method org/eclipse/egit/core/test/TestProject.getProject:()Lorg/eclipse/core/resources/IProject;
      11: ldc           #142                // String sub/a.txt
      13: ldc           #92                 // String some text
      15: invokevirtual #94                 // Method org/eclipse/egit/core/test/TestUtils.addFileToProject:(Lorg/eclipse/core/resources/IProject;Ljava/lang/String;Ljava/lang/String;)Lorg/eclipse/core/resources/IFile;
      18: astore_1      
      19: aload_0       
      20: getfield      #86                 // Field testUtils:Lorg/eclipse/egit/core/test/TestUtils;
      23: aload_0       
      24: getfield      #35                 // Field project:Lorg/eclipse/egit/core/test/TestProject;
      27: invokevirtual #39                 // Method org/eclipse/egit/core/test/TestProject.getProject:()Lorg/eclipse/core/resources/IProject;
      30: ldc           #144                // String sub/b.txt
      32: ldc           #92                 // String some text
      34: invokevirtual #94                 // Method org/eclipse/egit/core/test/TestUtils.addFileToProject:(Lorg/eclipse/core/resources/IProject;Ljava/lang/String;Ljava/lang/String;)Lorg/eclipse/core/resources/IFile;
      37: astore_2      
      38: aload_0       
      39: getfield      #19                 // Field resources:Ljava/util/List;
      42: aload_0       
      43: getfield      #35                 // Field project:Lorg/eclipse/egit/core/test/TestProject;
      46: invokevirtual #39                 // Method org/eclipse/egit/core/test/TestProject.getProject:()Lorg/eclipse/core/resources/IProject;
      49: ldc           #146                // String sub
      51: invokeinterface #148,  2          // InterfaceMethod org/eclipse/core/resources/IProject.getFolder:(Ljava/lang/String;)Lorg/eclipse/core/resources/IFolder;
      56: invokeinterface #121,  2          // InterfaceMethod java/util/List.add:(Ljava/lang/Object;)Z
      61: pop           
      62: new           #127                // class org/eclipse/egit/core/op/AddToIndexOperation
      65: dup           
      66: aload_0       
      67: getfield      #19                 // Field resources:Ljava/util/List;
      70: invokespecial #129                // Method org/eclipse/egit/core/op/AddToIndexOperation."<init>":(Ljava/util/Collection;)V
      73: aconst_null   
      74: invokevirtual #132                // Method org/eclipse/egit/core/op/AddToIndexOperation.execute:(Lorg/eclipse/core/runtime/IProgressMonitor;)V
      77: aload_0       
      78: getfield      #71                 // Field testRepository:Lorg/eclipse/egit/core/test/TestRepository;
      81: ldc           #154                // String first commit
      83: invokevirtual #156                // Method org/eclipse/egit/core/test/TestRepository.commit:(Ljava/lang/String;)Lorg/eclipse/jgit/revwalk/RevCommit;
      86: pop           
      87: aload_1       
      88: invokeinterface #160,  1          // InterfaceMethod org/eclipse/core/resources/IFile.getLocalTimeStamp:()J
      93: aload_0       
      94: getfield      #71                 // Field testRepository:Lorg/eclipse/egit/core/test/TestRepository;
      97: aload_1       
      98: invokeinterface #100,  1          // InterfaceMethod org/eclipse/core/resources/IFile.getLocation:()Lorg/eclipse/core/runtime/IPath;
     103: invokeinterface #106,  1          // InterfaceMethod org/eclipse/core/runtime/IPath.toPortableString:()Ljava/lang/String;
     108: invokevirtual #166                // Method org/eclipse/egit/core/test/TestRepository.lastModifiedInIndex:(Ljava/lang/String;)J
     111: invokestatic  #170                // Method org/junit/Assert.assertEquals:(JJ)V
     114: ldc2_w        #164                // long 1000l
     117: invokestatic  #174                // Method java/lang/Thread.sleep:(J)V
     120: aload_1       
     121: new           #180                // class java/io/ByteArrayInputStream
     124: dup           
     125: ldc           #182                // String other text
     127: aload_0       
     128: getfield      #35                 // Field project:Lorg/eclipse/egit/core/test/TestProject;
     131: getfield      #184                // Field org/eclipse/egit/core/test/TestProject.project:Lorg/eclipse/core/resources/IProject;
     134: invokeinterface #187,  1          // InterfaceMethod org/eclipse/core/resources/IProject.getDefaultCharset:()Ljava/lang/String;
     139: invokevirtual #190                // Method java/lang/String.getBytes:(Ljava/lang/String;)[B
     142: invokespecial #196                // Method java/io/ByteArrayInputStream."<init>":([B)V
     145: iconst_0      
     146: aconst_null   
     147: invokeinterface #199,  4          // InterfaceMethod org/eclipse/core/resources/IFile.setContents:(Ljava/io/InputStream;ILorg/eclipse/core/runtime/IProgressMonitor;)V
     152: aload_2       
     153: new           #180                // class java/io/ByteArrayInputStream
     156: dup           
     157: ldc           #182                // String other text
     159: aload_0       
     160: getfield      #35                 // Field project:Lorg/eclipse/egit/core/test/TestProject;
     163: getfield      #184                // Field org/eclipse/egit/core/test/TestProject.project:Lorg/eclipse/core/resources/IProject;
     166: invokeinterface #187,  1          // InterfaceMethod org/eclipse/core/resources/IProject.getDefaultCharset:()Ljava/lang/String;
     171: invokevirtual #190                // Method java/lang/String.getBytes:(Ljava/lang/String;)[B
     174: invokespecial #196                // Method java/io/ByteArrayInputStream."<init>":([B)V
     177: iconst_0      
     178: aconst_null   
     179: invokeinterface #199,  4          // InterfaceMethod org/eclipse/core/resources/IFile.setContents:(Ljava/io/InputStream;ILorg/eclipse/core/runtime/IProgressMonitor;)V
     184: aload_1       
     185: invokeinterface #160,  1          // InterfaceMethod org/eclipse/core/resources/IFile.getLocalTimeStamp:()J
     190: aload_0       
     191: getfield      #71                 // Field testRepository:Lorg/eclipse/egit/core/test/TestRepository;
     194: aload_1       
     195: invokeinterface #100,  1          // InterfaceMethod org/eclipse/core/resources/IFile.getLocation:()Lorg/eclipse/core/runtime/IPath;
     200: invokeinterface #106,  1          // InterfaceMethod org/eclipse/core/runtime/IPath.toPortableString:()Ljava/lang/String;
     205: invokevirtual #166                // Method org/eclipse/egit/core/test/TestRepository.lastModifiedInIndex:(Ljava/lang/String;)J
     208: lcmp          
     209: ifne          216
     212: iconst_1      
     213: goto          217
     216: iconst_0      
     217: invokestatic  #115                // Method org/junit/Assert.assertFalse:(Z)V
     220: aload_2       
     221: invokeinterface #160,  1          // InterfaceMethod org/eclipse/core/resources/IFile.getLocalTimeStamp:()J
     226: aload_0       
     227: getfield      #71                 // Field testRepository:Lorg/eclipse/egit/core/test/TestRepository;
     230: aload_1       
     231: invokeinterface #100,  1          // InterfaceMethod org/eclipse/core/resources/IFile.getLocation:()Lorg/eclipse/core/runtime/IPath;
     236: invokeinterface #106,  1          // InterfaceMethod org/eclipse/core/runtime/IPath.toPortableString:()Ljava/lang/String;
     241: invokevirtual #166                // Method org/eclipse/egit/core/test/TestRepository.lastModifiedInIndex:(Ljava/lang/String;)J
     244: lcmp          
     245: ifne          252
     248: iconst_1      
     249: goto          253
     252: iconst_0      
     253: invokestatic  #115                // Method org/junit/Assert.assertFalse:(Z)V
     256: new           #127                // class org/eclipse/egit/core/op/AddToIndexOperation
     259: dup           
     260: aload_0       
     261: getfield      #19                 // Field resources:Ljava/util/List;
     264: invokespecial #129                // Method org/eclipse/egit/core/op/AddToIndexOperation."<init>":(Ljava/util/Collection;)V
     267: aconst_null   
     268: invokevirtual #132                // Method org/eclipse/egit/core/op/AddToIndexOperation.execute:(Lorg/eclipse/core/runtime/IProgressMonitor;)V
     271: aload_0       
     272: getfield      #71                 // Field testRepository:Lorg/eclipse/egit/core/test/TestRepository;
     275: aload_1       
     276: invokeinterface #100,  1          // InterfaceMethod org/eclipse/core/resources/IFile.getLocation:()Lorg/eclipse/core/runtime/IPath;
     281: invokeinterface #106,  1          // InterfaceMethod org/eclipse/core/runtime/IPath.toPortableString:()Ljava/lang/String;
     286: invokevirtual #111                // Method org/eclipse/egit/core/test/TestRepository.inIndex:(Ljava/lang/String;)Z
     289: invokestatic  #136                // Method org/junit/Assert.assertTrue:(Z)V
     292: aload_0       
     293: getfield      #71                 // Field testRepository:Lorg/eclipse/egit/core/test/TestRepository;
     296: aload_2       
     297: invokeinterface #100,  1          // InterfaceMethod org/eclipse/core/resources/IFile.getLocation:()Lorg/eclipse/core/runtime/IPath;
     302: invokeinterface #106,  1          // InterfaceMethod org/eclipse/core/runtime/IPath.toPortableString:()Ljava/lang/String;
     307: invokevirtual #111                // Method org/eclipse/egit/core/test/TestRepository.inIndex:(Ljava/lang/String;)Z
     310: invokestatic  #136                // Method org/junit/Assert.assertTrue:(Z)V
     313: aload_1       
     314: invokeinterface #160,  1          // InterfaceMethod org/eclipse/core/resources/IFile.getLocalTimeStamp:()J
     319: ldc2_w        #205                // long 10l
     322: ldiv          
     323: aload_0       
     324: getfield      #71                 // Field testRepository:Lorg/eclipse/egit/core/test/TestRepository;
     327: aload_1       
     328: invokeinterface #100,  1          // InterfaceMethod org/eclipse/core/resources/IFile.getLocation:()Lorg/eclipse/core/runtime/IPath;
     333: invokeinterface #106,  1          // InterfaceMethod org/eclipse/core/runtime/IPath.toPortableString:()Ljava/lang/String;
     338: invokevirtual #166                // Method org/eclipse/egit/core/test/TestRepository.lastModifiedInIndex:(Ljava/lang/String;)J
     341: ldc2_w        #205                // long 10l
     344: ldiv          
     345: invokestatic  #170                // Method org/junit/Assert.assertEquals:(JJ)V
     348: aload_2       
     349: invokeinterface #160,  1          // InterfaceMethod org/eclipse/core/resources/IFile.getLocalTimeStamp:()J
     354: ldc2_w        #205                // long 10l
     357: ldiv          
     358: aload_0       
     359: getfield      #71                 // Field testRepository:Lorg/eclipse/egit/core/test/TestRepository;
     362: aload_2       
     363: invokeinterface #100,  1          // InterfaceMethod org/eclipse/core/resources/IFile.getLocation:()Lorg/eclipse/core/runtime/IPath;
     368: invokeinterface #106,  1          // InterfaceMethod org/eclipse/core/runtime/IPath.toPortableString:()Ljava/lang/String;
     373: invokevirtual #166                // Method org/eclipse/egit/core/test/TestRepository.lastModifiedInIndex:(Ljava/lang/String;)J
     376: ldc2_w        #205                // long 10l
     379: ldiv          
     380: invokestatic  #170                // Method org/junit/Assert.assertEquals:(JJ)V
     383: return        
}
