Compiled from "CommitOperationTest.java"
public class org.eclipse.egit.core.test.op.CommitOperationTest extends org.eclipse.egit.core.test.GitTestCase {
  private static java.util.List<org.eclipse.core.resources.IFile> EMPTY_FILE_LIST;

  private java.util.List<org.eclipse.core.resources.IResource> resources;

  org.eclipse.egit.core.test.TestRepository testRepository;

  org.eclipse.jgit.lib.Repository repository;

  static {};
    Code:
       0: new           #18                 // class java/util/ArrayList
       3: dup           
       4: invokespecial #20                 // Method java/util/ArrayList."<init>":()V
       7: putstatic     #23                 // Field EMPTY_FILE_LIST:Ljava/util/List;
      10: return        

  public org.eclipse.egit.core.test.op.CommitOperationTest();
    Code:
       0: aload_0       
       1: invokespecial #27                 // Method org/eclipse/egit/core/test/GitTestCase."<init>":()V
       4: aload_0       
       5: new           #18                 // class java/util/ArrayList
       8: dup           
       9: invokespecial #20                 // Method java/util/ArrayList."<init>":()V
      12: putfield      #28                 // Field resources:Ljava/util/List;
      15: return        

  public void setUp() throws java.lang.Exception;
    Code:
       0: aload_0       
       1: invokespecial #38                 // Method org/eclipse/egit/core/test/GitTestCase.setUp:()V
       4: aload_0       
       5: new           #40                 // class java/io/File
       8: dup           
       9: aload_0       
      10: getfield      #42                 // Field project:Lorg/eclipse/egit/core/test/TestProject;
      13: invokevirtual #46                 // Method org/eclipse/egit/core/test/TestProject.getProject:()Lorg/eclipse/core/resources/IProject;
      16: invokeinterface #52,  1           // InterfaceMethod org/eclipse/core/resources/IProject.getLocationURI:()Ljava/net/URI;
      21: invokevirtual #58                 // Method java/net/URI.getPath:()Ljava/lang/String;
      24: ldc           #64                 // String .git
      26: invokespecial #66                 // Method java/io/File."<init>":(Ljava/lang/String;Ljava/lang/String;)V
      29: putfield      #69                 // Field gitDir:Ljava/io/File;
      32: aload_0       
      33: new           #73                 // class org/eclipse/egit/core/test/TestRepository
      36: dup           
      37: aload_0       
      38: getfield      #69                 // Field gitDir:Ljava/io/File;
      41: invokespecial #75                 // Method org/eclipse/egit/core/test/TestRepository."<init>":(Ljava/io/File;)V
      44: putfield      #78                 // Field testRepository:Lorg/eclipse/egit/core/test/TestRepository;
      47: aload_0       
      48: aload_0       
      49: getfield      #78                 // Field testRepository:Lorg/eclipse/egit/core/test/TestRepository;
      52: invokevirtual #80                 // Method org/eclipse/egit/core/test/TestRepository.getRepository:()Lorg/eclipse/jgit/lib/Repository;
      55: putfield      #84                 // Field repository:Lorg/eclipse/jgit/lib/Repository;
      58: aload_0       
      59: getfield      #78                 // Field testRepository:Lorg/eclipse/egit/core/test/TestRepository;
      62: aload_0       
      63: getfield      #42                 // Field project:Lorg/eclipse/egit/core/test/TestProject;
      66: invokevirtual #46                 // Method org/eclipse/egit/core/test/TestProject.getProject:()Lorg/eclipse/core/resources/IProject;
      69: invokevirtual #86                 // Method org/eclipse/egit/core/test/TestRepository.connect:(Lorg/eclipse/core/resources/IProject;)V
      72: return        

  public void tearDown() throws java.lang.Exception;
    Code:
       0: aload_0       
       1: getfield      #78                 // Field testRepository:Lorg/eclipse/egit/core/test/TestRepository;
       4: invokevirtual #92                 // Method org/eclipse/egit/core/test/TestRepository.dispose:()V
       7: aload_0       
       8: aconst_null   
       9: putfield      #84                 // Field repository:Lorg/eclipse/jgit/lib/Repository;
      12: aload_0       
      13: invokespecial #95                 // Method org/eclipse/egit/core/test/GitTestCase.tearDown:()V
      16: return        

  public void testCommitAddedToIndexDeletedInWorkspace() throws java.lang.Exception;
    Code:
       0: aload_0       
       1: getfield      #99                 // Field testUtils:Lorg/eclipse/egit/core/test/TestUtils;
       4: aload_0       
       5: getfield      #42                 // Field project:Lorg/eclipse/egit/core/test/TestProject;
       8: invokevirtual #46                 // Method org/eclipse/egit/core/test/TestProject.getProject:()Lorg/eclipse/core/resources/IProject;
      11: ldc           #103                // String foo/a.txt
      13: ldc           #105                // String some text
      15: invokevirtual #107                // Method org/eclipse/egit/core/test/TestUtils.addFileToProject:(Lorg/eclipse/core/resources/IProject;Ljava/lang/String;Ljava/lang/String;)Lorg/eclipse/core/resources/IFile;
      18: pop           
      19: aload_0       
      20: getfield      #28                 // Field resources:Ljava/util/List;
      23: aload_0       
      24: getfield      #42                 // Field project:Lorg/eclipse/egit/core/test/TestProject;
      27: invokevirtual #46                 // Method org/eclipse/egit/core/test/TestProject.getProject:()Lorg/eclipse/core/resources/IProject;
      30: ldc           #113                // String foo
      32: invokeinterface #115,  2          // InterfaceMethod org/eclipse/core/resources/IProject.getFolder:(Ljava/lang/String;)Lorg/eclipse/core/resources/IFolder;
      37: invokeinterface #119,  2          // InterfaceMethod java/util/List.add:(Ljava/lang/Object;)Z
      42: pop           
      43: new           #125                // class org/eclipse/egit/core/op/AddToIndexOperation
      46: dup           
      47: aload_0       
      48: getfield      #28                 // Field resources:Ljava/util/List;
      51: invokespecial #127                // Method org/eclipse/egit/core/op/AddToIndexOperation."<init>":(Ljava/util/Collection;)V
      54: aconst_null   
      55: invokevirtual #130                // Method org/eclipse/egit/core/op/AddToIndexOperation.execute:(Lorg/eclipse/core/runtime/IProgressMonitor;)V
      58: new           #134                // class org/eclipse/egit/core/op/CommitOperation
      61: dup           
      62: aconst_null   
      63: aconst_null   
      64: ldc           #136                // String The Author <The.author@some.com>
      66: ldc           #138                // String The Commiter <The.committer@some.com>
      68: ldc           #140                // String first commit
      70: invokespecial #142                // Method org/eclipse/egit/core/op/CommitOperation."<init>":([Lorg/eclipse/core/resources/IFile;Ljava/util/Collection;Ljava/lang/String;Ljava/lang/String;Ljava/lang/String;)V
      73: astore_1      
      74: aload_1       
      75: iconst_1      
      76: invokevirtual #145                // Method org/eclipse/egit/core/op/CommitOperation.setCommitAll:(Z)V
      79: aload_1       
      80: aload_0       
      81: getfield      #84                 // Field repository:Lorg/eclipse/jgit/lib/Repository;
      84: invokevirtual #149                // Method org/eclipse/egit/core/op/CommitOperation.setRepository:(Lorg/eclipse/jgit/lib/Repository;)V
      87: aload_1       
      88: aconst_null   
      89: invokevirtual #153                // Method org/eclipse/egit/core/op/CommitOperation.execute:(Lorg/eclipse/core/runtime/IProgressMonitor;)V
      92: aload_0       
      93: getfield      #99                 // Field testUtils:Lorg/eclipse/egit/core/test/TestUtils;
      96: aload_0       
      97: getfield      #42                 // Field project:Lorg/eclipse/egit/core/test/TestProject;
     100: invokevirtual #46                 // Method org/eclipse/egit/core/test/TestProject.getProject:()Lorg/eclipse/core/resources/IProject;
     103: ldc           #154                // String zar/b.txt
     105: ldc           #105                // String some text
     107: invokevirtual #107                // Method org/eclipse/egit/core/test/TestUtils.addFileToProject:(Lorg/eclipse/core/resources/IProject;Ljava/lang/String;Ljava/lang/String;)Lorg/eclipse/core/resources/IFile;
     110: pop           
     111: aload_0       
     112: getfield      #28                 // Field resources:Ljava/util/List;
     115: aload_0       
     116: getfield      #42                 // Field project:Lorg/eclipse/egit/core/test/TestProject;
     119: invokevirtual #46                 // Method org/eclipse/egit/core/test/TestProject.getProject:()Lorg/eclipse/core/resources/IProject;
     122: ldc           #156                // String zar
     124: invokeinterface #115,  2          // InterfaceMethod org/eclipse/core/resources/IProject.getFolder:(Ljava/lang/String;)Lorg/eclipse/core/resources/IFolder;
     129: invokeinterface #119,  2          // InterfaceMethod java/util/List.add:(Ljava/lang/Object;)Z
     134: pop           
     135: new           #125                // class org/eclipse/egit/core/op/AddToIndexOperation
     138: dup           
     139: aload_0       
     140: getfield      #28                 // Field resources:Ljava/util/List;
     143: invokespecial #127                // Method org/eclipse/egit/core/op/AddToIndexOperation."<init>":(Ljava/util/Collection;)V
     146: aconst_null   
     147: invokevirtual #130                // Method org/eclipse/egit/core/op/AddToIndexOperation.execute:(Lorg/eclipse/core/runtime/IProgressMonitor;)V
     150: aload_0       
     151: getfield      #42                 // Field project:Lorg/eclipse/egit/core/test/TestProject;
     154: invokevirtual #46                 // Method org/eclipse/egit/core/test/TestProject.getProject:()Lorg/eclipse/core/resources/IProject;
     157: ldc           #154                // String zar/b.txt
     159: invokeinterface #158,  2          // InterfaceMethod org/eclipse/core/resources/IProject.getFile:(Ljava/lang/String;)Lorg/eclipse/core/resources/IFile;
     164: astore_2      
     165: aload_2       
     166: invokeinterface #162,  1          // InterfaceMethod org/eclipse/core/resources/IFile.getLocation:()Lorg/eclipse/core/runtime/IPath;
     171: astore_3      
     172: new           #168                // class java/lang/StringBuilder
     175: dup           
     176: ldc           #170                // String could not delete file 
     178: invokespecial #172                // Method java/lang/StringBuilder."<init>":(Ljava/lang/String;)V
     181: aload_3       
     182: invokeinterface #175,  1          // InterfaceMethod org/eclipse/core/runtime/IPath.toOSString:()Ljava/lang/String;
     187: invokevirtual #180                // Method java/lang/StringBuilder.append:(Ljava/lang/String;)Ljava/lang/StringBuilder;
     190: invokevirtual #184                // Method java/lang/StringBuilder.toString:()Ljava/lang/String;
     193: aload_3       
     194: invokeinterface #187,  1          // InterfaceMethod org/eclipse/core/runtime/IPath.toFile:()Ljava/io/File;
     199: invokevirtual #191                // Method java/io/File.delete:()Z
     202: invokestatic  #195                // Method org/junit/Assert.assertTrue:(Ljava/lang/String;Z)V
     205: aload_2       
     206: iconst_0      
     207: aconst_null   
     208: invokeinterface #201,  3          // InterfaceMethod org/eclipse/core/resources/IFile.refreshLocal:(ILorg/eclipse/core/runtime/IProgressMonitor;)V
     213: aload_0       
     214: getfield      #42                 // Field project:Lorg/eclipse/egit/core/test/TestProject;
     217: invokevirtual #46                 // Method org/eclipse/egit/core/test/TestProject.getProject:()Lorg/eclipse/core/resources/IProject;
     220: ldc           #154                // String zar/b.txt
     222: invokeinterface #158,  2          // InterfaceMethod org/eclipse/core/resources/IProject.getFile:(Ljava/lang/String;)Lorg/eclipse/core/resources/IFile;
     227: invokeinterface #205,  1          // InterfaceMethod org/eclipse/core/resources/IFile.exists:()Z
     232: invokestatic  #208                // Method org/junit/Assert.assertFalse:(Z)V
     235: iconst_1      
     236: anewarray     #163                // class org/eclipse/core/resources/IFile
     239: dup           
     240: iconst_0      
     241: aload_0       
     242: getfield      #42                 // Field project:Lorg/eclipse/egit/core/test/TestProject;
     245: invokevirtual #46                 // Method org/eclipse/egit/core/test/TestProject.getProject:()Lorg/eclipse/core/resources/IProject;
     248: ldc           #154                // String zar/b.txt
     250: invokeinterface #158,  2          // InterfaceMethod org/eclipse/core/resources/IProject.getFile:(Ljava/lang/String;)Lorg/eclipse/core/resources/IFile;
     255: aastore       
     256: astore        4
     258: new           #134                // class org/eclipse/egit/core/op/CommitOperation
     261: dup           
     262: aload         4
     264: aconst_null   
     265: ldc           #136                // String The Author <The.author@some.com>
     267: ldc           #138                // String The Commiter <The.committer@some.com>
     269: ldc           #140                // String first commit
     271: invokespecial #142                // Method org/eclipse/egit/core/op/CommitOperation."<init>":([Lorg/eclipse/core/resources/IFile;Ljava/util/Collection;Ljava/lang/String;Ljava/lang/String;Ljava/lang/String;)V
     274: astore_1      
     275: aload_1       
     276: aload_0       
     277: getfield      #84                 // Field repository:Lorg/eclipse/jgit/lib/Repository;
     280: invokevirtual #149                // Method org/eclipse/egit/core/op/CommitOperation.setRepository:(Lorg/eclipse/jgit/lib/Repository;)V
     283: aload_1       
     284: aconst_null   
     285: invokevirtual #153                // Method org/eclipse/egit/core/op/CommitOperation.execute:(Lorg/eclipse/core/runtime/IProgressMonitor;)V
     288: ldc           #211                // String expected CoreException
     290: invokestatic  #213                // Method org/junit/Assert.fail:(Ljava/lang/String;)V
     293: goto          311
     296: astore        5
     298: ldc           #216                // String No changes
     300: aload         5
     302: invokevirtual #218                // Method org/eclipse/core/runtime/CoreException.getCause:()Ljava/lang/Throwable;
     305: invokevirtual #224                // Method java/lang/Throwable.getMessage:()Ljava/lang/String;
     308: invokestatic  #229                // Method org/junit/Assert.assertEquals:(Ljava/lang/Object;Ljava/lang/Object;)V
     311: aconst_null   
     312: astore        5
     314: aconst_null   
     315: astore        6
     317: new           #233                // class org/eclipse/jgit/treewalk/TreeWalk
     320: dup           
     321: aload_0       
     322: getfield      #84                 // Field repository:Lorg/eclipse/jgit/lib/Repository;
     325: invokespecial #235                // Method org/eclipse/jgit/treewalk/TreeWalk."<init>":(Lorg/eclipse/jgit/lib/Repository;)V
     328: astore        7
     330: aload         7
     332: aload_0       
     333: getfield      #84                 // Field repository:Lorg/eclipse/jgit/lib/Repository;
     336: ldc           #237                // String HEAD^{tree}
     338: invokevirtual #239                // Method org/eclipse/jgit/lib/Repository.resolve:(Ljava/lang/String;)Lorg/eclipse/jgit/lib/ObjectId;
     341: invokevirtual #245                // Method org/eclipse/jgit/treewalk/TreeWalk.addTree:(Lorg/eclipse/jgit/lib/AnyObjectId;)I
     344: pop           
     345: aload         7
     347: invokevirtual #249                // Method org/eclipse/jgit/treewalk/TreeWalk.next:()Z
     350: invokestatic  #252                // Method org/junit/Assert.assertTrue:(Z)V
     353: ldc           #113                // String foo
     355: aload         7
     357: invokevirtual #254                // Method org/eclipse/jgit/treewalk/TreeWalk.getPathString:()Ljava/lang/String;
     360: invokestatic  #229                // Method org/junit/Assert.assertEquals:(Ljava/lang/Object;Ljava/lang/Object;)V
     363: aload         7
     365: invokevirtual #257                // Method org/eclipse/jgit/treewalk/TreeWalk.enterSubtree:()V
     368: aload         7
     370: invokevirtual #249                // Method org/eclipse/jgit/treewalk/TreeWalk.next:()Z
     373: invokestatic  #252                // Method org/junit/Assert.assertTrue:(Z)V
     376: ldc           #103                // String foo/a.txt
     378: aload         7
     380: invokevirtual #254                // Method org/eclipse/jgit/treewalk/TreeWalk.getPathString:()Ljava/lang/String;
     383: invokestatic  #229                // Method org/junit/Assert.assertEquals:(Ljava/lang/Object;Ljava/lang/Object;)V
     386: aload         7
     388: invokevirtual #249                // Method org/eclipse/jgit/treewalk/TreeWalk.next:()Z
     391: invokestatic  #208                // Method org/junit/Assert.assertFalse:(Z)V
     394: aload         7
     396: ifnull        453
     399: aload         7
     401: invokevirtual #260                // Method org/eclipse/jgit/treewalk/TreeWalk.close:()V
     404: goto          453
     407: astore        5
     409: aload         7
     411: ifnull        419
     414: aload         7
     416: invokevirtual #260                // Method org/eclipse/jgit/treewalk/TreeWalk.close:()V
     419: aload         5
     421: athrow        
     422: astore        6
     424: aload         5
     426: ifnonnull     436
     429: aload         6
     431: astore        5
     433: goto          450
     436: aload         5
     438: aload         6
     440: if_acmpeq     450
     443: aload         5
     445: aload         6
     447: invokevirtual #263                // Method java/lang/Throwable.addSuppressed:(Ljava/lang/Throwable;)V
     450: aload         5
     452: athrow        
     453: return        
    Exception table:
       from    to  target type
         283   293   296   Class org/eclipse/core/runtime/CoreException
         330   394   407   any
         317   422   422   any

  public void testCommitAll() throws java.lang.Exception;
    Code:
       0: aload_0       
       1: getfield      #99                 // Field testUtils:Lorg/eclipse/egit/core/test/TestUtils;
       4: aload_0       
       5: getfield      #42                 // Field project:Lorg/eclipse/egit/core/test/TestProject;
       8: invokevirtual #46                 // Method org/eclipse/egit/core/test/TestProject.getProject:()Lorg/eclipse/core/resources/IProject;
      11: ldc_w         #282                // String sub/a.txt
      14: ldc           #105                // String some text
      16: invokevirtual #107                // Method org/eclipse/egit/core/test/TestUtils.addFileToProject:(Lorg/eclipse/core/resources/IProject;Ljava/lang/String;Ljava/lang/String;)Lorg/eclipse/core/resources/IFile;
      19: astore_1      
      20: aload_0       
      21: getfield      #99                 // Field testUtils:Lorg/eclipse/egit/core/test/TestUtils;
      24: aload_0       
      25: getfield      #42                 // Field project:Lorg/eclipse/egit/core/test/TestProject;
      28: invokevirtual #46                 // Method org/eclipse/egit/core/test/TestProject.getProject:()Lorg/eclipse/core/resources/IProject;
      31: ldc_w         #284                // String sub/b.txt
      34: ldc           #105                // String some text
      36: invokevirtual #107                // Method org/eclipse/egit/core/test/TestUtils.addFileToProject:(Lorg/eclipse/core/resources/IProject;Ljava/lang/String;Ljava/lang/String;)Lorg/eclipse/core/resources/IFile;
      39: pop           
      40: aload_0       
      41: getfield      #28                 // Field resources:Ljava/util/List;
      44: aload_0       
      45: getfield      #42                 // Field project:Lorg/eclipse/egit/core/test/TestProject;
      48: invokevirtual #46                 // Method org/eclipse/egit/core/test/TestProject.getProject:()Lorg/eclipse/core/resources/IProject;
      51: ldc_w         #286                // String sub
      54: invokeinterface #115,  2          // InterfaceMethod org/eclipse/core/resources/IProject.getFolder:(Ljava/lang/String;)Lorg/eclipse/core/resources/IFolder;
      59: invokeinterface #119,  2          // InterfaceMethod java/util/List.add:(Ljava/lang/Object;)Z
      64: pop           
      65: new           #125                // class org/eclipse/egit/core/op/AddToIndexOperation
      68: dup           
      69: aload_0       
      70: getfield      #28                 // Field resources:Ljava/util/List;
      73: invokespecial #127                // Method org/eclipse/egit/core/op/AddToIndexOperation."<init>":(Ljava/util/Collection;)V
      76: aconst_null   
      77: invokevirtual #130                // Method org/eclipse/egit/core/op/AddToIndexOperation.execute:(Lorg/eclipse/core/runtime/IProgressMonitor;)V
      80: new           #134                // class org/eclipse/egit/core/op/CommitOperation
      83: dup           
      84: aconst_null   
      85: aconst_null   
      86: ldc           #136                // String The Author <The.author@some.com>
      88: ldc           #138                // String The Commiter <The.committer@some.com>
      90: ldc           #140                // String first commit
      92: invokespecial #142                // Method org/eclipse/egit/core/op/CommitOperation."<init>":([Lorg/eclipse/core/resources/IFile;Ljava/util/Collection;Ljava/lang/String;Ljava/lang/String;Ljava/lang/String;)V
      95: astore_2      
      96: aload_2       
      97: iconst_1      
      98: invokevirtual #145                // Method org/eclipse/egit/core/op/CommitOperation.setCommitAll:(Z)V
     101: aload_2       
     102: aload_0       
     103: getfield      #84                 // Field repository:Lorg/eclipse/jgit/lib/Repository;
     106: invokevirtual #149                // Method org/eclipse/egit/core/op/CommitOperation.setRepository:(Lorg/eclipse/jgit/lib/Repository;)V
     109: aload_2       
     110: aconst_null   
     111: invokevirtual #153                // Method org/eclipse/egit/core/op/CommitOperation.execute:(Lorg/eclipse/core/runtime/IProgressMonitor;)V
     114: new           #288                // class org/eclipse/jgit/api/Git
     117: dup           
     118: aload_0       
     119: getfield      #84                 // Field repository:Lorg/eclipse/jgit/lib/Repository;
     122: invokespecial #290                // Method org/eclipse/jgit/api/Git."<init>":(Lorg/eclipse/jgit/lib/Repository;)V
     125: astore_3      
     126: aload_3       
     127: invokevirtual #291                // Method org/eclipse/jgit/api/Git.log:()Lorg/eclipse/jgit/api/LogCommand;
     130: invokevirtual #295                // Method org/eclipse/jgit/api/LogCommand.call:()Ljava/lang/Iterable;
     133: invokeinterface #301,  1          // InterfaceMethod java/lang/Iterable.iterator:()Ljava/util/Iterator;
     138: astore        4
     140: aload         4
     142: invokeinterface #307,  1          // InterfaceMethod java/util/Iterator.next:()Ljava/lang/Object;
     147: checkcast     #312                // class org/eclipse/jgit/revwalk/RevCommit
     150: astore        5
     152: aload         5
     154: invokevirtual #314                // Method org/eclipse/jgit/revwalk/RevCommit.getCommitTime:()I
     157: ifle          164
     160: iconst_1      
     161: goto          165
     164: iconst_0      
     165: invokestatic  #252                // Method org/junit/Assert.assertTrue:(Z)V
     168: ldc           #140                // String first commit
     170: aload         5
     172: invokevirtual #318                // Method org/eclipse/jgit/revwalk/RevCommit.getFullMessage:()Ljava/lang/String;
     175: invokestatic  #229                // Method org/junit/Assert.assertEquals:(Ljava/lang/Object;Ljava/lang/Object;)V
     178: aload_0       
     179: getfield      #99                 // Field testUtils:Lorg/eclipse/egit/core/test/TestUtils;
     182: aload_0       
     183: getfield      #42                 // Field project:Lorg/eclipse/egit/core/test/TestProject;
     186: invokevirtual #46                 // Method org/eclipse/egit/core/test/TestProject.getProject:()Lorg/eclipse/core/resources/IProject;
     189: aload_1       
     190: ldc_w         #321                // String changed text
     193: invokevirtual #323                // Method org/eclipse/egit/core/test/TestUtils.changeContentOfFile:(Lorg/eclipse/core/resources/IProject;Lorg/eclipse/core/resources/IFile;Ljava/lang/String;)Lorg/eclipse/core/resources/IFile;
     196: pop           
     197: new           #134                // class org/eclipse/egit/core/op/CommitOperation
     200: dup           
     201: aconst_null   
     202: aconst_null   
     203: ldc           #136                // String The Author <The.author@some.com>
     205: ldc           #138                // String The Commiter <The.committer@some.com>
     207: ldc_w         #327                // String second commit
     210: invokespecial #142                // Method org/eclipse/egit/core/op/CommitOperation."<init>":([Lorg/eclipse/core/resources/IFile;Ljava/util/Collection;Ljava/lang/String;Ljava/lang/String;Ljava/lang/String;)V
     213: astore_2      
     214: aload_2       
     215: iconst_1      
     216: invokevirtual #145                // Method org/eclipse/egit/core/op/CommitOperation.setCommitAll:(Z)V
     219: aload_2       
     220: aload_0       
     221: getfield      #84                 // Field repository:Lorg/eclipse/jgit/lib/Repository;
     224: invokevirtual #149                // Method org/eclipse/egit/core/op/CommitOperation.setRepository:(Lorg/eclipse/jgit/lib/Repository;)V
     227: aload_2       
     228: aconst_null   
     229: invokevirtual #153                // Method org/eclipse/egit/core/op/CommitOperation.execute:(Lorg/eclipse/core/runtime/IProgressMonitor;)V
     232: new           #288                // class org/eclipse/jgit/api/Git
     235: dup           
     236: aload_0       
     237: getfield      #84                 // Field repository:Lorg/eclipse/jgit/lib/Repository;
     240: invokespecial #290                // Method org/eclipse/jgit/api/Git."<init>":(Lorg/eclipse/jgit/lib/Repository;)V
     243: astore_3      
     244: aload_3       
     245: invokevirtual #291                // Method org/eclipse/jgit/api/Git.log:()Lorg/eclipse/jgit/api/LogCommand;
     248: invokevirtual #295                // Method org/eclipse/jgit/api/LogCommand.call:()Ljava/lang/Iterable;
     251: invokeinterface #301,  1          // InterfaceMethod java/lang/Iterable.iterator:()Ljava/util/Iterator;
     256: astore        4
     258: aload         4
     260: invokeinterface #307,  1          // InterfaceMethod java/util/Iterator.next:()Ljava/lang/Object;
     265: checkcast     #312                // class org/eclipse/jgit/revwalk/RevCommit
     268: astore        6
     270: aload         6
     272: invokevirtual #314                // Method org/eclipse/jgit/revwalk/RevCommit.getCommitTime:()I
     275: ifle          282
     278: iconst_1      
     279: goto          283
     282: iconst_0      
     283: invokestatic  #252                // Method org/junit/Assert.assertTrue:(Z)V
     286: ldc_w         #327                // String second commit
     289: aload         6
     291: invokevirtual #318                // Method org/eclipse/jgit/revwalk/RevCommit.getFullMessage:()Ljava/lang/String;
     294: invokestatic  #229                // Method org/junit/Assert.assertEquals:(Ljava/lang/Object;Ljava/lang/Object;)V
     297: aload         6
     299: iconst_0      
     300: invokevirtual #329                // Method org/eclipse/jgit/revwalk/RevCommit.getParent:(I)Lorg/eclipse/jgit/revwalk/RevCommit;
     303: aload         5
     305: invokevirtual #333                // Method org/eclipse/jgit/revwalk/RevCommit.equals:(Lorg/eclipse/jgit/lib/AnyObjectId;)Z
     308: pop           
     309: ldc_w         #337                // String The Author
     312: aload         6
     314: invokevirtual #339                // Method org/eclipse/jgit/revwalk/RevCommit.getAuthorIdent:()Lorg/eclipse/jgit/lib/PersonIdent;
     317: invokevirtual #343                // Method org/eclipse/jgit/lib/PersonIdent.getName:()Ljava/lang/String;
     320: invokestatic  #229                // Method org/junit/Assert.assertEquals:(Ljava/lang/Object;Ljava/lang/Object;)V
     323: ldc_w         #348                // String The.author@some.com
     326: aload         6
     328: invokevirtual #339                // Method org/eclipse/jgit/revwalk/RevCommit.getAuthorIdent:()Lorg/eclipse/jgit/lib/PersonIdent;
     331: invokevirtual #350                // Method org/eclipse/jgit/lib/PersonIdent.getEmailAddress:()Ljava/lang/String;
     334: invokestatic  #229                // Method org/junit/Assert.assertEquals:(Ljava/lang/Object;Ljava/lang/Object;)V
     337: ldc_w         #353                // String The Commiter
     340: aload         6
     342: invokevirtual #355                // Method org/eclipse/jgit/revwalk/RevCommit.getCommitterIdent:()Lorg/eclipse/jgit/lib/PersonIdent;
     345: invokevirtual #343                // Method org/eclipse/jgit/lib/PersonIdent.getName:()Ljava/lang/String;
     348: invokestatic  #229                // Method org/junit/Assert.assertEquals:(Ljava/lang/Object;Ljava/lang/Object;)V
     351: ldc_w         #358                // String The.committer@some.com
     354: aload         6
     356: invokevirtual #355                // Method org/eclipse/jgit/revwalk/RevCommit.getCommitterIdent:()Lorg/eclipse/jgit/lib/PersonIdent;
     359: invokevirtual #350                // Method org/eclipse/jgit/lib/PersonIdent.getEmailAddress:()Ljava/lang/String;
     362: invokestatic  #229                // Method org/junit/Assert.assertEquals:(Ljava/lang/Object;Ljava/lang/Object;)V
     365: return        

  public void testCommitEmptiedTree() throws java.lang.Exception;
    Code:
       0: aload_0       
       1: getfield      #99                 // Field testUtils:Lorg/eclipse/egit/core/test/TestUtils;
       4: aload_0       
       5: getfield      #42                 // Field project:Lorg/eclipse/egit/core/test/TestProject;
       8: invokevirtual #46                 // Method org/eclipse/egit/core/test/TestProject.getProject:()Lorg/eclipse/core/resources/IProject;
      11: ldc_w         #371                // String sub1/a.txt
      14: ldc           #105                // String some text
      16: invokevirtual #107                // Method org/eclipse/egit/core/test/TestUtils.addFileToProject:(Lorg/eclipse/core/resources/IProject;Ljava/lang/String;Ljava/lang/String;)Lorg/eclipse/core/resources/IFile;
      19: pop           
      20: aload_0       
      21: getfield      #99                 // Field testUtils:Lorg/eclipse/egit/core/test/TestUtils;
      24: aload_0       
      25: getfield      #42                 // Field project:Lorg/eclipse/egit/core/test/TestProject;
      28: invokevirtual #46                 // Method org/eclipse/egit/core/test/TestProject.getProject:()Lorg/eclipse/core/resources/IProject;
      31: ldc_w         #373                // String sub2/b.txt
      34: ldc           #105                // String some text
      36: invokevirtual #107                // Method org/eclipse/egit/core/test/TestUtils.addFileToProject:(Lorg/eclipse/core/resources/IProject;Ljava/lang/String;Ljava/lang/String;)Lorg/eclipse/core/resources/IFile;
      39: pop           
      40: aload_0       
      41: getfield      #28                 // Field resources:Ljava/util/List;
      44: aload_0       
      45: getfield      #42                 // Field project:Lorg/eclipse/egit/core/test/TestProject;
      48: invokevirtual #46                 // Method org/eclipse/egit/core/test/TestProject.getProject:()Lorg/eclipse/core/resources/IProject;
      51: ldc_w         #375                // String sub1
      54: invokeinterface #115,  2          // InterfaceMethod org/eclipse/core/resources/IProject.getFolder:(Ljava/lang/String;)Lorg/eclipse/core/resources/IFolder;
      59: invokeinterface #119,  2          // InterfaceMethod java/util/List.add:(Ljava/lang/Object;)Z
      64: pop           
      65: aload_0       
      66: getfield      #28                 // Field resources:Ljava/util/List;
      69: aload_0       
      70: getfield      #42                 // Field project:Lorg/eclipse/egit/core/test/TestProject;
      73: invokevirtual #46                 // Method org/eclipse/egit/core/test/TestProject.getProject:()Lorg/eclipse/core/resources/IProject;
      76: ldc_w         #377                // String sub2
      79: invokeinterface #115,  2          // InterfaceMethod org/eclipse/core/resources/IProject.getFolder:(Ljava/lang/String;)Lorg/eclipse/core/resources/IFolder;
      84: invokeinterface #119,  2          // InterfaceMethod java/util/List.add:(Ljava/lang/Object;)Z
      89: pop           
      90: new           #125                // class org/eclipse/egit/core/op/AddToIndexOperation
      93: dup           
      94: aload_0       
      95: getfield      #28                 // Field resources:Ljava/util/List;
      98: invokespecial #127                // Method org/eclipse/egit/core/op/AddToIndexOperation."<init>":(Ljava/util/Collection;)V
     101: aconst_null   
     102: invokevirtual #130                // Method org/eclipse/egit/core/op/AddToIndexOperation.execute:(Lorg/eclipse/core/runtime/IProgressMonitor;)V
     105: new           #134                // class org/eclipse/egit/core/op/CommitOperation
     108: dup           
     109: aconst_null   
     110: aconst_null   
     111: ldc           #136                // String The Author <The.author@some.com>
     113: ldc           #138                // String The Commiter <The.committer@some.com>
     115: ldc           #140                // String first commit
     117: invokespecial #142                // Method org/eclipse/egit/core/op/CommitOperation."<init>":([Lorg/eclipse/core/resources/IFile;Ljava/util/Collection;Ljava/lang/String;Ljava/lang/String;Ljava/lang/String;)V
     120: astore_1      
     121: aload_1       
     122: iconst_1      
     123: invokevirtual #145                // Method org/eclipse/egit/core/op/CommitOperation.setCommitAll:(Z)V
     126: aload_1       
     127: aload_0       
     128: getfield      #84                 // Field repository:Lorg/eclipse/jgit/lib/Repository;
     131: invokevirtual #149                // Method org/eclipse/egit/core/op/CommitOperation.setRepository:(Lorg/eclipse/jgit/lib/Repository;)V
     134: aload_1       
     135: aconst_null   
     136: invokevirtual #153                // Method org/eclipse/egit/core/op/CommitOperation.execute:(Lorg/eclipse/core/runtime/IProgressMonitor;)V
     139: new           #288                // class org/eclipse/jgit/api/Git
     142: dup           
     143: aload_0       
     144: getfield      #84                 // Field repository:Lorg/eclipse/jgit/lib/Repository;
     147: invokespecial #290                // Method org/eclipse/jgit/api/Git."<init>":(Lorg/eclipse/jgit/lib/Repository;)V
     150: astore_2      
     151: aload_2       
     152: invokevirtual #291                // Method org/eclipse/jgit/api/Git.log:()Lorg/eclipse/jgit/api/LogCommand;
     155: invokevirtual #295                // Method org/eclipse/jgit/api/LogCommand.call:()Ljava/lang/Iterable;
     158: invokeinterface #301,  1          // InterfaceMethod java/lang/Iterable.iterator:()Ljava/util/Iterator;
     163: astore_3      
     164: aload_3       
     165: invokeinterface #307,  1          // InterfaceMethod java/util/Iterator.next:()Ljava/lang/Object;
     170: checkcast     #312                // class org/eclipse/jgit/revwalk/RevCommit
     173: astore        4
     175: aconst_null   
     176: astore        5
     178: aconst_null   
     179: astore        6
     181: new           #233                // class org/eclipse/jgit/treewalk/TreeWalk
     184: dup           
     185: aload_0       
     186: getfield      #84                 // Field repository:Lorg/eclipse/jgit/lib/Repository;
     189: invokespecial #235                // Method org/eclipse/jgit/treewalk/TreeWalk."<init>":(Lorg/eclipse/jgit/lib/Repository;)V
     192: astore        7
     194: aload         7
     196: aload         4
     198: invokevirtual #379                // Method org/eclipse/jgit/revwalk/RevCommit.getTree:()Lorg/eclipse/jgit/revwalk/RevTree;
     201: invokevirtual #383                // Method org/eclipse/jgit/revwalk/RevTree.getId:()Lorg/eclipse/jgit/lib/ObjectId;
     204: invokevirtual #245                // Method org/eclipse/jgit/treewalk/TreeWalk.addTree:(Lorg/eclipse/jgit/lib/AnyObjectId;)I
     207: pop           
     208: aload         7
     210: iconst_1      
     211: invokevirtual #389                // Method org/eclipse/jgit/treewalk/TreeWalk.setRecursive:(Z)V
     214: aload         7
     216: iconst_1      
     217: invokevirtual #392                // Method org/eclipse/jgit/treewalk/TreeWalk.setPostOrderTraversal:(Z)V
     220: aload         7
     222: invokevirtual #249                // Method org/eclipse/jgit/treewalk/TreeWalk.next:()Z
     225: invokestatic  #252                // Method org/junit/Assert.assertTrue:(Z)V
     228: ldc_w         #371                // String sub1/a.txt
     231: aload         7
     233: invokevirtual #254                // Method org/eclipse/jgit/treewalk/TreeWalk.getPathString:()Ljava/lang/String;
     236: invokestatic  #229                // Method org/junit/Assert.assertEquals:(Ljava/lang/Object;Ljava/lang/Object;)V
     239: aload         7
     241: invokevirtual #249                // Method org/eclipse/jgit/treewalk/TreeWalk.next:()Z
     244: invokestatic  #252                // Method org/junit/Assert.assertTrue:(Z)V
     247: ldc_w         #375                // String sub1
     250: aload         7
     252: invokevirtual #254                // Method org/eclipse/jgit/treewalk/TreeWalk.getPathString:()Ljava/lang/String;
     255: invokestatic  #229                // Method org/junit/Assert.assertEquals:(Ljava/lang/Object;Ljava/lang/Object;)V
     258: aload         7
     260: invokevirtual #249                // Method org/eclipse/jgit/treewalk/TreeWalk.next:()Z
     263: invokestatic  #252                // Method org/junit/Assert.assertTrue:(Z)V
     266: ldc_w         #373                // String sub2/b.txt
     269: aload         7
     271: invokevirtual #254                // Method org/eclipse/jgit/treewalk/TreeWalk.getPathString:()Ljava/lang/String;
     274: invokestatic  #229                // Method org/junit/Assert.assertEquals:(Ljava/lang/Object;Ljava/lang/Object;)V
     277: aload         7
     279: invokevirtual #249                // Method org/eclipse/jgit/treewalk/TreeWalk.next:()Z
     282: invokestatic  #252                // Method org/junit/Assert.assertTrue:(Z)V
     285: ldc_w         #377                // String sub2
     288: aload         7
     290: invokevirtual #254                // Method org/eclipse/jgit/treewalk/TreeWalk.getPathString:()Ljava/lang/String;
     293: invokestatic  #229                // Method org/junit/Assert.assertEquals:(Ljava/lang/Object;Ljava/lang/Object;)V
     296: aload         7
     298: invokevirtual #249                // Method org/eclipse/jgit/treewalk/TreeWalk.next:()Z
     301: invokestatic  #208                // Method org/junit/Assert.assertFalse:(Z)V
     304: aload         7
     306: ifnull        363
     309: aload         7
     311: invokevirtual #260                // Method org/eclipse/jgit/treewalk/TreeWalk.close:()V
     314: goto          363
     317: astore        5
     319: aload         7
     321: ifnull        329
     324: aload         7
     326: invokevirtual #260                // Method org/eclipse/jgit/treewalk/TreeWalk.close:()V
     329: aload         5
     331: athrow        
     332: astore        6
     334: aload         5
     336: ifnonnull     346
     339: aload         6
     341: astore        5
     343: goto          360
     346: aload         5
     348: aload         6
     350: if_acmpeq     360
     353: aload         5
     355: aload         6
     357: invokevirtual #263                // Method java/lang/Throwable.addSuppressed:(Ljava/lang/Throwable;)V
     360: aload         5
     362: athrow        
     363: aload_0       
     364: getfield      #42                 // Field project:Lorg/eclipse/egit/core/test/TestProject;
     367: invokevirtual #46                 // Method org/eclipse/egit/core/test/TestProject.getProject:()Lorg/eclipse/core/resources/IProject;
     370: ldc_w         #377                // String sub2
     373: invokeinterface #115,  2          // InterfaceMethod org/eclipse/core/resources/IProject.getFolder:(Ljava/lang/String;)Lorg/eclipse/core/resources/IFolder;
     378: iconst_1      
     379: aconst_null   
     380: invokeinterface #395,  3          // InterfaceMethod org/eclipse/core/resources/IFolder.delete:(ILorg/eclipse/core/runtime/IProgressMonitor;)V
     385: iconst_1      
     386: anewarray     #163                // class org/eclipse/core/resources/IFile
     389: dup           
     390: iconst_0      
     391: aload_0       
     392: getfield      #42                 // Field project:Lorg/eclipse/egit/core/test/TestProject;
     395: invokevirtual #46                 // Method org/eclipse/egit/core/test/TestProject.getProject:()Lorg/eclipse/core/resources/IProject;
     398: ldc_w         #373                // String sub2/b.txt
     401: invokeinterface #158,  2          // InterfaceMethod org/eclipse/core/resources/IProject.getFile:(Ljava/lang/String;)Lorg/eclipse/core/resources/IFile;
     406: aastore       
     407: astore        5
     409: new           #18                 // class java/util/ArrayList
     412: dup           
     413: invokespecial #20                 // Method java/util/ArrayList."<init>":()V
     416: astore        6
     418: aload         6
     420: aload         5
     422: iconst_0      
     423: aaload        
     424: invokevirtual #399                // Method java/util/ArrayList.add:(Ljava/lang/Object;)Z
     427: pop           
     428: new           #18                 // class java/util/ArrayList
     431: dup           
     432: invokespecial #20                 // Method java/util/ArrayList."<init>":()V
     435: astore        7
     437: new           #134                // class org/eclipse/egit/core/op/CommitOperation
     440: dup           
     441: aload         5
     443: aload         7
     445: ldc           #136                // String The Author <The.author@some.com>
     447: ldc           #138                // String The Commiter <The.committer@some.com>
     449: ldc_w         #327                // String second commit
     452: invokespecial #142                // Method org/eclipse/egit/core/op/CommitOperation."<init>":([Lorg/eclipse/core/resources/IFile;Ljava/util/Collection;Ljava/lang/String;Ljava/lang/String;Ljava/lang/String;)V
     455: astore_1      
     456: aload_1       
     457: iconst_0      
     458: invokevirtual #145                // Method org/eclipse/egit/core/op/CommitOperation.setCommitAll:(Z)V
     461: aload_1       
     462: aconst_null   
     463: invokevirtual #153                // Method org/eclipse/egit/core/op/CommitOperation.execute:(Lorg/eclipse/core/runtime/IProgressMonitor;)V
     466: new           #288                // class org/eclipse/jgit/api/Git
     469: dup           
     470: aload_0       
     471: getfield      #84                 // Field repository:Lorg/eclipse/jgit/lib/Repository;
     474: invokespecial #290                // Method org/eclipse/jgit/api/Git."<init>":(Lorg/eclipse/jgit/lib/Repository;)V
     477: astore_2      
     478: aload_2       
     479: invokevirtual #291                // Method org/eclipse/jgit/api/Git.log:()Lorg/eclipse/jgit/api/LogCommand;
     482: invokevirtual #295                // Method org/eclipse/jgit/api/LogCommand.call:()Ljava/lang/Iterable;
     485: invokeinterface #301,  1          // InterfaceMethod java/lang/Iterable.iterator:()Ljava/util/Iterator;
     490: astore_3      
     491: aload_3       
     492: invokeinterface #307,  1          // InterfaceMethod java/util/Iterator.next:()Ljava/lang/Object;
     497: checkcast     #312                // class org/eclipse/jgit/revwalk/RevCommit
     500: astore        4
     502: aconst_null   
     503: astore        8
     505: aconst_null   
     506: astore        9
     508: new           #233                // class org/eclipse/jgit/treewalk/TreeWalk
     511: dup           
     512: aload_0       
     513: getfield      #84                 // Field repository:Lorg/eclipse/jgit/lib/Repository;
     516: invokespecial #235                // Method org/eclipse/jgit/treewalk/TreeWalk."<init>":(Lorg/eclipse/jgit/lib/Repository;)V
     519: astore        10
     521: aload         10
     523: aload         4
     525: invokevirtual #379                // Method org/eclipse/jgit/revwalk/RevCommit.getTree:()Lorg/eclipse/jgit/revwalk/RevTree;
     528: invokevirtual #383                // Method org/eclipse/jgit/revwalk/RevTree.getId:()Lorg/eclipse/jgit/lib/ObjectId;
     531: invokevirtual #245                // Method org/eclipse/jgit/treewalk/TreeWalk.addTree:(Lorg/eclipse/jgit/lib/AnyObjectId;)I
     534: pop           
     535: aload         10
     537: iconst_1      
     538: invokevirtual #389                // Method org/eclipse/jgit/treewalk/TreeWalk.setRecursive:(Z)V
     541: aload         10
     543: iconst_1      
     544: invokevirtual #392                // Method org/eclipse/jgit/treewalk/TreeWalk.setPostOrderTraversal:(Z)V
     547: aload         10
     549: invokevirtual #249                // Method org/eclipse/jgit/treewalk/TreeWalk.next:()Z
     552: invokestatic  #252                // Method org/junit/Assert.assertTrue:(Z)V
     555: ldc_w         #371                // String sub1/a.txt
     558: aload         10
     560: invokevirtual #254                // Method org/eclipse/jgit/treewalk/TreeWalk.getPathString:()Ljava/lang/String;
     563: invokestatic  #229                // Method org/junit/Assert.assertEquals:(Ljava/lang/Object;Ljava/lang/Object;)V
     566: aload         10
     568: invokevirtual #249                // Method org/eclipse/jgit/treewalk/TreeWalk.next:()Z
     571: invokestatic  #252                // Method org/junit/Assert.assertTrue:(Z)V
     574: ldc_w         #375                // String sub1
     577: aload         10
     579: invokevirtual #254                // Method org/eclipse/jgit/treewalk/TreeWalk.getPathString:()Ljava/lang/String;
     582: invokestatic  #229                // Method org/junit/Assert.assertEquals:(Ljava/lang/Object;Ljava/lang/Object;)V
     585: aload         10
     587: invokevirtual #249                // Method org/eclipse/jgit/treewalk/TreeWalk.next:()Z
     590: invokestatic  #208                // Method org/junit/Assert.assertFalse:(Z)V
     593: aload         10
     595: ifnull        652
     598: aload         10
     600: invokevirtual #260                // Method org/eclipse/jgit/treewalk/TreeWalk.close:()V
     603: goto          652
     606: astore        8
     608: aload         10
     610: ifnull        618
     613: aload         10
     615: invokevirtual #260                // Method org/eclipse/jgit/treewalk/TreeWalk.close:()V
     618: aload         8
     620: athrow        
     621: astore        9
     623: aload         8
     625: ifnonnull     635
     628: aload         9
     630: astore        8
     632: goto          649
     635: aload         8
     637: aload         9
     639: if_acmpeq     649
     642: aload         8
     644: aload         9
     646: invokevirtual #263                // Method java/lang/Throwable.addSuppressed:(Ljava/lang/Throwable;)V
     649: aload         8
     651: athrow        
     652: return        
    Exception table:
       from    to  target type
         194   304   317   any
         181   332   332   any
         521   593   606   any
         508   621   621   any

  public void testCommitUntracked() throws java.lang.Exception;
    Code:
       0: aload_0       
       1: getfield      #99                 // Field testUtils:Lorg/eclipse/egit/core/test/TestUtils;
       4: aload_0       
       5: getfield      #42                 // Field project:Lorg/eclipse/egit/core/test/TestProject;
       8: invokevirtual #46                 // Method org/eclipse/egit/core/test/TestProject.getProject:()Lorg/eclipse/core/resources/IProject;
      11: ldc           #103                // String foo/a.txt
      13: ldc           #105                // String some text
      15: invokevirtual #107                // Method org/eclipse/egit/core/test/TestUtils.addFileToProject:(Lorg/eclipse/core/resources/IProject;Ljava/lang/String;Ljava/lang/String;)Lorg/eclipse/core/resources/IFile;
      18: astore_1      
      19: aload_0       
      20: getfield      #99                 // Field testUtils:Lorg/eclipse/egit/core/test/TestUtils;
      23: aload_0       
      24: getfield      #42                 // Field project:Lorg/eclipse/egit/core/test/TestProject;
      27: invokevirtual #46                 // Method org/eclipse/egit/core/test/TestProject.getProject:()Lorg/eclipse/core/resources/IProject;
      30: ldc_w         #405                // String foo/b.txt
      33: ldc           #105                // String some text
      35: invokevirtual #107                // Method org/eclipse/egit/core/test/TestUtils.addFileToProject:(Lorg/eclipse/core/resources/IProject;Ljava/lang/String;Ljava/lang/String;)Lorg/eclipse/core/resources/IFile;
      38: astore_2      
      39: aload_0       
      40: getfield      #99                 // Field testUtils:Lorg/eclipse/egit/core/test/TestUtils;
      43: aload_0       
      44: getfield      #42                 // Field project:Lorg/eclipse/egit/core/test/TestProject;
      47: invokevirtual #46                 // Method org/eclipse/egit/core/test/TestProject.getProject:()Lorg/eclipse/core/resources/IProject;
      50: ldc_w         #407                // String foo/c.txt
      53: ldc           #105                // String some text
      55: invokevirtual #107                // Method org/eclipse/egit/core/test/TestUtils.addFileToProject:(Lorg/eclipse/core/resources/IProject;Ljava/lang/String;Ljava/lang/String;)Lorg/eclipse/core/resources/IFile;
      58: pop           
      59: iconst_2      
      60: anewarray     #163                // class org/eclipse/core/resources/IFile
      63: dup           
      64: iconst_0      
      65: aload_1       
      66: aastore       
      67: dup           
      68: iconst_1      
      69: aload_2       
      70: aastore       
      71: astore_3      
      72: new           #134                // class org/eclipse/egit/core/op/CommitOperation
      75: dup           
      76: aload_3       
      77: aload_3       
      78: invokestatic  #409                // Method java/util/Arrays.asList:([Ljava/lang/Object;)Ljava/util/List;
      81: ldc           #136                // String The Author <The.author@some.com>
      83: ldc           #138                // String The Commiter <The.committer@some.com>
      85: ldc           #140                // String first commit
      87: invokespecial #142                // Method org/eclipse/egit/core/op/CommitOperation."<init>":([Lorg/eclipse/core/resources/IFile;Ljava/util/Collection;Ljava/lang/String;Ljava/lang/String;Ljava/lang/String;)V
      90: astore        4
      92: aload         4
      94: aconst_null   
      95: invokevirtual #153                // Method org/eclipse/egit/core/op/CommitOperation.execute:(Lorg/eclipse/core/runtime/IProgressMonitor;)V
      98: aload_0       
      99: getfield      #99                 // Field testUtils:Lorg/eclipse/egit/core/test/TestUtils;
     102: aload_0       
     103: getfield      #84                 // Field repository:Lorg/eclipse/jgit/lib/Repository;
     106: aload_0       
     107: aload_3       
     108: invokespecial #415                // Method getRepoRelativePaths:([Lorg/eclipse/core/resources/IFile;)[Ljava/lang/String;
     111: invokevirtual #419                // Method org/eclipse/egit/core/test/TestUtils.assertRepositoryContainsFiles:(Lorg/eclipse/jgit/lib/Repository;[Ljava/lang/String;)V
     114: return        

  private java.lang.String[] getRepoRelativePaths(org.eclipse.core.resources.IFile[]);
    Code:
       0: new           #18                 // class java/util/ArrayList
       3: dup           
       4: invokespecial #20                 // Method java/util/ArrayList."<init>":()V
       7: astore_2      
       8: aload_1       
       9: dup           
      10: astore        6
      12: arraylength   
      13: istore        5
      15: iconst_0      
      16: istore        4
      18: goto          46
      21: aload         6
      23: iload         4
      25: aaload        
      26: astore_3      
      27: aload_2       
      28: aload_3       
      29: invokeinterface #425,  1          // InterfaceMethod org/eclipse/core/resources/IFile.getProjectRelativePath:()Lorg/eclipse/core/runtime/IPath;
      34: invokeinterface #428,  1          // InterfaceMethod org/eclipse/core/runtime/IPath.toString:()Ljava/lang/String;
      39: invokevirtual #399                // Method java/util/ArrayList.add:(Ljava/lang/Object;)Z
      42: pop           
      43: iinc          4, 1
      46: iload         4
      48: iload         5
      50: if_icmplt     21
      53: aload_2       
      54: aload_2       
      55: invokevirtual #429                // Method java/util/ArrayList.size:()I
      58: anewarray     #432                // class java/lang/String
      61: invokevirtual #434                // Method java/util/ArrayList.toArray:([Ljava/lang/Object;)[Ljava/lang/Object;
      64: checkcast     #438                // class "[Ljava/lang/String;"
      67: areturn       

  public void testCommitStaged() throws java.lang.Exception;
    Code:
       0: aload_0       
       1: getfield      #99                 // Field testUtils:Lorg/eclipse/egit/core/test/TestUtils;
       4: aload_0       
       5: getfield      #42                 // Field project:Lorg/eclipse/egit/core/test/TestProject;
       8: invokevirtual #46                 // Method org/eclipse/egit/core/test/TestProject.getProject:()Lorg/eclipse/core/resources/IProject;
      11: ldc           #103                // String foo/a.txt
      13: ldc           #105                // String some text
      15: invokevirtual #107                // Method org/eclipse/egit/core/test/TestUtils.addFileToProject:(Lorg/eclipse/core/resources/IProject;Ljava/lang/String;Ljava/lang/String;)Lorg/eclipse/core/resources/IFile;
      18: astore_1      
      19: aload_0       
      20: getfield      #99                 // Field testUtils:Lorg/eclipse/egit/core/test/TestUtils;
      23: aload_0       
      24: getfield      #42                 // Field project:Lorg/eclipse/egit/core/test/TestProject;
      27: invokevirtual #46                 // Method org/eclipse/egit/core/test/TestProject.getProject:()Lorg/eclipse/core/resources/IProject;
      30: ldc_w         #405                // String foo/b.txt
      33: ldc           #105                // String some text
      35: invokevirtual #107                // Method org/eclipse/egit/core/test/TestUtils.addFileToProject:(Lorg/eclipse/core/resources/IProject;Ljava/lang/String;Ljava/lang/String;)Lorg/eclipse/core/resources/IFile;
      38: astore_2      
      39: iconst_2      
      40: anewarray     #163                // class org/eclipse/core/resources/IFile
      43: dup           
      44: iconst_0      
      45: aload_1       
      46: aastore       
      47: dup           
      48: iconst_1      
      49: aload_2       
      50: aastore       
      51: astore_3      
      52: new           #134                // class org/eclipse/egit/core/op/CommitOperation
      55: dup           
      56: aload_3       
      57: aload_3       
      58: invokestatic  #409                // Method java/util/Arrays.asList:([Ljava/lang/Object;)Ljava/util/List;
      61: ldc           #136                // String The Author <The.author@some.com>
      63: ldc           #138                // String The Commiter <The.committer@some.com>
      65: ldc           #140                // String first commit
      67: invokespecial #142                // Method org/eclipse/egit/core/op/CommitOperation."<init>":([Lorg/eclipse/core/resources/IFile;Ljava/util/Collection;Ljava/lang/String;Ljava/lang/String;Ljava/lang/String;)V
      70: astore        4
      72: aload         4
      74: aconst_null   
      75: invokevirtual #153                // Method org/eclipse/egit/core/op/CommitOperation.execute:(Lorg/eclipse/core/runtime/IProgressMonitor;)V
      78: aload_0       
      79: getfield      #99                 // Field testUtils:Lorg/eclipse/egit/core/test/TestUtils;
      82: aload_0       
      83: getfield      #42                 // Field project:Lorg/eclipse/egit/core/test/TestProject;
      86: invokevirtual #46                 // Method org/eclipse/egit/core/test/TestProject.getProject:()Lorg/eclipse/core/resources/IProject;
      89: aload_1       
      90: ldc_w         #445                // String new content of A
      93: invokevirtual #323                // Method org/eclipse/egit/core/test/TestUtils.changeContentOfFile:(Lorg/eclipse/core/resources/IProject;Lorg/eclipse/core/resources/IFile;Ljava/lang/String;)Lorg/eclipse/core/resources/IFile;
      96: pop           
      97: aload_0       
      98: getfield      #99                 // Field testUtils:Lorg/eclipse/egit/core/test/TestUtils;
     101: aload_0       
     102: getfield      #42                 // Field project:Lorg/eclipse/egit/core/test/TestProject;
     105: invokevirtual #46                 // Method org/eclipse/egit/core/test/TestProject.getProject:()Lorg/eclipse/core/resources/IProject;
     108: aload_2       
     109: ldc_w         #447                // String new content of B
     112: invokevirtual #323                // Method org/eclipse/egit/core/test/TestUtils.changeContentOfFile:(Lorg/eclipse/core/resources/IProject;Lorg/eclipse/core/resources/IFile;Ljava/lang/String;)Lorg/eclipse/core/resources/IFile;
     115: pop           
     116: aload_0       
     117: getfield      #28                 // Field resources:Ljava/util/List;
     120: aload_1       
     121: invokeinterface #119,  2          // InterfaceMethod java/util/List.add:(Ljava/lang/Object;)Z
     126: pop           
     127: aload_0       
     128: getfield      #28                 // Field resources:Ljava/util/List;
     131: aload_2       
     132: invokeinterface #119,  2          // InterfaceMethod java/util/List.add:(Ljava/lang/Object;)Z
     137: pop           
     138: new           #125                // class org/eclipse/egit/core/op/AddToIndexOperation
     141: dup           
     142: aload_0       
     143: getfield      #28                 // Field resources:Ljava/util/List;
     146: invokespecial #127                // Method org/eclipse/egit/core/op/AddToIndexOperation."<init>":(Ljava/util/Collection;)V
     149: aconst_null   
     150: invokevirtual #130                // Method org/eclipse/egit/core/op/AddToIndexOperation.execute:(Lorg/eclipse/core/runtime/IProgressMonitor;)V
     153: new           #134                // class org/eclipse/egit/core/op/CommitOperation
     156: dup           
     157: aload_3       
     158: getstatic     #23                 // Field EMPTY_FILE_LIST:Ljava/util/List;
     161: ldc           #136                // String The Author <The.author@some.com>
     163: ldc           #138                // String The Commiter <The.committer@some.com>
     165: ldc_w         #327                // String second commit
     168: invokespecial #142                // Method org/eclipse/egit/core/op/CommitOperation."<init>":([Lorg/eclipse/core/resources/IFile;Ljava/util/Collection;Ljava/lang/String;Ljava/lang/String;Ljava/lang/String;)V
     171: astore        4
     173: aload         4
     175: aconst_null   
     176: invokevirtual #153                // Method org/eclipse/egit/core/op/CommitOperation.execute:(Lorg/eclipse/core/runtime/IProgressMonitor;)V
     179: aload_0       
     180: getfield      #99                 // Field testUtils:Lorg/eclipse/egit/core/test/TestUtils;
     183: aload_0       
     184: getfield      #84                 // Field repository:Lorg/eclipse/jgit/lib/Repository;
     187: iconst_4      
     188: anewarray     #432                // class java/lang/String
     191: dup           
     192: iconst_0      
     193: ldc           #103                // String foo/a.txt
     195: aastore       
     196: dup           
     197: iconst_1      
     198: ldc_w         #445                // String new content of A
     201: aastore       
     202: dup           
     203: iconst_2      
     204: ldc_w         #405                // String foo/b.txt
     207: aastore       
     208: dup           
     209: iconst_3      
     210: ldc_w         #447                // String new content of B
     213: aastore       
     214: invokevirtual #449                // Method org/eclipse/egit/core/test/TestUtils.assertRepositoryContainsFilesWithContent:(Lorg/eclipse/jgit/lib/Repository;[Ljava/lang/String;)V
     217: return        

  public void testCommitIndexSubset() throws java.lang.Exception;
    Code:
       0: aload_0       
       1: getfield      #99                 // Field testUtils:Lorg/eclipse/egit/core/test/TestUtils;
       4: aload_0       
       5: getfield      #42                 // Field project:Lorg/eclipse/egit/core/test/TestProject;
       8: invokevirtual #46                 // Method org/eclipse/egit/core/test/TestProject.getProject:()Lorg/eclipse/core/resources/IProject;
      11: ldc           #103                // String foo/a.txt
      13: ldc           #105                // String some text
      15: invokevirtual #107                // Method org/eclipse/egit/core/test/TestUtils.addFileToProject:(Lorg/eclipse/core/resources/IProject;Ljava/lang/String;Ljava/lang/String;)Lorg/eclipse/core/resources/IFile;
      18: astore_1      
      19: aload_0       
      20: getfield      #99                 // Field testUtils:Lorg/eclipse/egit/core/test/TestUtils;
      23: aload_0       
      24: getfield      #42                 // Field project:Lorg/eclipse/egit/core/test/TestProject;
      27: invokevirtual #46                 // Method org/eclipse/egit/core/test/TestProject.getProject:()Lorg/eclipse/core/resources/IProject;
      30: ldc_w         #405                // String foo/b.txt
      33: ldc           #105                // String some text
      35: invokevirtual #107                // Method org/eclipse/egit/core/test/TestUtils.addFileToProject:(Lorg/eclipse/core/resources/IProject;Ljava/lang/String;Ljava/lang/String;)Lorg/eclipse/core/resources/IFile;
      38: astore_2      
      39: iconst_2      
      40: anewarray     #163                // class org/eclipse/core/resources/IFile
      43: dup           
      44: iconst_0      
      45: aload_1       
      46: aastore       
      47: dup           
      48: iconst_1      
      49: aload_2       
      50: aastore       
      51: astore_3      
      52: new           #134                // class org/eclipse/egit/core/op/CommitOperation
      55: dup           
      56: aload_3       
      57: aload_3       
      58: invokestatic  #409                // Method java/util/Arrays.asList:([Ljava/lang/Object;)Ljava/util/List;
      61: ldc           #136                // String The Author <The.author@some.com>
      63: ldc           #138                // String The Commiter <The.committer@some.com>
      65: ldc           #140                // String first commit
      67: invokespecial #142                // Method org/eclipse/egit/core/op/CommitOperation."<init>":([Lorg/eclipse/core/resources/IFile;Ljava/util/Collection;Ljava/lang/String;Ljava/lang/String;Ljava/lang/String;)V
      70: astore        4
      72: aload         4
      74: aconst_null   
      75: invokevirtual #153                // Method org/eclipse/egit/core/op/CommitOperation.execute:(Lorg/eclipse/core/runtime/IProgressMonitor;)V
      78: aload_0       
      79: getfield      #99                 // Field testUtils:Lorg/eclipse/egit/core/test/TestUtils;
      82: aload_0       
      83: getfield      #42                 // Field project:Lorg/eclipse/egit/core/test/TestProject;
      86: invokevirtual #46                 // Method org/eclipse/egit/core/test/TestProject.getProject:()Lorg/eclipse/core/resources/IProject;
      89: aload_1       
      90: ldc_w         #445                // String new content of A
      93: invokevirtual #323                // Method org/eclipse/egit/core/test/TestUtils.changeContentOfFile:(Lorg/eclipse/core/resources/IProject;Lorg/eclipse/core/resources/IFile;Ljava/lang/String;)Lorg/eclipse/core/resources/IFile;
      96: pop           
      97: aload_0       
      98: getfield      #99                 // Field testUtils:Lorg/eclipse/egit/core/test/TestUtils;
     101: aload_0       
     102: getfield      #42                 // Field project:Lorg/eclipse/egit/core/test/TestProject;
     105: invokevirtual #46                 // Method org/eclipse/egit/core/test/TestProject.getProject:()Lorg/eclipse/core/resources/IProject;
     108: aload_2       
     109: ldc_w         #447                // String new content of B
     112: invokevirtual #323                // Method org/eclipse/egit/core/test/TestUtils.changeContentOfFile:(Lorg/eclipse/core/resources/IProject;Lorg/eclipse/core/resources/IFile;Ljava/lang/String;)Lorg/eclipse/core/resources/IFile;
     115: pop           
     116: aload_0       
     117: getfield      #28                 // Field resources:Ljava/util/List;
     120: aload_1       
     121: invokeinterface #119,  2          // InterfaceMethod java/util/List.add:(Ljava/lang/Object;)Z
     126: pop           
     127: aload_0       
     128: getfield      #28                 // Field resources:Ljava/util/List;
     131: aload_2       
     132: invokeinterface #119,  2          // InterfaceMethod java/util/List.add:(Ljava/lang/Object;)Z
     137: pop           
     138: new           #125                // class org/eclipse/egit/core/op/AddToIndexOperation
     141: dup           
     142: aload_0       
     143: getfield      #28                 // Field resources:Ljava/util/List;
     146: invokespecial #127                // Method org/eclipse/egit/core/op/AddToIndexOperation."<init>":(Ljava/util/Collection;)V
     149: aconst_null   
     150: invokevirtual #130                // Method org/eclipse/egit/core/op/AddToIndexOperation.execute:(Lorg/eclipse/core/runtime/IProgressMonitor;)V
     153: iconst_1      
     154: anewarray     #163                // class org/eclipse/core/resources/IFile
     157: dup           
     158: iconst_0      
     159: aload_1       
     160: aastore       
     161: astore        5
     163: new           #134                // class org/eclipse/egit/core/op/CommitOperation
     166: dup           
     167: aload         5
     169: getstatic     #23                 // Field EMPTY_FILE_LIST:Ljava/util/List;
     172: ldc           #136                // String The Author <The.author@some.com>
     174: ldc           #138                // String The Commiter <The.committer@some.com>
     176: ldc_w         #327                // String second commit
     179: invokespecial #142                // Method org/eclipse/egit/core/op/CommitOperation."<init>":([Lorg/eclipse/core/resources/IFile;Ljava/util/Collection;Ljava/lang/String;Ljava/lang/String;Ljava/lang/String;)V
     182: astore        4
     184: aload         4
     186: aconst_null   
     187: invokevirtual #153                // Method org/eclipse/egit/core/op/CommitOperation.execute:(Lorg/eclipse/core/runtime/IProgressMonitor;)V
     190: aload_0       
     191: getfield      #99                 // Field testUtils:Lorg/eclipse/egit/core/test/TestUtils;
     194: aload_0       
     195: getfield      #84                 // Field repository:Lorg/eclipse/jgit/lib/Repository;
     198: iconst_4      
     199: anewarray     #432                // class java/lang/String
     202: dup           
     203: iconst_0      
     204: ldc           #103                // String foo/a.txt
     206: aastore       
     207: dup           
     208: iconst_1      
     209: ldc_w         #445                // String new content of A
     212: aastore       
     213: dup           
     214: iconst_2      
     215: ldc_w         #405                // String foo/b.txt
     218: aastore       
     219: dup           
     220: iconst_3      
     221: ldc           #105                // String some text
     223: aastore       
     224: invokevirtual #449                // Method org/eclipse/egit/core/test/TestUtils.assertRepositoryContainsFilesWithContent:(Lorg/eclipse/jgit/lib/Repository;[Ljava/lang/String;)V
     227: return        

  public void testCommitWithStaging() throws java.lang.Exception;
    Code:
       0: aload_0       
       1: getfield      #99                 // Field testUtils:Lorg/eclipse/egit/core/test/TestUtils;
       4: aload_0       
       5: getfield      #42                 // Field project:Lorg/eclipse/egit/core/test/TestProject;
       8: invokevirtual #46                 // Method org/eclipse/egit/core/test/TestProject.getProject:()Lorg/eclipse/core/resources/IProject;
      11: ldc           #103                // String foo/a.txt
      13: ldc           #105                // String some text
      15: invokevirtual #107                // Method org/eclipse/egit/core/test/TestUtils.addFileToProject:(Lorg/eclipse/core/resources/IProject;Ljava/lang/String;Ljava/lang/String;)Lorg/eclipse/core/resources/IFile;
      18: astore_1      
      19: aload_0       
      20: getfield      #99                 // Field testUtils:Lorg/eclipse/egit/core/test/TestUtils;
      23: aload_0       
      24: getfield      #42                 // Field project:Lorg/eclipse/egit/core/test/TestProject;
      27: invokevirtual #46                 // Method org/eclipse/egit/core/test/TestProject.getProject:()Lorg/eclipse/core/resources/IProject;
      30: ldc_w         #405                // String foo/b.txt
      33: ldc           #105                // String some text
      35: invokevirtual #107                // Method org/eclipse/egit/core/test/TestUtils.addFileToProject:(Lorg/eclipse/core/resources/IProject;Ljava/lang/String;Ljava/lang/String;)Lorg/eclipse/core/resources/IFile;
      38: astore_2      
      39: iconst_2      
      40: anewarray     #163                // class org/eclipse/core/resources/IFile
      43: dup           
      44: iconst_0      
      45: aload_1       
      46: aastore       
      47: dup           
      48: iconst_1      
      49: aload_2       
      50: aastore       
      51: astore_3      
      52: new           #134                // class org/eclipse/egit/core/op/CommitOperation
      55: dup           
      56: aload_3       
      57: aload_3       
      58: invokestatic  #409                // Method java/util/Arrays.asList:([Ljava/lang/Object;)Ljava/util/List;
      61: ldc           #136                // String The Author <The.author@some.com>
      63: ldc           #138                // String The Commiter <The.committer@some.com>
      65: ldc           #140                // String first commit
      67: invokespecial #142                // Method org/eclipse/egit/core/op/CommitOperation."<init>":([Lorg/eclipse/core/resources/IFile;Ljava/util/Collection;Ljava/lang/String;Ljava/lang/String;Ljava/lang/String;)V
      70: astore        4
      72: aload         4
      74: aconst_null   
      75: invokevirtual #153                // Method org/eclipse/egit/core/op/CommitOperation.execute:(Lorg/eclipse/core/runtime/IProgressMonitor;)V
      78: aload_0       
      79: getfield      #99                 // Field testUtils:Lorg/eclipse/egit/core/test/TestUtils;
      82: aload_0       
      83: getfield      #42                 // Field project:Lorg/eclipse/egit/core/test/TestProject;
      86: invokevirtual #46                 // Method org/eclipse/egit/core/test/TestProject.getProject:()Lorg/eclipse/core/resources/IProject;
      89: aload_1       
      90: ldc_w         #445                // String new content of A
      93: invokevirtual #323                // Method org/eclipse/egit/core/test/TestUtils.changeContentOfFile:(Lorg/eclipse/core/resources/IProject;Lorg/eclipse/core/resources/IFile;Ljava/lang/String;)Lorg/eclipse/core/resources/IFile;
      96: pop           
      97: aload_0       
      98: getfield      #99                 // Field testUtils:Lorg/eclipse/egit/core/test/TestUtils;
     101: aload_0       
     102: getfield      #42                 // Field project:Lorg/eclipse/egit/core/test/TestProject;
     105: invokevirtual #46                 // Method org/eclipse/egit/core/test/TestProject.getProject:()Lorg/eclipse/core/resources/IProject;
     108: aload_2       
     109: ldc_w         #447                // String new content of B
     112: invokevirtual #323                // Method org/eclipse/egit/core/test/TestUtils.changeContentOfFile:(Lorg/eclipse/core/resources/IProject;Lorg/eclipse/core/resources/IFile;Ljava/lang/String;)Lorg/eclipse/core/resources/IFile;
     115: pop           
     116: aload_0       
     117: getfield      #28                 // Field resources:Ljava/util/List;
     120: aload_1       
     121: invokeinterface #119,  2          // InterfaceMethod java/util/List.add:(Ljava/lang/Object;)Z
     126: pop           
     127: aload_0       
     128: getfield      #28                 // Field resources:Ljava/util/List;
     131: aload_2       
     132: invokeinterface #119,  2          // InterfaceMethod java/util/List.add:(Ljava/lang/Object;)Z
     137: pop           
     138: new           #134                // class org/eclipse/egit/core/op/CommitOperation
     141: dup           
     142: aload_3       
     143: getstatic     #23                 // Field EMPTY_FILE_LIST:Ljava/util/List;
     146: ldc           #136                // String The Author <The.author@some.com>
     148: ldc           #138                // String The Commiter <The.committer@some.com>
     150: ldc           #140                // String first commit
     152: invokespecial #142                // Method org/eclipse/egit/core/op/CommitOperation."<init>":([Lorg/eclipse/core/resources/IFile;Ljava/util/Collection;Ljava/lang/String;Ljava/lang/String;Ljava/lang/String;)V
     155: astore        4
     157: aload         4
     159: aconst_null   
     160: invokevirtual #153                // Method org/eclipse/egit/core/op/CommitOperation.execute:(Lorg/eclipse/core/runtime/IProgressMonitor;)V
     163: aload_0       
     164: getfield      #99                 // Field testUtils:Lorg/eclipse/egit/core/test/TestUtils;
     167: aload_0       
     168: getfield      #84                 // Field repository:Lorg/eclipse/jgit/lib/Repository;
     171: iconst_4      
     172: anewarray     #432                // class java/lang/String
     175: dup           
     176: iconst_0      
     177: ldc           #103                // String foo/a.txt
     179: aastore       
     180: dup           
     181: iconst_1      
     182: ldc_w         #445                // String new content of A
     185: aastore       
     186: dup           
     187: iconst_2      
     188: ldc_w         #405                // String foo/b.txt
     191: aastore       
     192: dup           
     193: iconst_3      
     194: ldc_w         #447                // String new content of B
     197: aastore       
     198: invokevirtual #449                // Method org/eclipse/egit/core/test/TestUtils.assertRepositoryContainsFilesWithContent:(Lorg/eclipse/jgit/lib/Repository;[Ljava/lang/String;)V
     201: return        
}
