Compiled from "GitProjectSetCapabilityTest.java"
public class org.eclipse.egit.core.test.GitProjectSetCapabilityTest {
  private org.eclipse.egit.core.GitProjectSetCapability capability;

  private java.util.List<org.eclipse.core.resources.IProject> createdProjects;

  private java.util.List<java.io.File> pathsToClean;

  public org.eclipse.egit.core.test.GitProjectSetCapabilityTest();
    Code:
       0: aload_0       
       1: invokespecial #16                 // Method java/lang/Object."<init>":()V
       4: aload_0       
       5: new           #18                 // class java/util/ArrayList
       8: dup           
       9: invokespecial #20                 // Method java/util/ArrayList."<init>":()V
      12: putfield      #21                 // Field createdProjects:Ljava/util/List;
      15: aload_0       
      16: new           #18                 // class java/util/ArrayList
      19: dup           
      20: invokespecial #20                 // Method java/util/ArrayList."<init>":()V
      23: putfield      #23                 // Field pathsToClean:Ljava/util/List;
      26: return        

  public void setUp();
    Code:
       0: invokestatic  #32                 // Method org/eclipse/egit/core/Activator.getDefault:()Lorg/eclipse/egit/core/Activator;
       3: invokevirtual #38                 // Method org/eclipse/egit/core/Activator.getRepositoryCache:()Lorg/eclipse/egit/core/RepositoryCache;
       6: invokevirtual #42                 // Method org/eclipse/egit/core/RepositoryCache.clear:()V
       9: aload_0       
      10: new           #47                 // class org/eclipse/egit/core/GitProjectSetCapability
      13: dup           
      14: invokespecial #49                 // Method org/eclipse/egit/core/GitProjectSetCapability."<init>":()V
      17: putfield      #50                 // Field capability:Lorg/eclipse/egit/core/GitProjectSetCapability;
      20: return        

  public void tearDown() throws java.lang.Exception;
    Code:
       0: invokestatic  #57                 // Method org/eclipse/core/resources/ResourcesPlugin.getWorkspace:()Lorg/eclipse/core/resources/IWorkspace;
       3: invokeinterface #63,  1           // InterfaceMethod org/eclipse/core/resources/IWorkspace.getRoot:()Lorg/eclipse/core/resources/IWorkspaceRoot;
       8: iconst_1      
       9: aconst_null   
      10: invokeinterface #69,  3           // InterfaceMethod org/eclipse/core/resources/IWorkspaceRoot.delete:(ILorg/eclipse/core/runtime/IProgressMonitor;)V
      15: invokestatic  #32                 // Method org/eclipse/egit/core/Activator.getDefault:()Lorg/eclipse/egit/core/Activator;
      18: invokevirtual #38                 // Method org/eclipse/egit/core/Activator.getRepositoryCache:()Lorg/eclipse/egit/core/RepositoryCache;
      21: invokevirtual #42                 // Method org/eclipse/egit/core/RepositoryCache.clear:()V
      24: aload_0       
      25: getfield      #21                 // Field createdProjects:Ljava/util/List;
      28: invokeinterface #75,  1           // InterfaceMethod java/util/List.iterator:()Ljava/util/Iterator;
      33: astore_2      
      34: goto          65
      37: aload_2       
      38: invokeinterface #81,  1           // InterfaceMethod java/util/Iterator.next:()Ljava/lang/Object;
      43: checkcast     #87                 // class org/eclipse/core/resources/IProject
      46: astore_1      
      47: aload_1       
      48: invokeinterface #89,  1           // InterfaceMethod org/eclipse/core/resources/IProject.exists:()Z
      53: ifeq          65
      56: aload_1       
      57: iconst_1      
      58: iconst_1      
      59: aconst_null   
      60: invokeinterface #93,  4           // InterfaceMethod org/eclipse/core/resources/IProject.delete:(ZZLorg/eclipse/core/runtime/IProgressMonitor;)V
      65: aload_2       
      66: invokeinterface #96,  1           // InterfaceMethod java/util/Iterator.hasNext:()Z
      71: ifne          37
      74: aload_0       
      75: getfield      #23                 // Field pathsToClean:Ljava/util/List;
      78: invokeinterface #75,  1           // InterfaceMethod java/util/List.iterator:()Ljava/util/Iterator;
      83: astore_2      
      84: goto          109
      87: aload_2       
      88: invokeinterface #81,  1           // InterfaceMethod java/util/Iterator.next:()Ljava/lang/Object;
      93: checkcast     #99                 // class java/io/File
      96: astore_1      
      97: aload_1       
      98: invokevirtual #101                // Method java/io/File.exists:()Z
     101: ifeq          109
     104: aload_1       
     105: iconst_3      
     106: invokestatic  #102                // Method org/eclipse/jgit/util/FileUtils.delete:(Ljava/io/File;I)V
     109: aload_2       
     110: invokeinterface #96,  1           // InterfaceMethod java/util/Iterator.hasNext:()Z
     115: ifne          87
     118: return        

  public void testExport() throws java.lang.Exception;
    Code:
       0: aload_0       
       1: ldc           #114                // String a
       3: invokespecial #116                // Method createProject:(Ljava/lang/String;)Lorg/eclipse/core/resources/IProject;
       6: astore_1      
       7: aload_0       
       8: aload_1       
       9: invokeinterface #120,  1          // InterfaceMethod org/eclipse/core/resources/IProject.getLocation:()Lorg/eclipse/core/runtime/IPath;
      14: ldc           #124                // String http://example.org/repo-a
      16: ldc           #126                // String master
      18: invokespecial #128                // Method createRepository:(Lorg/eclipse/core/runtime/IPath;Ljava/lang/String;Ljava/lang/String;)Ljava/io/File;
      21: astore_2      
      22: aload_0       
      23: aload_1       
      24: aload_2       
      25: invokespecial #132                // Method connectProject:(Lorg/eclipse/core/resources/IProject;Ljava/io/File;)V
      28: invokestatic  #57                 // Method org/eclipse/core/resources/ResourcesPlugin.getWorkspace:()Lorg/eclipse/core/resources/IWorkspace;
      31: invokeinterface #63,  1           // InterfaceMethod org/eclipse/core/resources/IWorkspace.getRoot:()Lorg/eclipse/core/resources/IWorkspaceRoot;
      36: invokeinterface #136,  1          // InterfaceMethod org/eclipse/core/resources/IWorkspaceRoot.getLocation:()Lorg/eclipse/core/runtime/IPath;
      41: ldc           #137                // String b
      43: invokeinterface #139,  2          // InterfaceMethod org/eclipse/core/runtime/IPath.append:(Ljava/lang/String;)Lorg/eclipse/core/runtime/IPath;
      48: astore_3      
      49: aload_0       
      50: aload_3       
      51: ldc           #145                // String http://example.org/repo-b
      53: ldc           #126                // String master
      55: invokespecial #128                // Method createRepository:(Lorg/eclipse/core/runtime/IPath;Ljava/lang/String;Ljava/lang/String;)Ljava/io/File;
      58: astore        4
      60: aload_0       
      61: aload_3       
      62: ldc           #147                // String ba
      64: invokespecial #149                // Method createProject:(Lorg/eclipse/core/runtime/IPath;Ljava/lang/String;)Lorg/eclipse/core/resources/IProject;
      67: astore        5
      69: aload_0       
      70: aload_3       
      71: ldc           #152                // String bb
      73: invokespecial #149                // Method createProject:(Lorg/eclipse/core/runtime/IPath;Ljava/lang/String;)Lorg/eclipse/core/resources/IProject;
      76: astore        6
      78: aload_0       
      79: aload         5
      81: aload         4
      83: invokespecial #132                // Method connectProject:(Lorg/eclipse/core/resources/IProject;Ljava/io/File;)V
      86: aload_0       
      87: aload         6
      89: aload         4
      91: invokespecial #132                // Method connectProject:(Lorg/eclipse/core/resources/IProject;Ljava/io/File;)V
      94: aload_0       
      95: getfield      #23                 // Field pathsToClean:Ljava/util/List;
      98: aload_3       
      99: invokeinterface #154,  1          // InterfaceMethod org/eclipse/core/runtime/IPath.toFile:()Ljava/io/File;
     104: invokeinterface #158,  2          // InterfaceMethod java/util/List.add:(Ljava/lang/Object;)Z
     109: pop           
     110: aload_0       
     111: ldc           #162                // String c
     113: invokespecial #116                // Method createProject:(Ljava/lang/String;)Lorg/eclipse/core/resources/IProject;
     116: astore        7
     118: aload_0       
     119: aload         7
     121: invokeinterface #120,  1          // InterfaceMethod org/eclipse/core/resources/IProject.getLocation:()Lorg/eclipse/core/runtime/IPath;
     126: ldc           #164                // String http://example.org/repo-c
     128: ldc           #166                // String stable
     130: invokespecial #128                // Method createRepository:(Lorg/eclipse/core/runtime/IPath;Ljava/lang/String;Ljava/lang/String;)Ljava/io/File;
     133: astore        8
     135: aload_0       
     136: aload         7
     138: aload         8
     140: invokespecial #132                // Method connectProject:(Lorg/eclipse/core/resources/IProject;Ljava/io/File;)V
     143: iconst_4      
     144: anewarray     #87                 // class org/eclipse/core/resources/IProject
     147: dup           
     148: iconst_0      
     149: aload_1       
     150: aastore       
     151: dup           
     152: iconst_1      
     153: aload         5
     155: aastore       
     156: dup           
     157: iconst_2      
     158: aload         6
     160: aastore       
     161: dup           
     162: iconst_3      
     163: aload         7
     165: aastore       
     166: astore        9
     168: aload_0       
     169: getfield      #50                 // Field capability:Lorg/eclipse/egit/core/GitProjectSetCapability;
     172: aload         9
     174: new           #168                // class org/eclipse/team/core/ProjectSetSerializationContext
     177: dup           
     178: invokespecial #170                // Method org/eclipse/team/core/ProjectSetSerializationContext."<init>":()V
     181: new           #171                // class org/eclipse/core/runtime/NullProgressMonitor
     184: dup           
     185: invokespecial #173                // Method org/eclipse/core/runtime/NullProgressMonitor."<init>":()V
     188: invokevirtual #174                // Method org/eclipse/egit/core/GitProjectSetCapability.asReference:([Lorg/eclipse/core/resources/IProject;Lorg/eclipse/team/core/ProjectSetSerializationContext;Lorg/eclipse/core/runtime/IProgressMonitor;)[Ljava/lang/String;
     191: astore        10
     193: ldc2_w        #178                // long 4l
     196: aload         10
     198: arraylength   
     199: i2l           
     200: invokestatic  #180                // Method org/junit/Assert.assertEquals:(JJ)V
     203: ldc           #186                // String 1.0,http://example.org/repo-a,master,.
     205: aload         10
     207: iconst_0      
     208: aaload        
     209: invokestatic  #188                // Method org/junit/Assert.assertEquals:(Ljava/lang/Object;Ljava/lang/Object;)V
     212: ldc           #191                // String 1.0,http://example.org/repo-b,master,ba
     214: aload         10
     216: iconst_1      
     217: aaload        
     218: invokestatic  #188                // Method org/junit/Assert.assertEquals:(Ljava/lang/Object;Ljava/lang/Object;)V
     221: ldc           #193                // String 1.0,http://example.org/repo-b,master,bb
     223: aload         10
     225: iconst_2      
     226: aaload        
     227: invokestatic  #188                // Method org/junit/Assert.assertEquals:(Ljava/lang/Object;Ljava/lang/Object;)V
     230: ldc           #195                // String 1.0,http://example.org/repo-c,stable,.
     232: aload         10
     234: iconst_3      
     235: aaload        
     236: invokestatic  #188                // Method org/junit/Assert.assertEquals:(Ljava/lang/Object;Ljava/lang/Object;)V
     239: return        

  public void testImport() throws java.lang.Exception;
    Code:
       0: invokestatic  #57                 // Method org/eclipse/core/resources/ResourcesPlugin.getWorkspace:()Lorg/eclipse/core/resources/IWorkspace;
       3: invokeinterface #63,  1           // InterfaceMethod org/eclipse/core/resources/IWorkspace.getRoot:()Lorg/eclipse/core/resources/IWorkspaceRoot;
       8: astore_1      
       9: aload_1       
      10: invokeinterface #136,  1          // InterfaceMethod org/eclipse/core/resources/IWorkspaceRoot.getLocation:()Lorg/eclipse/core/runtime/IPath;
      15: ldc           #211                // String repos
      17: invokeinterface #139,  2          // InterfaceMethod org/eclipse/core/runtime/IPath.append:(Ljava/lang/String;)Lorg/eclipse/core/runtime/IPath;
      22: astore_2      
      23: aload_0       
      24: getfield      #23                 // Field pathsToClean:Ljava/util/List;
      27: aload_2       
      28: invokeinterface #154,  1          // InterfaceMethod org/eclipse/core/runtime/IPath.toFile:()Ljava/io/File;
      33: invokeinterface #158,  2          // InterfaceMethod java/util/List.add:(Ljava/lang/Object;)Z
      38: pop           
      39: aload_2       
      40: ldc           #114                // String a
      42: invokeinterface #139,  2          // InterfaceMethod org/eclipse/core/runtime/IPath.append:(Ljava/lang/String;)Lorg/eclipse/core/runtime/IPath;
      47: astore_3      
      48: aload_0       
      49: aload_2       
      50: ldc           #114                // String a
      52: invokespecial #149                // Method createProject:(Lorg/eclipse/core/runtime/IPath;Ljava/lang/String;)Lorg/eclipse/core/resources/IProject;
      55: astore        4
      57: aload_0       
      58: aload_3       
      59: ldc           #213                // String notused
      61: ldc           #126                // String master
      63: invokespecial #128                // Method createRepository:(Lorg/eclipse/core/runtime/IPath;Ljava/lang/String;Ljava/lang/String;)Ljava/io/File;
      66: pop           
      67: aload         4
      69: iconst_0      
      70: iconst_1      
      71: aconst_null   
      72: invokeinterface #93,  4           // InterfaceMethod org/eclipse/core/resources/IProject.delete:(ZZLorg/eclipse/core/runtime/IProgressMonitor;)V
      77: aload_2       
      78: ldc           #137                // String b
      80: invokeinterface #139,  2          // InterfaceMethod org/eclipse/core/runtime/IPath.append:(Ljava/lang/String;)Lorg/eclipse/core/runtime/IPath;
      85: astore        5
      87: aload_0       
      88: aload         5
      90: ldc           #147                // String ba
      92: invokespecial #149                // Method createProject:(Lorg/eclipse/core/runtime/IPath;Ljava/lang/String;)Lorg/eclipse/core/resources/IProject;
      95: astore        6
      97: aload_0       
      98: aload         5
     100: ldc           #152                // String bb
     102: invokespecial #149                // Method createProject:(Lorg/eclipse/core/runtime/IPath;Ljava/lang/String;)Lorg/eclipse/core/resources/IProject;
     105: astore        7
     107: aload_0       
     108: aload         5
     110: ldc           #213                // String notused
     112: ldc           #126                // String master
     114: invokespecial #128                // Method createRepository:(Lorg/eclipse/core/runtime/IPath;Ljava/lang/String;Ljava/lang/String;)Ljava/io/File;
     117: pop           
     118: aload         6
     120: iconst_0      
     121: iconst_1      
     122: aconst_null   
     123: invokeinterface #93,  4           // InterfaceMethod org/eclipse/core/resources/IProject.delete:(ZZLorg/eclipse/core/runtime/IProgressMonitor;)V
     128: aload         7
     130: iconst_0      
     131: iconst_1      
     132: aconst_null   
     133: invokeinterface #93,  4           // InterfaceMethod org/eclipse/core/resources/IProject.delete:(ZZLorg/eclipse/core/runtime/IProgressMonitor;)V
     138: aload_2       
     139: ldc           #162                // String c
     141: invokeinterface #139,  2          // InterfaceMethod org/eclipse/core/runtime/IPath.append:(Ljava/lang/String;)Lorg/eclipse/core/runtime/IPath;
     146: astore        8
     148: aload_0       
     149: aload_2       
     150: ldc           #162                // String c
     152: invokespecial #149                // Method createProject:(Lorg/eclipse/core/runtime/IPath;Ljava/lang/String;)Lorg/eclipse/core/resources/IProject;
     155: astore        9
     157: aload_0       
     158: aload         8
     160: ldc           #213                // String notused
     162: ldc           #166                // String stable
     164: invokespecial #128                // Method createRepository:(Lorg/eclipse/core/runtime/IPath;Ljava/lang/String;Ljava/lang/String;)Ljava/io/File;
     167: pop           
     168: aload         9
     170: iconst_0      
     171: iconst_1      
     172: aconst_null   
     173: invokeinterface #93,  4           // InterfaceMethod org/eclipse/core/resources/IProject.delete:(ZZLorg/eclipse/core/runtime/IProgressMonitor;)V
     178: new           #215                // class java/lang/StringBuilder
     181: dup           
     182: ldc           #217                // String 1.0,
     184: invokespecial #219                // Method java/lang/StringBuilder."<init>":(Ljava/lang/String;)V
     187: aload_3       
     188: invokeinterface #154,  1          // InterfaceMethod org/eclipse/core/runtime/IPath.toFile:()Ljava/io/File;
     193: invokevirtual #222                // Method java/io/File.toURI:()Ljava/net/URI;
     196: invokevirtual #226                // Method java/net/URI.toString:()Ljava/lang/String;
     199: invokevirtual #232                // Method java/lang/StringBuilder.append:(Ljava/lang/String;)Ljava/lang/StringBuilder;
     202: ldc           #235                // String ,master,.
     204: invokevirtual #232                // Method java/lang/StringBuilder.append:(Ljava/lang/String;)Ljava/lang/StringBuilder;
     207: invokevirtual #237                // Method java/lang/StringBuilder.toString:()Ljava/lang/String;
     210: astore        10
     212: new           #215                // class java/lang/StringBuilder
     215: dup           
     216: ldc           #217                // String 1.0,
     218: invokespecial #219                // Method java/lang/StringBuilder."<init>":(Ljava/lang/String;)V
     221: aload         5
     223: invokeinterface #154,  1          // InterfaceMethod org/eclipse/core/runtime/IPath.toFile:()Ljava/io/File;
     228: invokevirtual #222                // Method java/io/File.toURI:()Ljava/net/URI;
     231: invokevirtual #226                // Method java/net/URI.toString:()Ljava/lang/String;
     234: invokevirtual #232                // Method java/lang/StringBuilder.append:(Ljava/lang/String;)Ljava/lang/StringBuilder;
     237: ldc           #238                // String ,master,ba
     239: invokevirtual #232                // Method java/lang/StringBuilder.append:(Ljava/lang/String;)Ljava/lang/StringBuilder;
     242: invokevirtual #237                // Method java/lang/StringBuilder.toString:()Ljava/lang/String;
     245: astore        11
     247: new           #215                // class java/lang/StringBuilder
     250: dup           
     251: ldc           #217                // String 1.0,
     253: invokespecial #219                // Method java/lang/StringBuilder."<init>":(Ljava/lang/String;)V
     256: aload         5
     258: invokeinterface #154,  1          // InterfaceMethod org/eclipse/core/runtime/IPath.toFile:()Ljava/io/File;
     263: invokevirtual #222                // Method java/io/File.toURI:()Ljava/net/URI;
     266: invokevirtual #226                // Method java/net/URI.toString:()Ljava/lang/String;
     269: invokevirtual #232                // Method java/lang/StringBuilder.append:(Ljava/lang/String;)Ljava/lang/StringBuilder;
     272: ldc           #240                // String ,master,bb
     274: invokevirtual #232                // Method java/lang/StringBuilder.append:(Ljava/lang/String;)Ljava/lang/StringBuilder;
     277: invokevirtual #237                // Method java/lang/StringBuilder.toString:()Ljava/lang/String;
     280: astore        12
     282: new           #215                // class java/lang/StringBuilder
     285: dup           
     286: ldc           #217                // String 1.0,
     288: invokespecial #219                // Method java/lang/StringBuilder."<init>":(Ljava/lang/String;)V
     291: aload         8
     293: invokeinterface #154,  1          // InterfaceMethod org/eclipse/core/runtime/IPath.toFile:()Ljava/io/File;
     298: invokevirtual #222                // Method java/io/File.toURI:()Ljava/net/URI;
     301: invokevirtual #226                // Method java/net/URI.toString:()Ljava/lang/String;
     304: invokevirtual #232                // Method java/lang/StringBuilder.append:(Ljava/lang/String;)Ljava/lang/StringBuilder;
     307: ldc           #242                // String ,stable,.
     309: invokevirtual #232                // Method java/lang/StringBuilder.append:(Ljava/lang/String;)Ljava/lang/StringBuilder;
     312: invokevirtual #237                // Method java/lang/StringBuilder.toString:()Ljava/lang/String;
     315: astore        13
     317: iconst_4      
     318: anewarray     #244                // class java/lang/String
     321: dup           
     322: iconst_0      
     323: aload         10
     325: aastore       
     326: dup           
     327: iconst_1      
     328: aload         11
     330: aastore       
     331: dup           
     332: iconst_2      
     333: aload         12
     335: aastore       
     336: dup           
     337: iconst_3      
     338: aload         13
     340: aastore       
     341: astore        14
     343: aload_0       
     344: aload         14
     346: invokespecial #246                // Method addToWorkspace:([Ljava/lang/String;)V
     349: aload_0       
     350: getfield      #23                 // Field pathsToClean:Ljava/util/List;
     353: aload_1       
     354: invokeinterface #136,  1          // InterfaceMethod org/eclipse/core/resources/IWorkspaceRoot.getLocation:()Lorg/eclipse/core/runtime/IPath;
     359: ldc           #137                // String b
     361: invokeinterface #139,  2          // InterfaceMethod org/eclipse/core/runtime/IPath.append:(Ljava/lang/String;)Lorg/eclipse/core/runtime/IPath;
     366: invokeinterface #154,  1          // InterfaceMethod org/eclipse/core/runtime/IPath.toFile:()Ljava/io/File;
     371: invokeinterface #158,  2          // InterfaceMethod java/util/List.add:(Ljava/lang/Object;)Z
     376: pop           
     377: aload_1       
     378: ldc           #114                // String a
     380: invokeinterface #250,  2          // InterfaceMethod org/eclipse/core/resources/IWorkspaceRoot.getProject:(Ljava/lang/String;)Lorg/eclipse/core/resources/IProject;
     385: astore        15
     387: aload_0       
     388: getfield      #21                 // Field createdProjects:Ljava/util/List;
     391: aload         15
     393: invokeinterface #158,  2          // InterfaceMethod java/util/List.add:(Ljava/lang/Object;)Z
     398: pop           
     399: aload         15
     401: invokeinterface #89,  1           // InterfaceMethod org/eclipse/core/resources/IProject.exists:()Z
     406: invokestatic  #253                // Method org/junit/Assert.assertTrue:(Z)V
     409: aload         15
     411: invokestatic  #257                // Method org/eclipse/egit/core/project/RepositoryMapping.getMapping:(Lorg/eclipse/core/resources/IProject;)Lorg/eclipse/egit/core/project/RepositoryMapping;
     414: invokestatic  #263                // Method org/junit/Assert.assertNotNull:(Ljava/lang/Object;)V
     417: aload_1       
     418: ldc           #147                // String ba
     420: invokeinterface #250,  2          // InterfaceMethod org/eclipse/core/resources/IWorkspaceRoot.getProject:(Ljava/lang/String;)Lorg/eclipse/core/resources/IProject;
     425: astore        16
     427: aload_0       
     428: getfield      #21                 // Field createdProjects:Ljava/util/List;
     431: aload         16
     433: invokeinterface #158,  2          // InterfaceMethod java/util/List.add:(Ljava/lang/Object;)Z
     438: pop           
     439: aload         16
     441: invokeinterface #89,  1           // InterfaceMethod org/eclipse/core/resources/IProject.exists:()Z
     446: invokestatic  #253                // Method org/junit/Assert.assertTrue:(Z)V
     449: aload_1       
     450: invokeinterface #136,  1          // InterfaceMethod org/eclipse/core/resources/IWorkspaceRoot.getLocation:()Lorg/eclipse/core/runtime/IPath;
     455: ldc_w         #267                // String b/ba
     458: invokeinterface #139,  2          // InterfaceMethod org/eclipse/core/runtime/IPath.append:(Ljava/lang/String;)Lorg/eclipse/core/runtime/IPath;
     463: aload         16
     465: invokeinterface #120,  1          // InterfaceMethod org/eclipse/core/resources/IProject.getLocation:()Lorg/eclipse/core/runtime/IPath;
     470: invokestatic  #188                // Method org/junit/Assert.assertEquals:(Ljava/lang/Object;Ljava/lang/Object;)V
     473: aload         16
     475: invokestatic  #257                // Method org/eclipse/egit/core/project/RepositoryMapping.getMapping:(Lorg/eclipse/core/resources/IProject;)Lorg/eclipse/egit/core/project/RepositoryMapping;
     478: invokestatic  #263                // Method org/junit/Assert.assertNotNull:(Ljava/lang/Object;)V
     481: aload_1       
     482: ldc           #152                // String bb
     484: invokeinterface #250,  2          // InterfaceMethod org/eclipse/core/resources/IWorkspaceRoot.getProject:(Ljava/lang/String;)Lorg/eclipse/core/resources/IProject;
     489: astore        17
     491: aload_0       
     492: getfield      #21                 // Field createdProjects:Ljava/util/List;
     495: aload         17
     497: invokeinterface #158,  2          // InterfaceMethod java/util/List.add:(Ljava/lang/Object;)Z
     502: pop           
     503: aload         17
     505: invokeinterface #89,  1           // InterfaceMethod org/eclipse/core/resources/IProject.exists:()Z
     510: invokestatic  #253                // Method org/junit/Assert.assertTrue:(Z)V
     513: aload_1       
     514: invokeinterface #136,  1          // InterfaceMethod org/eclipse/core/resources/IWorkspaceRoot.getLocation:()Lorg/eclipse/core/runtime/IPath;
     519: ldc_w         #269                // String b/bb
     522: invokeinterface #139,  2          // InterfaceMethod org/eclipse/core/runtime/IPath.append:(Ljava/lang/String;)Lorg/eclipse/core/runtime/IPath;
     527: aload         17
     529: invokeinterface #120,  1          // InterfaceMethod org/eclipse/core/resources/IProject.getLocation:()Lorg/eclipse/core/runtime/IPath;
     534: invokestatic  #188                // Method org/junit/Assert.assertEquals:(Ljava/lang/Object;Ljava/lang/Object;)V
     537: aload         17
     539: invokestatic  #257                // Method org/eclipse/egit/core/project/RepositoryMapping.getMapping:(Lorg/eclipse/core/resources/IProject;)Lorg/eclipse/egit/core/project/RepositoryMapping;
     542: invokestatic  #263                // Method org/junit/Assert.assertNotNull:(Ljava/lang/Object;)V
     545: aload_1       
     546: ldc           #162                // String c
     548: invokeinterface #250,  2          // InterfaceMethod org/eclipse/core/resources/IWorkspaceRoot.getProject:(Ljava/lang/String;)Lorg/eclipse/core/resources/IProject;
     553: astore        18
     555: aload_0       
     556: getfield      #21                 // Field createdProjects:Ljava/util/List;
     559: aload         18
     561: invokeinterface #158,  2          // InterfaceMethod java/util/List.add:(Ljava/lang/Object;)Z
     566: pop           
     567: aload         18
     569: invokeinterface #89,  1           // InterfaceMethod org/eclipse/core/resources/IProject.exists:()Z
     574: invokestatic  #253                // Method org/junit/Assert.assertTrue:(Z)V
     577: aload         18
     579: invokestatic  #257                // Method org/eclipse/egit/core/project/RepositoryMapping.getMapping:(Lorg/eclipse/core/resources/IProject;)Lorg/eclipse/egit/core/project/RepositoryMapping;
     582: astore        19
     584: aload         19
     586: invokestatic  #263                // Method org/junit/Assert.assertNotNull:(Ljava/lang/Object;)V
     589: ldc           #166                // String stable
     591: aload         19
     593: invokevirtual #271                // Method org/eclipse/egit/core/project/RepositoryMapping.getRepository:()Lorg/eclipse/jgit/lib/Repository;
     596: invokevirtual #275                // Method org/eclipse/jgit/lib/Repository.getBranch:()Ljava/lang/String;
     599: invokestatic  #188                // Method org/junit/Assert.assertEquals:(Ljava/lang/Object;Ljava/lang/Object;)V
     602: return        

  public void testImportWithDifferentBranchesOfSameRepo() throws java.lang.Exception;
    Code:
       0: invokestatic  #57                 // Method org/eclipse/core/resources/ResourcesPlugin.getWorkspace:()Lorg/eclipse/core/resources/IWorkspace;
       3: invokeinterface #63,  1           // InterfaceMethod org/eclipse/core/resources/IWorkspace.getRoot:()Lorg/eclipse/core/resources/IWorkspaceRoot;
       8: astore_1      
       9: aload_1       
      10: invokeinterface #136,  1          // InterfaceMethod org/eclipse/core/resources/IWorkspaceRoot.getLocation:()Lorg/eclipse/core/runtime/IPath;
      15: ldc           #211                // String repos
      17: invokeinterface #139,  2          // InterfaceMethod org/eclipse/core/runtime/IPath.append:(Ljava/lang/String;)Lorg/eclipse/core/runtime/IPath;
      22: astore_2      
      23: aload_0       
      24: getfield      #23                 // Field pathsToClean:Ljava/util/List;
      27: aload_2       
      28: invokeinterface #154,  1          // InterfaceMethod org/eclipse/core/runtime/IPath.toFile:()Ljava/io/File;
      33: invokeinterface #158,  2          // InterfaceMethod java/util/List.add:(Ljava/lang/Object;)Z
      38: pop           
      39: aload_2       
      40: ldc_w         #297                // String x
      43: invokeinterface #139,  2          // InterfaceMethod org/eclipse/core/runtime/IPath.append:(Ljava/lang/String;)Lorg/eclipse/core/runtime/IPath;
      48: astore_3      
      49: aload_0       
      50: aload_3       
      51: ldc_w         #299                // String xa
      54: invokespecial #149                // Method createProject:(Lorg/eclipse/core/runtime/IPath;Ljava/lang/String;)Lorg/eclipse/core/resources/IProject;
      57: astore        4
      59: aload_0       
      60: aload_3       
      61: ldc_w         #301                // String xb
      64: invokespecial #149                // Method createProject:(Lorg/eclipse/core/runtime/IPath;Ljava/lang/String;)Lorg/eclipse/core/resources/IProject;
      67: astore        5
      69: aload_0       
      70: aload_3       
      71: ldc           #213                // String notused
      73: ldc           #166                // String stable
      75: invokespecial #128                // Method createRepository:(Lorg/eclipse/core/runtime/IPath;Ljava/lang/String;Ljava/lang/String;)Ljava/io/File;
      78: pop           
      79: aload         4
      81: iconst_0      
      82: iconst_1      
      83: aconst_null   
      84: invokeinterface #93,  4           // InterfaceMethod org/eclipse/core/resources/IProject.delete:(ZZLorg/eclipse/core/runtime/IProgressMonitor;)V
      89: aload         5
      91: iconst_0      
      92: iconst_1      
      93: aconst_null   
      94: invokeinterface #93,  4           // InterfaceMethod org/eclipse/core/resources/IProject.delete:(ZZLorg/eclipse/core/runtime/IProgressMonitor;)V
      99: new           #215                // class java/lang/StringBuilder
     102: dup           
     103: ldc           #217                // String 1.0,
     105: invokespecial #219                // Method java/lang/StringBuilder."<init>":(Ljava/lang/String;)V
     108: aload_3       
     109: invokeinterface #154,  1          // InterfaceMethod org/eclipse/core/runtime/IPath.toFile:()Ljava/io/File;
     114: invokevirtual #222                // Method java/io/File.toURI:()Ljava/net/URI;
     117: invokevirtual #226                // Method java/net/URI.toString:()Ljava/lang/String;
     120: invokevirtual #232                // Method java/lang/StringBuilder.append:(Ljava/lang/String;)Ljava/lang/StringBuilder;
     123: ldc_w         #303                // String ,master,xa
     126: invokevirtual #232                // Method java/lang/StringBuilder.append:(Ljava/lang/String;)Ljava/lang/StringBuilder;
     129: invokevirtual #237                // Method java/lang/StringBuilder.toString:()Ljava/lang/String;
     132: astore        6
     134: new           #215                // class java/lang/StringBuilder
     137: dup           
     138: ldc           #217                // String 1.0,
     140: invokespecial #219                // Method java/lang/StringBuilder."<init>":(Ljava/lang/String;)V
     143: aload_3       
     144: invokeinterface #154,  1          // InterfaceMethod org/eclipse/core/runtime/IPath.toFile:()Ljava/io/File;
     149: invokevirtual #222                // Method java/io/File.toURI:()Ljava/net/URI;
     152: invokevirtual #226                // Method java/net/URI.toString:()Ljava/lang/String;
     155: invokevirtual #232                // Method java/lang/StringBuilder.append:(Ljava/lang/String;)Ljava/lang/StringBuilder;
     158: ldc_w         #305                // String ,stable,xb
     161: invokevirtual #232                // Method java/lang/StringBuilder.append:(Ljava/lang/String;)Ljava/lang/StringBuilder;
     164: invokevirtual #237                // Method java/lang/StringBuilder.toString:()Ljava/lang/String;
     167: astore        7
     169: iconst_2      
     170: anewarray     #244                // class java/lang/String
     173: dup           
     174: iconst_0      
     175: aload         6
     177: aastore       
     178: dup           
     179: iconst_1      
     180: aload         7
     182: aastore       
     183: astore        8
     185: aload_0       
     186: aload         8
     188: invokespecial #246                // Method addToWorkspace:([Ljava/lang/String;)V
     191: aload_0       
     192: getfield      #23                 // Field pathsToClean:Ljava/util/List;
     195: aload_1       
     196: invokeinterface #136,  1          // InterfaceMethod org/eclipse/core/resources/IWorkspaceRoot.getLocation:()Lorg/eclipse/core/runtime/IPath;
     201: ldc_w         #297                // String x
     204: invokeinterface #139,  2          // InterfaceMethod org/eclipse/core/runtime/IPath.append:(Ljava/lang/String;)Lorg/eclipse/core/runtime/IPath;
     209: invokeinterface #154,  1          // InterfaceMethod org/eclipse/core/runtime/IPath.toFile:()Ljava/io/File;
     214: invokeinterface #158,  2          // InterfaceMethod java/util/List.add:(Ljava/lang/Object;)Z
     219: pop           
     220: aload_0       
     221: getfield      #23                 // Field pathsToClean:Ljava/util/List;
     224: aload_1       
     225: invokeinterface #136,  1          // InterfaceMethod org/eclipse/core/resources/IWorkspaceRoot.getLocation:()Lorg/eclipse/core/runtime/IPath;
     230: ldc_w         #307                // String x_stable
     233: invokeinterface #139,  2          // InterfaceMethod org/eclipse/core/runtime/IPath.append:(Ljava/lang/String;)Lorg/eclipse/core/runtime/IPath;
     238: invokeinterface #154,  1          // InterfaceMethod org/eclipse/core/runtime/IPath.toFile:()Ljava/io/File;
     243: invokeinterface #158,  2          // InterfaceMethod java/util/List.add:(Ljava/lang/Object;)Z
     248: pop           
     249: aload_1       
     250: ldc_w         #299                // String xa
     253: invokeinterface #250,  2          // InterfaceMethod org/eclipse/core/resources/IWorkspaceRoot.getProject:(Ljava/lang/String;)Lorg/eclipse/core/resources/IProject;
     258: astore        9
     260: aload_0       
     261: getfield      #21                 // Field createdProjects:Ljava/util/List;
     264: aload         9
     266: invokeinterface #158,  2          // InterfaceMethod java/util/List.add:(Ljava/lang/Object;)Z
     271: pop           
     272: aload         9
     274: invokeinterface #89,  1           // InterfaceMethod org/eclipse/core/resources/IProject.exists:()Z
     279: invokestatic  #253                // Method org/junit/Assert.assertTrue:(Z)V
     282: aload_1       
     283: invokeinterface #136,  1          // InterfaceMethod org/eclipse/core/resources/IWorkspaceRoot.getLocation:()Lorg/eclipse/core/runtime/IPath;
     288: ldc_w         #309                // String x/xa
     291: invokeinterface #139,  2          // InterfaceMethod org/eclipse/core/runtime/IPath.append:(Ljava/lang/String;)Lorg/eclipse/core/runtime/IPath;
     296: aload         9
     298: invokeinterface #120,  1          // InterfaceMethod org/eclipse/core/resources/IProject.getLocation:()Lorg/eclipse/core/runtime/IPath;
     303: invokestatic  #188                // Method org/junit/Assert.assertEquals:(Ljava/lang/Object;Ljava/lang/Object;)V
     306: aload         9
     308: invokestatic  #257                // Method org/eclipse/egit/core/project/RepositoryMapping.getMapping:(Lorg/eclipse/core/resources/IProject;)Lorg/eclipse/egit/core/project/RepositoryMapping;
     311: astore        10
     313: aload         10
     315: invokestatic  #263                // Method org/junit/Assert.assertNotNull:(Ljava/lang/Object;)V
     318: ldc           #126                // String master
     320: aload         10
     322: invokevirtual #271                // Method org/eclipse/egit/core/project/RepositoryMapping.getRepository:()Lorg/eclipse/jgit/lib/Repository;
     325: invokevirtual #275                // Method org/eclipse/jgit/lib/Repository.getBranch:()Ljava/lang/String;
     328: invokestatic  #188                // Method org/junit/Assert.assertEquals:(Ljava/lang/Object;Ljava/lang/Object;)V
     331: aload_1       
     332: ldc_w         #301                // String xb
     335: invokeinterface #250,  2          // InterfaceMethod org/eclipse/core/resources/IWorkspaceRoot.getProject:(Ljava/lang/String;)Lorg/eclipse/core/resources/IProject;
     340: astore        11
     342: aload_0       
     343: getfield      #21                 // Field createdProjects:Ljava/util/List;
     346: aload         11
     348: invokeinterface #158,  2          // InterfaceMethod java/util/List.add:(Ljava/lang/Object;)Z
     353: pop           
     354: aload         11
     356: invokeinterface #89,  1           // InterfaceMethod org/eclipse/core/resources/IProject.exists:()Z
     361: invokestatic  #253                // Method org/junit/Assert.assertTrue:(Z)V
     364: aload_1       
     365: invokeinterface #136,  1          // InterfaceMethod org/eclipse/core/resources/IWorkspaceRoot.getLocation:()Lorg/eclipse/core/runtime/IPath;
     370: ldc_w         #311                // String x_stable/xb
     373: invokeinterface #139,  2          // InterfaceMethod org/eclipse/core/runtime/IPath.append:(Ljava/lang/String;)Lorg/eclipse/core/runtime/IPath;
     378: aload         11
     380: invokeinterface #120,  1          // InterfaceMethod org/eclipse/core/resources/IProject.getLocation:()Lorg/eclipse/core/runtime/IPath;
     385: invokestatic  #188                // Method org/junit/Assert.assertEquals:(Ljava/lang/Object;Ljava/lang/Object;)V
     388: aload         11
     390: invokestatic  #257                // Method org/eclipse/egit/core/project/RepositoryMapping.getMapping:(Lorg/eclipse/core/resources/IProject;)Lorg/eclipse/egit/core/project/RepositoryMapping;
     393: astore        12
     395: aload         12
     397: invokestatic  #263                // Method org/junit/Assert.assertNotNull:(Ljava/lang/Object;)V
     400: ldc           #166                // String stable
     402: aload         12
     404: invokevirtual #271                // Method org/eclipse/egit/core/project/RepositoryMapping.getRepository:()Lorg/eclipse/jgit/lib/Repository;
     407: invokevirtual #275                // Method org/eclipse/jgit/lib/Repository.getBranch:()Ljava/lang/String;
     410: invokestatic  #188                // Method org/junit/Assert.assertEquals:(Ljava/lang/Object;Ljava/lang/Object;)V
     413: return        

  public void testImportWithMultipleCallsForSameDestinationRepo() throws java.lang.Exception;
    Code:
       0: invokestatic  #57                 // Method org/eclipse/core/resources/ResourcesPlugin.getWorkspace:()Lorg/eclipse/core/resources/IWorkspace;
       3: invokeinterface #63,  1           // InterfaceMethod org/eclipse/core/resources/IWorkspace.getRoot:()Lorg/eclipse/core/resources/IWorkspaceRoot;
       8: astore_1      
       9: aload_1       
      10: invokeinterface #136,  1          // InterfaceMethod org/eclipse/core/resources/IWorkspaceRoot.getLocation:()Lorg/eclipse/core/runtime/IPath;
      15: ldc           #211                // String repos
      17: invokeinterface #139,  2          // InterfaceMethod org/eclipse/core/runtime/IPath.append:(Ljava/lang/String;)Lorg/eclipse/core/runtime/IPath;
      22: astore_2      
      23: aload_0       
      24: getfield      #23                 // Field pathsToClean:Ljava/util/List;
      27: aload_2       
      28: invokeinterface #154,  1          // InterfaceMethod org/eclipse/core/runtime/IPath.toFile:()Ljava/io/File;
      33: invokeinterface #158,  2          // InterfaceMethod java/util/List.add:(Ljava/lang/Object;)Z
      38: pop           
      39: aload_2       
      40: ldc_w         #297                // String x
      43: invokeinterface #139,  2          // InterfaceMethod org/eclipse/core/runtime/IPath.append:(Ljava/lang/String;)Lorg/eclipse/core/runtime/IPath;
      48: astore_3      
      49: aload_0       
      50: aload_3       
      51: ldc_w         #299                // String xa
      54: invokespecial #149                // Method createProject:(Lorg/eclipse/core/runtime/IPath;Ljava/lang/String;)Lorg/eclipse/core/resources/IProject;
      57: astore        4
      59: aload_0       
      60: aload_3       
      61: ldc_w         #301                // String xb
      64: invokespecial #149                // Method createProject:(Lorg/eclipse/core/runtime/IPath;Ljava/lang/String;)Lorg/eclipse/core/resources/IProject;
      67: astore        5
      69: aload_3       
      70: invokestatic  #323                // Method createUrl:(Lorg/eclipse/core/runtime/IPath;)Ljava/lang/String;
      73: astore        6
      75: aload_0       
      76: aload_3       
      77: aload         6
      79: ldc           #166                // String stable
      81: invokespecial #128                // Method createRepository:(Lorg/eclipse/core/runtime/IPath;Ljava/lang/String;Ljava/lang/String;)Ljava/io/File;
      84: pop           
      85: aload         4
      87: iconst_0      
      88: iconst_1      
      89: aconst_null   
      90: invokeinterface #93,  4           // InterfaceMethod org/eclipse/core/resources/IProject.delete:(ZZLorg/eclipse/core/runtime/IProgressMonitor;)V
      95: aload         5
      97: iconst_0      
      98: iconst_1      
      99: aconst_null   
     100: invokeinterface #93,  4           // InterfaceMethod org/eclipse/core/resources/IProject.delete:(ZZLorg/eclipse/core/runtime/IProgressMonitor;)V
     105: aload_3       
     106: ldc           #126                // String master
     108: ldc_w         #299                // String xa
     111: invokestatic  #327                // Method createProjectReference:(Lorg/eclipse/core/runtime/IPath;Ljava/lang/String;Ljava/lang/String;)Ljava/lang/String;
     114: astore        7
     116: aload_3       
     117: ldc           #126                // String master
     119: ldc_w         #301                // String xb
     122: invokestatic  #327                // Method createProjectReference:(Lorg/eclipse/core/runtime/IPath;Ljava/lang/String;Ljava/lang/String;)Ljava/lang/String;
     125: astore        8
     127: aload_0       
     128: iconst_1      
     129: anewarray     #244                // class java/lang/String
     132: dup           
     133: iconst_0      
     134: aload         7
     136: aastore       
     137: invokespecial #246                // Method addToWorkspace:([Ljava/lang/String;)V
     140: aload_0       
     141: iconst_1      
     142: anewarray     #244                // class java/lang/String
     145: dup           
     146: iconst_0      
     147: aload         8
     149: aastore       
     150: invokespecial #246                // Method addToWorkspace:([Ljava/lang/String;)V
     153: aload_0       
     154: getfield      #23                 // Field pathsToClean:Ljava/util/List;
     157: aload_1       
     158: invokeinterface #136,  1          // InterfaceMethod org/eclipse/core/resources/IWorkspaceRoot.getLocation:()Lorg/eclipse/core/runtime/IPath;
     163: ldc_w         #297                // String x
     166: invokeinterface #139,  2          // InterfaceMethod org/eclipse/core/runtime/IPath.append:(Ljava/lang/String;)Lorg/eclipse/core/runtime/IPath;
     171: invokeinterface #154,  1          // InterfaceMethod org/eclipse/core/runtime/IPath.toFile:()Ljava/io/File;
     176: invokeinterface #158,  2          // InterfaceMethod java/util/List.add:(Ljava/lang/Object;)Z
     181: pop           
     182: aload_2       
     183: ldc_w         #331                // String other
     186: invokeinterface #139,  2          // InterfaceMethod org/eclipse/core/runtime/IPath.append:(Ljava/lang/String;)Lorg/eclipse/core/runtime/IPath;
     191: ldc_w         #297                // String x
     194: invokeinterface #139,  2          // InterfaceMethod org/eclipse/core/runtime/IPath.append:(Ljava/lang/String;)Lorg/eclipse/core/runtime/IPath;
     199: astore        9
     201: aload         9
     203: ldc           #126                // String master
     205: ldc_w         #301                // String xb
     208: invokestatic  #327                // Method createProjectReference:(Lorg/eclipse/core/runtime/IPath;Ljava/lang/String;Ljava/lang/String;)Ljava/lang/String;
     211: astore        10
     213: aload_0       
     214: getfield      #50                 // Field capability:Lorg/eclipse/egit/core/GitProjectSetCapability;
     217: iconst_1      
     218: anewarray     #244                // class java/lang/String
     221: dup           
     222: iconst_0      
     223: aload         10
     225: aastore       
     226: new           #168                // class org/eclipse/team/core/ProjectSetSerializationContext
     229: dup           
     230: invokespecial #170                // Method org/eclipse/team/core/ProjectSetSerializationContext."<init>":()V
     233: new           #171                // class org/eclipse/core/runtime/NullProgressMonitor
     236: dup           
     237: invokespecial #173                // Method org/eclipse/core/runtime/NullProgressMonitor."<init>":()V
     240: invokevirtual #333                // Method org/eclipse/egit/core/GitProjectSetCapability.addToWorkspace:([Ljava/lang/String;Lorg/eclipse/team/core/ProjectSetSerializationContext;Lorg/eclipse/core/runtime/IProgressMonitor;)[Lorg/eclipse/core/resources/IProject;
     243: pop           
     244: ldc_w         #336                // String Should throw TeamException when a repo exists at the place but doesn't have the same URL.
     247: invokestatic  #338                // Method org/junit/Assert.fail:(Ljava/lang/String;)V
     250: goto          254
     253: pop           
     254: return        
    Exception table:
       from    to  target type
         213   250   253   Class org/eclipse/team/core/TeamException

  public void testImportWhereRepoAlreadyExistsAtDifferentLocation() throws java.lang.Exception;
    Code:
       0: invokestatic  #57                 // Method org/eclipse/core/resources/ResourcesPlugin.getWorkspace:()Lorg/eclipse/core/resources/IWorkspace;
       3: invokeinterface #63,  1           // InterfaceMethod org/eclipse/core/resources/IWorkspace.getRoot:()Lorg/eclipse/core/resources/IWorkspaceRoot;
       8: astore_1      
       9: aload_1       
      10: invokeinterface #136,  1          // InterfaceMethod org/eclipse/core/resources/IWorkspaceRoot.getLocation:()Lorg/eclipse/core/runtime/IPath;
      15: ldc_w         #349                // String existingbutdifferent
      18: invokeinterface #139,  2          // InterfaceMethod org/eclipse/core/runtime/IPath.append:(Ljava/lang/String;)Lorg/eclipse/core/runtime/IPath;
      23: astore_2      
      24: aload_0       
      25: getfield      #23                 // Field pathsToClean:Ljava/util/List;
      28: aload_2       
      29: invokeinterface #154,  1          // InterfaceMethod org/eclipse/core/runtime/IPath.toFile:()Ljava/io/File;
      34: invokeinterface #158,  2          // InterfaceMethod java/util/List.add:(Ljava/lang/Object;)Z
      39: pop           
      40: aload_2       
      41: ldc_w         #351                // String repo
      44: invokeinterface #139,  2          // InterfaceMethod org/eclipse/core/runtime/IPath.append:(Ljava/lang/String;)Lorg/eclipse/core/runtime/IPath;
      49: astore_3      
      50: aload_0       
      51: aload_3       
      52: ldc_w         #353                // String project
      55: invokespecial #149                // Method createProject:(Lorg/eclipse/core/runtime/IPath;Ljava/lang/String;)Lorg/eclipse/core/resources/IProject;
      58: astore        4
      60: aload         4
      62: iconst_0      
      63: iconst_1      
      64: aconst_null   
      65: invokeinterface #93,  4           // InterfaceMethod org/eclipse/core/resources/IProject.delete:(ZZLorg/eclipse/core/runtime/IProgressMonitor;)V
      70: aload_3       
      71: invokestatic  #323                // Method createUrl:(Lorg/eclipse/core/runtime/IPath;)Ljava/lang/String;
      74: astore        5
      76: aload_0       
      77: aload_3       
      78: aload         5
      80: ldc           #126                // String master
      82: invokespecial #128                // Method createRepository:(Lorg/eclipse/core/runtime/IPath;Ljava/lang/String;Ljava/lang/String;)Ljava/io/File;
      85: astore        6
      87: aload_2       
      88: ldc_w         #331                // String other
      91: invokeinterface #139,  2          // InterfaceMethod org/eclipse/core/runtime/IPath.append:(Ljava/lang/String;)Lorg/eclipse/core/runtime/IPath;
      96: astore        7
      98: aload_0       
      99: aload         7
     101: ldc_w         #354                // String other-url
     104: ldc           #126                // String master
     106: invokespecial #128                // Method createRepository:(Lorg/eclipse/core/runtime/IPath;Ljava/lang/String;Ljava/lang/String;)Ljava/io/File;
     109: astore        8
     111: invokestatic  #32                 // Method org/eclipse/egit/core/Activator.getDefault:()Lorg/eclipse/egit/core/Activator;
     114: invokevirtual #356                // Method org/eclipse/egit/core/Activator.getRepositoryUtil:()Lorg/eclipse/egit/core/RepositoryUtil;
     117: astore        9
     119: aload         9
     121: aload         6
     123: invokevirtual #360                // Method org/eclipse/egit/core/RepositoryUtil.addConfiguredRepository:(Ljava/io/File;)Z
     126: pop           
     127: aload         9
     129: aload         8
     131: invokevirtual #360                // Method org/eclipse/egit/core/RepositoryUtil.addConfiguredRepository:(Ljava/io/File;)Z
     134: pop           
     135: aload_3       
     136: ldc           #126                // String master
     138: ldc_w         #353                // String project
     141: invokestatic  #327                // Method createProjectReference:(Lorg/eclipse/core/runtime/IPath;Ljava/lang/String;Ljava/lang/String;)Ljava/lang/String;
     144: astore        10
     146: aload_0       
     147: iconst_1      
     148: anewarray     #244                // class java/lang/String
     151: dup           
     152: iconst_0      
     153: aload         10
     155: aastore       
     156: invokespecial #246                // Method addToWorkspace:([Ljava/lang/String;)V
     159: aload_1       
     160: ldc_w         #353                // String project
     163: invokeinterface #250,  2          // InterfaceMethod org/eclipse/core/resources/IWorkspaceRoot.getProject:(Ljava/lang/String;)Lorg/eclipse/core/resources/IProject;
     168: astore        11
     170: ldc_w         #366                // String Expected imported project to be from already existing repository
     173: aload_1       
     174: invokeinterface #136,  1          // InterfaceMethod org/eclipse/core/resources/IWorkspaceRoot.getLocation:()Lorg/eclipse/core/runtime/IPath;
     179: ldc_w         #368                // String existingbutdifferent/repo/project
     182: invokeinterface #139,  2          // InterfaceMethod org/eclipse/core/runtime/IPath.append:(Ljava/lang/String;)Lorg/eclipse/core/runtime/IPath;
     187: aload         11
     189: invokeinterface #120,  1          // InterfaceMethod org/eclipse/core/resources/IProject.getLocation:()Lorg/eclipse/core/runtime/IPath;
     194: invokestatic  #370                // Method org/junit/Assert.assertEquals:(Ljava/lang/String;Ljava/lang/Object;Ljava/lang/Object;)V
     197: return        

  public void testImportFromRepoWithUrlOnlyDifferingInUserName() throws java.lang.Exception;
    Code:
       0: invokestatic  #57                 // Method org/eclipse/core/resources/ResourcesPlugin.getWorkspace:()Lorg/eclipse/core/resources/IWorkspace;
       3: invokeinterface #63,  1           // InterfaceMethod org/eclipse/core/resources/IWorkspace.getRoot:()Lorg/eclipse/core/resources/IWorkspaceRoot;
       8: astore_1      
       9: aload_1       
      10: invokeinterface #136,  1          // InterfaceMethod org/eclipse/core/resources/IWorkspaceRoot.getLocation:()Lorg/eclipse/core/runtime/IPath;
      15: ldc           #211                // String repos
      17: invokeinterface #139,  2          // InterfaceMethod org/eclipse/core/runtime/IPath.append:(Ljava/lang/String;)Lorg/eclipse/core/runtime/IPath;
      22: astore_2      
      23: aload_0       
      24: getfield      #23                 // Field pathsToClean:Ljava/util/List;
      27: aload_2       
      28: invokeinterface #154,  1          // InterfaceMethod org/eclipse/core/runtime/IPath.toFile:()Ljava/io/File;
      33: invokeinterface #158,  2          // InterfaceMethod java/util/List.add:(Ljava/lang/Object;)Z
      38: pop           
      39: aload_2       
      40: ldc_w         #351                // String repo
      43: invokeinterface #139,  2          // InterfaceMethod org/eclipse/core/runtime/IPath.append:(Ljava/lang/String;)Lorg/eclipse/core/runtime/IPath;
      48: astore_3      
      49: aload_0       
      50: aload_3       
      51: ldc_w         #353                // String project
      54: invokespecial #149                // Method createProject:(Lorg/eclipse/core/runtime/IPath;Ljava/lang/String;)Lorg/eclipse/core/resources/IProject;
      57: astore        4
      59: aload         4
      61: iconst_0      
      62: iconst_1      
      63: aconst_null   
      64: invokeinterface #93,  4           // InterfaceMethod org/eclipse/core/resources/IProject.delete:(ZZLorg/eclipse/core/runtime/IProgressMonitor;)V
      69: aload_3       
      70: ldc_w         #382                // String ssh
      73: ldc_w         #384                // String userName
      76: invokestatic  #386                // Method createUrl:(Lorg/eclipse/core/runtime/IPath;Ljava/lang/String;Ljava/lang/String;)Ljava/lang/String;
      79: astore        5
      81: aload_0       
      82: aload_3       
      83: aload         5
      85: ldc           #126                // String master
      87: invokespecial #128                // Method createRepository:(Lorg/eclipse/core/runtime/IPath;Ljava/lang/String;Ljava/lang/String;)Ljava/io/File;
      90: astore        6
      92: invokestatic  #32                 // Method org/eclipse/egit/core/Activator.getDefault:()Lorg/eclipse/egit/core/Activator;
      95: invokevirtual #356                // Method org/eclipse/egit/core/Activator.getRepositoryUtil:()Lorg/eclipse/egit/core/RepositoryUtil;
      98: astore        7
     100: aload         7
     102: aload         6
     104: invokevirtual #360                // Method org/eclipse/egit/core/RepositoryUtil.addConfiguredRepository:(Ljava/io/File;)Z
     107: pop           
     108: aload_3       
     109: ldc_w         #382                // String ssh
     112: aconst_null   
     113: ldc           #126                // String master
     115: ldc_w         #353                // String project
     118: invokestatic  #388                // Method createProjectReference:(Lorg/eclipse/core/runtime/IPath;Ljava/lang/String;Ljava/lang/String;Ljava/lang/String;Ljava/lang/String;)Ljava/lang/String;
     121: astore        8
     123: aload_0       
     124: iconst_1      
     125: anewarray     #244                // class java/lang/String
     128: dup           
     129: iconst_0      
     130: aload         8
     132: aastore       
     133: invokespecial #246                // Method addToWorkspace:([Ljava/lang/String;)V
     136: aload_1       
     137: ldc_w         #353                // String project
     140: invokeinterface #250,  2          // InterfaceMethod org/eclipse/core/resources/IWorkspaceRoot.getProject:(Ljava/lang/String;)Lorg/eclipse/core/resources/IProject;
     145: astore        9
     147: ldc_w         #391                // String Expected imported project to be from already existing repository. User name must be ignored in URL.
     150: aload_1       
     151: invokeinterface #136,  1          // InterfaceMethod org/eclipse/core/resources/IWorkspaceRoot.getLocation:()Lorg/eclipse/core/runtime/IPath;
     156: ldc_w         #393                // String repos/repo/project
     159: invokeinterface #139,  2          // InterfaceMethod org/eclipse/core/runtime/IPath.append:(Ljava/lang/String;)Lorg/eclipse/core/runtime/IPath;
     164: aload         9
     166: invokeinterface #120,  1          // InterfaceMethod org/eclipse/core/resources/IProject.getLocation:()Lorg/eclipse/core/runtime/IPath;
     171: invokestatic  #370                // Method org/junit/Assert.assertEquals:(Ljava/lang/String;Ljava/lang/Object;Ljava/lang/Object;)V
     174: return        

  private org.eclipse.core.resources.IProject createProject(java.lang.String) throws org.eclipse.core.runtime.CoreException;
    Code:
       0: invokestatic  #57                 // Method org/eclipse/core/resources/ResourcesPlugin.getWorkspace:()Lorg/eclipse/core/resources/IWorkspace;
       3: invokeinterface #63,  1           // InterfaceMethod org/eclipse/core/resources/IWorkspace.getRoot:()Lorg/eclipse/core/resources/IWorkspaceRoot;
       8: astore_2      
       9: aload_2       
      10: aload_1       
      11: invokeinterface #250,  2          // InterfaceMethod org/eclipse/core/resources/IWorkspaceRoot.getProject:(Ljava/lang/String;)Lorg/eclipse/core/resources/IProject;
      16: astore_3      
      17: aload_3       
      18: aconst_null   
      19: invokeinterface #397,  2          // InterfaceMethod org/eclipse/core/resources/IProject.create:(Lorg/eclipse/core/runtime/IProgressMonitor;)V
      24: aload_3       
      25: aconst_null   
      26: invokeinterface #401,  2          // InterfaceMethod org/eclipse/core/resources/IProject.open:(Lorg/eclipse/core/runtime/IProgressMonitor;)V
      31: aload_0       
      32: getfield      #21                 // Field createdProjects:Ljava/util/List;
      35: aload_3       
      36: invokeinterface #158,  2          // InterfaceMethod java/util/List.add:(Ljava/lang/Object;)Z
      41: pop           
      42: aload_3       
      43: areturn       

  private org.eclipse.core.resources.IProject createProject(org.eclipse.core.runtime.IPath, java.lang.String) throws org.eclipse.core.runtime.CoreException;
    Code:
       0: invokestatic  #57                 // Method org/eclipse/core/resources/ResourcesPlugin.getWorkspace:()Lorg/eclipse/core/resources/IWorkspace;
       3: invokeinterface #63,  1           // InterfaceMethod org/eclipse/core/resources/IWorkspace.getRoot:()Lorg/eclipse/core/resources/IWorkspaceRoot;
       8: astore_3      
       9: aload_3       
      10: aload_2       
      11: invokeinterface #250,  2          // InterfaceMethod org/eclipse/core/resources/IWorkspaceRoot.getProject:(Ljava/lang/String;)Lorg/eclipse/core/resources/IProject;
      16: astore        4
      18: invokestatic  #57                 // Method org/eclipse/core/resources/ResourcesPlugin.getWorkspace:()Lorg/eclipse/core/resources/IWorkspace;
      21: aload         4
      23: invokeinterface #406,  1          // InterfaceMethod org/eclipse/core/resources/IProject.getName:()Ljava/lang/String;
      28: invokeinterface #409,  2          // InterfaceMethod org/eclipse/core/resources/IWorkspace.newProjectDescription:(Ljava/lang/String;)Lorg/eclipse/core/resources/IProjectDescription;
      33: astore        5
      35: aload         5
      37: aload_1       
      38: aload_2       
      39: invokeinterface #139,  2          // InterfaceMethod org/eclipse/core/runtime/IPath.append:(Ljava/lang/String;)Lorg/eclipse/core/runtime/IPath;
      44: invokeinterface #413,  2          // InterfaceMethod org/eclipse/core/resources/IProjectDescription.setLocation:(Lorg/eclipse/core/runtime/IPath;)V
      49: aload         4
      51: aload         5
      53: aconst_null   
      54: invokeinterface #419,  3          // InterfaceMethod org/eclipse/core/resources/IProject.create:(Lorg/eclipse/core/resources/IProjectDescription;Lorg/eclipse/core/runtime/IProgressMonitor;)V
      59: aload         4
      61: aconst_null   
      62: invokeinterface #401,  2          // InterfaceMethod org/eclipse/core/resources/IProject.open:(Lorg/eclipse/core/runtime/IProgressMonitor;)V
      67: aload_0       
      68: getfield      #21                 // Field createdProjects:Ljava/util/List;
      71: aload         4
      73: invokeinterface #158,  2          // InterfaceMethod java/util/List.add:(Ljava/lang/Object;)Z
      78: pop           
      79: aload         4
      81: areturn       

  private java.io.File createRepository(org.eclipse.core.runtime.IPath, java.lang.String, java.lang.String) throws java.lang.Exception;
    Code:
       0: new           #99                 // class java/io/File
       3: dup           
       4: aload_1       
       5: invokeinterface #154,  1          // InterfaceMethod org/eclipse/core/runtime/IPath.toFile:()Ljava/io/File;
      10: ldc_w         #425                // String .git
      13: invokespecial #427                // Method java/io/File."<init>":(Ljava/io/File;Ljava/lang/String;)V
      16: astore        4
      18: aload         4
      20: invokestatic  #430                // Method org/eclipse/jgit/storage/file/FileRepositoryBuilder.create:(Ljava/io/File;)Lorg/eclipse/jgit/lib/Repository;
      23: astore        5
      25: aload         5
      27: invokevirtual #435                // Method org/eclipse/jgit/lib/Repository.getConfig:()Lorg/eclipse/jgit/lib/StoredConfig;
      30: ldc_w         #439                // String remote
      33: ldc_w         #441                // String origin
      36: ldc_w         #443                // String url
      39: aload_2       
      40: invokevirtual #444                // Method org/eclipse/jgit/lib/StoredConfig.setString:(Ljava/lang/String;Ljava/lang/String;Ljava/lang/String;Ljava/lang/String;)V
      43: aload         5
      45: invokevirtual #435                // Method org/eclipse/jgit/lib/Repository.getConfig:()Lorg/eclipse/jgit/lib/StoredConfig;
      48: ldc_w         #450                // String branch
      51: aload_3       
      52: ldc_w         #439                // String remote
      55: ldc_w         #441                // String origin
      58: invokevirtual #444                // Method org/eclipse/jgit/lib/StoredConfig.setString:(Ljava/lang/String;Ljava/lang/String;Ljava/lang/String;Ljava/lang/String;)V
      61: aload         5
      63: invokevirtual #452                // Method org/eclipse/jgit/lib/Repository.create:()V
      66: aload         5
      68: invokevirtual #454                // Method org/eclipse/jgit/lib/Repository.close:()V
      71: new           #457                // class org/eclipse/jgit/api/Git
      74: dup           
      75: aload         5
      77: invokespecial #459                // Method org/eclipse/jgit/api/Git."<init>":(Lorg/eclipse/jgit/lib/Repository;)V
      80: astore        6
      82: aload         6
      84: invokevirtual #462                // Method org/eclipse/jgit/api/Git.add:()Lorg/eclipse/jgit/api/AddCommand;
      87: ldc_w         #465                // String .
      90: invokevirtual #467                // Method org/eclipse/jgit/api/AddCommand.addFilepattern:(Ljava/lang/String;)Lorg/eclipse/jgit/api/AddCommand;
      93: invokevirtual #473                // Method org/eclipse/jgit/api/AddCommand.call:()Lorg/eclipse/jgit/dircache/DirCache;
      96: pop           
      97: aload         6
      99: invokevirtual #477                // Method org/eclipse/jgit/api/Git.commit:()Lorg/eclipse/jgit/api/CommitCommand;
     102: ldc_w         #481                // String initial
     105: invokevirtual #483                // Method org/eclipse/jgit/api/CommitCommand.setMessage:(Ljava/lang/String;)Lorg/eclipse/jgit/api/CommitCommand;
     108: invokevirtual #489                // Method org/eclipse/jgit/api/CommitCommand.call:()Lorg/eclipse/jgit/revwalk/RevCommit;
     111: pop           
     112: aload_3       
     113: ldc           #126                // String master
     115: invokevirtual #492                // Method java/lang/String.equals:(Ljava/lang/Object;)Z
     118: ifne          138
     121: aload         6
     123: invokevirtual #495                // Method org/eclipse/jgit/api/Git.checkout:()Lorg/eclipse/jgit/api/CheckoutCommand;
     126: aload_3       
     127: invokevirtual #499                // Method org/eclipse/jgit/api/CheckoutCommand.setName:(Ljava/lang/String;)Lorg/eclipse/jgit/api/CheckoutCommand;
     130: iconst_1      
     131: invokevirtual #505                // Method org/eclipse/jgit/api/CheckoutCommand.setCreateBranch:(Z)Lorg/eclipse/jgit/api/CheckoutCommand;
     134: invokevirtual #509                // Method org/eclipse/jgit/api/CheckoutCommand.call:()Lorg/eclipse/jgit/lib/Ref;
     137: pop           
     138: aload_0       
     139: getfield      #23                 // Field pathsToClean:Ljava/util/List;
     142: aload         4
     144: invokeinterface #158,  2          // InterfaceMethod java/util/List.add:(Ljava/lang/Object;)Z
     149: pop           
     150: aload         4
     152: areturn       

  private void connectProject(org.eclipse.core.resources.IProject, java.io.File) throws org.eclipse.core.runtime.CoreException;
    Code:
       0: new           #517                // class org/eclipse/egit/core/op/ConnectProviderOperation
       3: dup           
       4: aload_1       
       5: invokeinterface #519,  1          // InterfaceMethod org/eclipse/core/resources/IProject.getProject:()Lorg/eclipse/core/resources/IProject;
      10: aload_2       
      11: invokespecial #522                // Method org/eclipse/egit/core/op/ConnectProviderOperation."<init>":(Lorg/eclipse/core/resources/IProject;Ljava/io/File;)V
      14: astore_3      
      15: aload_3       
      16: aconst_null   
      17: invokevirtual #524                // Method org/eclipse/egit/core/op/ConnectProviderOperation.execute:(Lorg/eclipse/core/runtime/IProgressMonitor;)V
      20: return        

  private static java.lang.String createProjectReference(org.eclipse.core.runtime.IPath, java.lang.String, java.lang.String);
    Code:
       0: new           #215                // class java/lang/StringBuilder
       3: dup           
       4: ldc           #217                // String 1.0,
       6: invokespecial #219                // Method java/lang/StringBuilder."<init>":(Ljava/lang/String;)V
       9: aload_0       
      10: invokestatic  #323                // Method createUrl:(Lorg/eclipse/core/runtime/IPath;)Ljava/lang/String;
      13: invokevirtual #232                // Method java/lang/StringBuilder.append:(Ljava/lang/String;)Ljava/lang/StringBuilder;
      16: ldc_w         #530                // String ,
      19: invokevirtual #232                // Method java/lang/StringBuilder.append:(Ljava/lang/String;)Ljava/lang/StringBuilder;
      22: aload_1       
      23: invokevirtual #232                // Method java/lang/StringBuilder.append:(Ljava/lang/String;)Ljava/lang/StringBuilder;
      26: ldc_w         #530                // String ,
      29: invokevirtual #232                // Method java/lang/StringBuilder.append:(Ljava/lang/String;)Ljava/lang/StringBuilder;
      32: aload_2       
      33: invokevirtual #232                // Method java/lang/StringBuilder.append:(Ljava/lang/String;)Ljava/lang/StringBuilder;
      36: invokevirtual #237                // Method java/lang/StringBuilder.toString:()Ljava/lang/String;
      39: areturn       

  private static java.lang.String createProjectReference(org.eclipse.core.runtime.IPath, java.lang.String, java.lang.String, java.lang.String, java.lang.String) throws java.lang.Exception;
    Code:
       0: new           #215                // class java/lang/StringBuilder
       3: dup           
       4: ldc           #217                // String 1.0,
       6: invokespecial #219                // Method java/lang/StringBuilder."<init>":(Ljava/lang/String;)V
       9: aload_0       
      10: aload_1       
      11: aload_2       
      12: invokestatic  #386                // Method createUrl:(Lorg/eclipse/core/runtime/IPath;Ljava/lang/String;Ljava/lang/String;)Ljava/lang/String;
      15: invokevirtual #232                // Method java/lang/StringBuilder.append:(Ljava/lang/String;)Ljava/lang/StringBuilder;
      18: ldc_w         #530                // String ,
      21: invokevirtual #232                // Method java/lang/StringBuilder.append:(Ljava/lang/String;)Ljava/lang/StringBuilder;
      24: aload_3       
      25: invokevirtual #232                // Method java/lang/StringBuilder.append:(Ljava/lang/String;)Ljava/lang/StringBuilder;
      28: ldc_w         #530                // String ,
      31: invokevirtual #232                // Method java/lang/StringBuilder.append:(Ljava/lang/String;)Ljava/lang/StringBuilder;
      34: aload         4
      36: invokevirtual #232                // Method java/lang/StringBuilder.append:(Ljava/lang/String;)Ljava/lang/StringBuilder;
      39: invokevirtual #237                // Method java/lang/StringBuilder.toString:()Ljava/lang/String;
      42: areturn       

  private static java.lang.String createUrl(org.eclipse.core.runtime.IPath);
    Code:
       0: aload_0       
       1: invokeinterface #154,  1          // InterfaceMethod org/eclipse/core/runtime/IPath.toFile:()Ljava/io/File;
       6: invokevirtual #222                // Method java/io/File.toURI:()Ljava/net/URI;
       9: invokevirtual #226                // Method java/net/URI.toString:()Ljava/lang/String;
      12: areturn       

  private static java.lang.String createUrl(org.eclipse.core.runtime.IPath, java.lang.String, java.lang.String) throws java.net.URISyntaxException;
    Code:
       0: new           #227                // class java/net/URI
       3: dup           
       4: aload_1       
       5: aload_2       
       6: ldc_w         #537                // String localhost
       9: bipush        42
      11: aload_0       
      12: aconst_null   
      13: invokeinterface #539,  2          // InterfaceMethod org/eclipse/core/runtime/IPath.setDevice:(Ljava/lang/String;)Lorg/eclipse/core/runtime/IPath;
      18: invokeinterface #542,  1          // InterfaceMethod org/eclipse/core/runtime/IPath.makeAbsolute:()Lorg/eclipse/core/runtime/IPath;
      23: invokeinterface #545,  1          // InterfaceMethod org/eclipse/core/runtime/IPath.toString:()Ljava/lang/String;
      28: aconst_null   
      29: aconst_null   
      30: invokespecial #546                // Method java/net/URI."<init>":(Ljava/lang/String;Ljava/lang/String;Ljava/lang/String;ILjava/lang/String;Ljava/lang/String;Ljava/lang/String;)V
      33: astore_3      
      34: aload_3       
      35: invokevirtual #226                // Method java/net/URI.toString:()Ljava/lang/String;
      38: areturn       

  private void addToWorkspace(java.lang.String[]) throws org.eclipse.team.core.TeamException;
    Code:
       0: aload_0       
       1: getfield      #50                 // Field capability:Lorg/eclipse/egit/core/GitProjectSetCapability;
       4: aload_1       
       5: new           #168                // class org/eclipse/team/core/ProjectSetSerializationContext
       8: dup           
       9: invokespecial #170                // Method org/eclipse/team/core/ProjectSetSerializationContext."<init>":()V
      12: new           #171                // class org/eclipse/core/runtime/NullProgressMonitor
      15: dup           
      16: invokespecial #173                // Method org/eclipse/core/runtime/NullProgressMonitor."<init>":()V
      19: invokevirtual #333                // Method org/eclipse/egit/core/GitProjectSetCapability.addToWorkspace:([Ljava/lang/String;Lorg/eclipse/team/core/ProjectSetSerializationContext;Lorg/eclipse/core/runtime/IProgressMonitor;)[Lorg/eclipse/core/resources/IProject;
      22: pop           
      23: return        
}
