Compiled from "ThreeWayDiffEntryTest.java"
public class org.eclipse.egit.core.synchronize.ThreeWayDiffEntryTest extends org.eclipse.jgit.junit.LocalDiskRepositoryTestCase {
  private org.eclipse.jgit.lib.Repository db;

  public org.eclipse.egit.core.synchronize.ThreeWayDiffEntryTest();
    Code:
       0: aload_0       
       1: invokespecial #10                 // Method org/eclipse/jgit/junit/LocalDiskRepositoryTestCase."<init>":()V
       4: return        

  public void setUp() throws java.lang.Exception;
    Code:
       0: aload_0       
       1: invokespecial #22                 // Method org/eclipse/jgit/junit/LocalDiskRepositoryTestCase.setUp:()V
       4: aload_0       
       5: aload_0       
       6: invokevirtual #24                 // Method createWorkRepository:()Lorg/eclipse/jgit/internal/storage/file/FileRepository;
       9: putfield      #28                 // Field db:Lorg/eclipse/jgit/lib/Repository;
      12: return        

  public void testShouldListOutgoingAddition() throws java.lang.Exception;
    Code:
       0: aload_0       
       1: ldc           #32                 // String a.txt
       3: ldc           #34                 // String content
       5: invokespecial #36                 // Method writeTrashFile:(Ljava/lang/String;Ljava/lang/String;)Ljava/io/File;
       8: pop           
       9: new           #40                 // class org/eclipse/jgit/api/Git
      12: dup           
      13: aload_0       
      14: getfield      #28                 // Field db:Lorg/eclipse/jgit/lib/Repository;
      17: invokespecial #42                 // Method org/eclipse/jgit/api/Git."<init>":(Lorg/eclipse/jgit/lib/Repository;)V
      20: astore_1      
      21: aload_1       
      22: invokevirtual #45                 // Method org/eclipse/jgit/api/Git.add:()Lorg/eclipse/jgit/api/AddCommand;
      25: ldc           #32                 // String a.txt
      27: invokevirtual #49                 // Method org/eclipse/jgit/api/AddCommand.addFilepattern:(Ljava/lang/String;)Lorg/eclipse/jgit/api/AddCommand;
      30: invokevirtual #55                 // Method org/eclipse/jgit/api/AddCommand.call:()Lorg/eclipse/jgit/dircache/DirCache;
      33: pop           
      34: aload_1       
      35: invokevirtual #59                 // Method org/eclipse/jgit/api/Git.commit:()Lorg/eclipse/jgit/api/CommitCommand;
      38: ldc           #63                 // String initial commit
      40: invokevirtual #65                 // Method org/eclipse/jgit/api/CommitCommand.setMessage:(Ljava/lang/String;)Lorg/eclipse/jgit/api/CommitCommand;
      43: invokevirtual #71                 // Method org/eclipse/jgit/api/CommitCommand.call:()Lorg/eclipse/jgit/revwalk/RevCommit;
      46: astore_2      
      47: aconst_null   
      48: astore_3      
      49: aconst_null   
      50: astore        4
      52: new           #74                 // class org/eclipse/jgit/treewalk/TreeWalk
      55: dup           
      56: aload_0       
      57: getfield      #28                 // Field db:Lorg/eclipse/jgit/lib/Repository;
      60: invokespecial #76                 // Method org/eclipse/jgit/treewalk/TreeWalk."<init>":(Lorg/eclipse/jgit/lib/Repository;)V
      63: astore        5
      65: aload         5
      67: aload_2       
      68: invokevirtual #77                 // Method org/eclipse/jgit/revwalk/RevCommit.getTree:()Lorg/eclipse/jgit/revwalk/RevTree;
      71: invokevirtual #83                 // Method org/eclipse/jgit/treewalk/TreeWalk.addTree:(Lorg/eclipse/jgit/lib/AnyObjectId;)I
      74: pop           
      75: aload         5
      77: new           #87                 // class org/eclipse/jgit/treewalk/EmptyTreeIterator
      80: dup           
      81: invokespecial #89                 // Method org/eclipse/jgit/treewalk/EmptyTreeIterator."<init>":()V
      84: invokevirtual #90                 // Method org/eclipse/jgit/treewalk/TreeWalk.addTree:(Lorg/eclipse/jgit/treewalk/AbstractTreeIterator;)I
      87: pop           
      88: aload         5
      90: new           #87                 // class org/eclipse/jgit/treewalk/EmptyTreeIterator
      93: dup           
      94: invokespecial #89                 // Method org/eclipse/jgit/treewalk/EmptyTreeIterator."<init>":()V
      97: invokevirtual #90                 // Method org/eclipse/jgit/treewalk/TreeWalk.addTree:(Lorg/eclipse/jgit/treewalk/AbstractTreeIterator;)I
     100: pop           
     101: aload         5
     103: invokestatic  #93                 // Method org/eclipse/egit/core/synchronize/ThreeWayDiffEntry.scan:(Lorg/eclipse/jgit/treewalk/TreeWalk;)Ljava/util/List;
     106: astore        6
     108: aload         6
     110: invokestatic  #99                 // Method org/hamcrest/CoreMatchers.notNullValue:()Lorg/hamcrest/Matcher;
     113: invokestatic  #105                // Method org/junit/Assert.assertThat:(Ljava/lang/Object;Lorg/hamcrest/Matcher;)V
     116: aload         6
     118: invokeinterface #111,  1          // InterfaceMethod java/util/List.size:()I
     123: invokestatic  #117                // Method java/lang/Integer.valueOf:(I)Ljava/lang/Integer;
     126: iconst_1      
     127: invokestatic  #117                // Method java/lang/Integer.valueOf:(I)Ljava/lang/Integer;
     130: invokestatic  #123                // Method org/hamcrest/CoreMatchers.is:(Ljava/lang/Object;)Lorg/hamcrest/Matcher;
     133: invokestatic  #105                // Method org/junit/Assert.assertThat:(Ljava/lang/Object;Lorg/hamcrest/Matcher;)V
     136: aload         6
     138: iconst_0      
     139: invokeinterface #127,  2          // InterfaceMethod java/util/List.get:(I)Ljava/lang/Object;
     144: checkcast     #94                 // class org/eclipse/egit/core/synchronize/ThreeWayDiffEntry
     147: astore        7
     149: aload         7
     151: invokevirtual #131                // Method org/eclipse/egit/core/synchronize/ThreeWayDiffEntry.getDirection:()Lorg/eclipse/egit/core/synchronize/ThreeWayDiffEntry$Direction;
     154: getstatic     #135                // Field org/eclipse/egit/core/synchronize/ThreeWayDiffEntry$Direction.OUTGOING:Lorg/eclipse/egit/core/synchronize/ThreeWayDiffEntry$Direction;
     157: invokestatic  #123                // Method org/hamcrest/CoreMatchers.is:(Ljava/lang/Object;)Lorg/hamcrest/Matcher;
     160: invokestatic  #105                // Method org/junit/Assert.assertThat:(Ljava/lang/Object;Lorg/hamcrest/Matcher;)V
     163: aload         7
     165: invokevirtual #141                // Method org/eclipse/egit/core/synchronize/ThreeWayDiffEntry.getChangeType:()Lorg/eclipse/egit/core/synchronize/ThreeWayDiffEntry$ChangeType;
     168: getstatic     #145                // Field org/eclipse/egit/core/synchronize/ThreeWayDiffEntry$ChangeType.ADD:Lorg/eclipse/egit/core/synchronize/ThreeWayDiffEntry$ChangeType;
     171: invokestatic  #123                // Method org/hamcrest/CoreMatchers.is:(Ljava/lang/Object;)Lorg/hamcrest/Matcher;
     174: invokestatic  #105                // Method org/junit/Assert.assertThat:(Ljava/lang/Object;Lorg/hamcrest/Matcher;)V
     177: aload         7
     179: invokevirtual #151                // Method org/eclipse/egit/core/synchronize/ThreeWayDiffEntry.getPath:()Ljava/lang/String;
     182: ldc           #32                 // String a.txt
     184: invokestatic  #123                // Method org/hamcrest/CoreMatchers.is:(Ljava/lang/Object;)Lorg/hamcrest/Matcher;
     187: invokestatic  #105                // Method org/junit/Assert.assertThat:(Ljava/lang/Object;Lorg/hamcrest/Matcher;)V
     190: aload         5
     192: ifnull        242
     195: aload         5
     197: invokevirtual #155                // Method org/eclipse/jgit/treewalk/TreeWalk.close:()V
     200: goto          242
     203: astore_3      
     204: aload         5
     206: ifnull        214
     209: aload         5
     211: invokevirtual #155                // Method org/eclipse/jgit/treewalk/TreeWalk.close:()V
     214: aload_3       
     215: athrow        
     216: astore        4
     218: aload_3       
     219: ifnonnull     228
     222: aload         4
     224: astore_3      
     225: goto          240
     228: aload_3       
     229: aload         4
     231: if_acmpeq     240
     234: aload_3       
     235: aload         4
     237: invokevirtual #158                // Method java/lang/Throwable.addSuppressed:(Ljava/lang/Throwable;)V
     240: aload_3       
     241: athrow        
     242: return        
    Exception table:
       from    to  target type
          65   190   203   any
          52   216   216   any

  public void testShouldListIncomingAddition() throws java.lang.Exception;
    Code:
       0: aload_0       
       1: ldc           #32                 // String a.txt
       3: ldc           #34                 // String content
       5: invokespecial #36                 // Method writeTrashFile:(Ljava/lang/String;Ljava/lang/String;)Ljava/io/File;
       8: pop           
       9: new           #40                 // class org/eclipse/jgit/api/Git
      12: dup           
      13: aload_0       
      14: getfield      #28                 // Field db:Lorg/eclipse/jgit/lib/Repository;
      17: invokespecial #42                 // Method org/eclipse/jgit/api/Git."<init>":(Lorg/eclipse/jgit/lib/Repository;)V
      20: astore_1      
      21: aload_1       
      22: invokevirtual #45                 // Method org/eclipse/jgit/api/Git.add:()Lorg/eclipse/jgit/api/AddCommand;
      25: ldc           #32                 // String a.txt
      27: invokevirtual #49                 // Method org/eclipse/jgit/api/AddCommand.addFilepattern:(Ljava/lang/String;)Lorg/eclipse/jgit/api/AddCommand;
      30: invokevirtual #55                 // Method org/eclipse/jgit/api/AddCommand.call:()Lorg/eclipse/jgit/dircache/DirCache;
      33: pop           
      34: aload_1       
      35: invokevirtual #59                 // Method org/eclipse/jgit/api/Git.commit:()Lorg/eclipse/jgit/api/CommitCommand;
      38: ldc           #63                 // String initial commit
      40: invokevirtual #65                 // Method org/eclipse/jgit/api/CommitCommand.setMessage:(Ljava/lang/String;)Lorg/eclipse/jgit/api/CommitCommand;
      43: invokevirtual #71                 // Method org/eclipse/jgit/api/CommitCommand.call:()Lorg/eclipse/jgit/revwalk/RevCommit;
      46: astore_2      
      47: aconst_null   
      48: astore_3      
      49: aconst_null   
      50: astore        4
      52: new           #74                 // class org/eclipse/jgit/treewalk/TreeWalk
      55: dup           
      56: aload_0       
      57: getfield      #28                 // Field db:Lorg/eclipse/jgit/lib/Repository;
      60: invokespecial #76                 // Method org/eclipse/jgit/treewalk/TreeWalk."<init>":(Lorg/eclipse/jgit/lib/Repository;)V
      63: astore        5
      65: aload         5
      67: new           #87                 // class org/eclipse/jgit/treewalk/EmptyTreeIterator
      70: dup           
      71: invokespecial #89                 // Method org/eclipse/jgit/treewalk/EmptyTreeIterator."<init>":()V
      74: invokevirtual #90                 // Method org/eclipse/jgit/treewalk/TreeWalk.addTree:(Lorg/eclipse/jgit/treewalk/AbstractTreeIterator;)I
      77: pop           
      78: aload         5
      80: new           #87                 // class org/eclipse/jgit/treewalk/EmptyTreeIterator
      83: dup           
      84: invokespecial #89                 // Method org/eclipse/jgit/treewalk/EmptyTreeIterator."<init>":()V
      87: invokevirtual #90                 // Method org/eclipse/jgit/treewalk/TreeWalk.addTree:(Lorg/eclipse/jgit/treewalk/AbstractTreeIterator;)I
      90: pop           
      91: aload         5
      93: aload_2       
      94: invokevirtual #77                 // Method org/eclipse/jgit/revwalk/RevCommit.getTree:()Lorg/eclipse/jgit/revwalk/RevTree;
      97: invokevirtual #83                 // Method org/eclipse/jgit/treewalk/TreeWalk.addTree:(Lorg/eclipse/jgit/lib/AnyObjectId;)I
     100: pop           
     101: aload         5
     103: invokestatic  #93                 // Method org/eclipse/egit/core/synchronize/ThreeWayDiffEntry.scan:(Lorg/eclipse/jgit/treewalk/TreeWalk;)Ljava/util/List;
     106: astore        6
     108: aload         6
     110: invokestatic  #99                 // Method org/hamcrest/CoreMatchers.notNullValue:()Lorg/hamcrest/Matcher;
     113: invokestatic  #105                // Method org/junit/Assert.assertThat:(Ljava/lang/Object;Lorg/hamcrest/Matcher;)V
     116: aload         6
     118: invokeinterface #111,  1          // InterfaceMethod java/util/List.size:()I
     123: invokestatic  #117                // Method java/lang/Integer.valueOf:(I)Ljava/lang/Integer;
     126: iconst_1      
     127: invokestatic  #117                // Method java/lang/Integer.valueOf:(I)Ljava/lang/Integer;
     130: invokestatic  #123                // Method org/hamcrest/CoreMatchers.is:(Ljava/lang/Object;)Lorg/hamcrest/Matcher;
     133: invokestatic  #105                // Method org/junit/Assert.assertThat:(Ljava/lang/Object;Lorg/hamcrest/Matcher;)V
     136: aload         6
     138: iconst_0      
     139: invokeinterface #127,  2          // InterfaceMethod java/util/List.get:(I)Ljava/lang/Object;
     144: checkcast     #94                 // class org/eclipse/egit/core/synchronize/ThreeWayDiffEntry
     147: astore        7
     149: aload         7
     151: invokevirtual #131                // Method org/eclipse/egit/core/synchronize/ThreeWayDiffEntry.getDirection:()Lorg/eclipse/egit/core/synchronize/ThreeWayDiffEntry$Direction;
     154: getstatic     #178                // Field org/eclipse/egit/core/synchronize/ThreeWayDiffEntry$Direction.INCOMING:Lorg/eclipse/egit/core/synchronize/ThreeWayDiffEntry$Direction;
     157: invokestatic  #123                // Method org/hamcrest/CoreMatchers.is:(Ljava/lang/Object;)Lorg/hamcrest/Matcher;
     160: invokestatic  #105                // Method org/junit/Assert.assertThat:(Ljava/lang/Object;Lorg/hamcrest/Matcher;)V
     163: aload         7
     165: invokevirtual #141                // Method org/eclipse/egit/core/synchronize/ThreeWayDiffEntry.getChangeType:()Lorg/eclipse/egit/core/synchronize/ThreeWayDiffEntry$ChangeType;
     168: getstatic     #145                // Field org/eclipse/egit/core/synchronize/ThreeWayDiffEntry$ChangeType.ADD:Lorg/eclipse/egit/core/synchronize/ThreeWayDiffEntry$ChangeType;
     171: invokestatic  #123                // Method org/hamcrest/CoreMatchers.is:(Ljava/lang/Object;)Lorg/hamcrest/Matcher;
     174: invokestatic  #105                // Method org/junit/Assert.assertThat:(Ljava/lang/Object;Lorg/hamcrest/Matcher;)V
     177: aload         7
     179: invokevirtual #151                // Method org/eclipse/egit/core/synchronize/ThreeWayDiffEntry.getPath:()Ljava/lang/String;
     182: ldc           #32                 // String a.txt
     184: invokestatic  #123                // Method org/hamcrest/CoreMatchers.is:(Ljava/lang/Object;)Lorg/hamcrest/Matcher;
     187: invokestatic  #105                // Method org/junit/Assert.assertThat:(Ljava/lang/Object;Lorg/hamcrest/Matcher;)V
     190: aload         5
     192: ifnull        242
     195: aload         5
     197: invokevirtual #155                // Method org/eclipse/jgit/treewalk/TreeWalk.close:()V
     200: goto          242
     203: astore_3      
     204: aload         5
     206: ifnull        214
     209: aload         5
     211: invokevirtual #155                // Method org/eclipse/jgit/treewalk/TreeWalk.close:()V
     214: aload_3       
     215: athrow        
     216: astore        4
     218: aload_3       
     219: ifnonnull     228
     222: aload         4
     224: astore_3      
     225: goto          240
     228: aload_3       
     229: aload         4
     231: if_acmpeq     240
     234: aload_3       
     235: aload         4
     237: invokevirtual #158                // Method java/lang/Throwable.addSuppressed:(Ljava/lang/Throwable;)V
     240: aload_3       
     241: athrow        
     242: return        
    Exception table:
       from    to  target type
          65   190   203   any
          52   216   216   any

  public void testShouldListOutgoingDelete() throws java.lang.Exception;
    Code:
       0: aload_0       
       1: ldc           #32                 // String a.txt
       3: ldc           #34                 // String content
       5: invokespecial #36                 // Method writeTrashFile:(Ljava/lang/String;Ljava/lang/String;)Ljava/io/File;
       8: pop           
       9: new           #40                 // class org/eclipse/jgit/api/Git
      12: dup           
      13: aload_0       
      14: getfield      #28                 // Field db:Lorg/eclipse/jgit/lib/Repository;
      17: invokespecial #42                 // Method org/eclipse/jgit/api/Git."<init>":(Lorg/eclipse/jgit/lib/Repository;)V
      20: astore_1      
      21: aload_1       
      22: invokevirtual #45                 // Method org/eclipse/jgit/api/Git.add:()Lorg/eclipse/jgit/api/AddCommand;
      25: ldc           #32                 // String a.txt
      27: invokevirtual #49                 // Method org/eclipse/jgit/api/AddCommand.addFilepattern:(Ljava/lang/String;)Lorg/eclipse/jgit/api/AddCommand;
      30: invokevirtual #55                 // Method org/eclipse/jgit/api/AddCommand.call:()Lorg/eclipse/jgit/dircache/DirCache;
      33: pop           
      34: aload_1       
      35: invokevirtual #59                 // Method org/eclipse/jgit/api/Git.commit:()Lorg/eclipse/jgit/api/CommitCommand;
      38: ldc           #63                 // String initial commit
      40: invokevirtual #65                 // Method org/eclipse/jgit/api/CommitCommand.setMessage:(Ljava/lang/String;)Lorg/eclipse/jgit/api/CommitCommand;
      43: invokevirtual #71                 // Method org/eclipse/jgit/api/CommitCommand.call:()Lorg/eclipse/jgit/revwalk/RevCommit;
      46: astore_2      
      47: aconst_null   
      48: astore_3      
      49: aconst_null   
      50: astore        4
      52: new           #74                 // class org/eclipse/jgit/treewalk/TreeWalk
      55: dup           
      56: aload_0       
      57: getfield      #28                 // Field db:Lorg/eclipse/jgit/lib/Repository;
      60: invokespecial #76                 // Method org/eclipse/jgit/treewalk/TreeWalk."<init>":(Lorg/eclipse/jgit/lib/Repository;)V
      63: astore        5
      65: aload         5
      67: new           #87                 // class org/eclipse/jgit/treewalk/EmptyTreeIterator
      70: dup           
      71: invokespecial #89                 // Method org/eclipse/jgit/treewalk/EmptyTreeIterator."<init>":()V
      74: invokevirtual #90                 // Method org/eclipse/jgit/treewalk/TreeWalk.addTree:(Lorg/eclipse/jgit/treewalk/AbstractTreeIterator;)I
      77: pop           
      78: aload         5
      80: aload_2       
      81: invokevirtual #77                 // Method org/eclipse/jgit/revwalk/RevCommit.getTree:()Lorg/eclipse/jgit/revwalk/RevTree;
      84: invokevirtual #83                 // Method org/eclipse/jgit/treewalk/TreeWalk.addTree:(Lorg/eclipse/jgit/lib/AnyObjectId;)I
      87: pop           
      88: aload         5
      90: aload_2       
      91: invokevirtual #77                 // Method org/eclipse/jgit/revwalk/RevCommit.getTree:()Lorg/eclipse/jgit/revwalk/RevTree;
      94: invokevirtual #83                 // Method org/eclipse/jgit/treewalk/TreeWalk.addTree:(Lorg/eclipse/jgit/lib/AnyObjectId;)I
      97: pop           
      98: aload         5
     100: invokestatic  #93                 // Method org/eclipse/egit/core/synchronize/ThreeWayDiffEntry.scan:(Lorg/eclipse/jgit/treewalk/TreeWalk;)Ljava/util/List;
     103: astore        6
     105: aload         6
     107: invokestatic  #99                 // Method org/hamcrest/CoreMatchers.notNullValue:()Lorg/hamcrest/Matcher;
     110: invokestatic  #105                // Method org/junit/Assert.assertThat:(Ljava/lang/Object;Lorg/hamcrest/Matcher;)V
     113: aload         6
     115: invokeinterface #111,  1          // InterfaceMethod java/util/List.size:()I
     120: invokestatic  #117                // Method java/lang/Integer.valueOf:(I)Ljava/lang/Integer;
     123: iconst_1      
     124: invokestatic  #117                // Method java/lang/Integer.valueOf:(I)Ljava/lang/Integer;
     127: invokestatic  #123                // Method org/hamcrest/CoreMatchers.is:(Ljava/lang/Object;)Lorg/hamcrest/Matcher;
     130: invokestatic  #105                // Method org/junit/Assert.assertThat:(Ljava/lang/Object;Lorg/hamcrest/Matcher;)V
     133: aload         6
     135: iconst_0      
     136: invokeinterface #127,  2          // InterfaceMethod java/util/List.get:(I)Ljava/lang/Object;
     141: checkcast     #94                 // class org/eclipse/egit/core/synchronize/ThreeWayDiffEntry
     144: astore        7
     146: aload         7
     148: invokevirtual #131                // Method org/eclipse/egit/core/synchronize/ThreeWayDiffEntry.getDirection:()Lorg/eclipse/egit/core/synchronize/ThreeWayDiffEntry$Direction;
     151: getstatic     #135                // Field org/eclipse/egit/core/synchronize/ThreeWayDiffEntry$Direction.OUTGOING:Lorg/eclipse/egit/core/synchronize/ThreeWayDiffEntry$Direction;
     154: invokestatic  #123                // Method org/hamcrest/CoreMatchers.is:(Ljava/lang/Object;)Lorg/hamcrest/Matcher;
     157: invokestatic  #105                // Method org/junit/Assert.assertThat:(Ljava/lang/Object;Lorg/hamcrest/Matcher;)V
     160: aload         7
     162: invokevirtual #141                // Method org/eclipse/egit/core/synchronize/ThreeWayDiffEntry.getChangeType:()Lorg/eclipse/egit/core/synchronize/ThreeWayDiffEntry$ChangeType;
     165: getstatic     #182                // Field org/eclipse/egit/core/synchronize/ThreeWayDiffEntry$ChangeType.DELETE:Lorg/eclipse/egit/core/synchronize/ThreeWayDiffEntry$ChangeType;
     168: invokestatic  #123                // Method org/hamcrest/CoreMatchers.is:(Ljava/lang/Object;)Lorg/hamcrest/Matcher;
     171: invokestatic  #105                // Method org/junit/Assert.assertThat:(Ljava/lang/Object;Lorg/hamcrest/Matcher;)V
     174: aload         7
     176: invokevirtual #151                // Method org/eclipse/egit/core/synchronize/ThreeWayDiffEntry.getPath:()Ljava/lang/String;
     179: ldc           #32                 // String a.txt
     181: invokestatic  #123                // Method org/hamcrest/CoreMatchers.is:(Ljava/lang/Object;)Lorg/hamcrest/Matcher;
     184: invokestatic  #105                // Method org/junit/Assert.assertThat:(Ljava/lang/Object;Lorg/hamcrest/Matcher;)V
     187: aload         5
     189: ifnull        239
     192: aload         5
     194: invokevirtual #155                // Method org/eclipse/jgit/treewalk/TreeWalk.close:()V
     197: goto          239
     200: astore_3      
     201: aload         5
     203: ifnull        211
     206: aload         5
     208: invokevirtual #155                // Method org/eclipse/jgit/treewalk/TreeWalk.close:()V
     211: aload_3       
     212: athrow        
     213: astore        4
     215: aload_3       
     216: ifnonnull     225
     219: aload         4
     221: astore_3      
     222: goto          237
     225: aload_3       
     226: aload         4
     228: if_acmpeq     237
     231: aload_3       
     232: aload         4
     234: invokevirtual #158                // Method java/lang/Throwable.addSuppressed:(Ljava/lang/Throwable;)V
     237: aload_3       
     238: athrow        
     239: return        
    Exception table:
       from    to  target type
          65   187   200   any
          52   213   213   any

  public void testShouldListIncomingDelete() throws java.lang.Exception;
    Code:
       0: aload_0       
       1: ldc           #32                 // String a.txt
       3: ldc           #34                 // String content
       5: invokespecial #36                 // Method writeTrashFile:(Ljava/lang/String;Ljava/lang/String;)Ljava/io/File;
       8: pop           
       9: new           #40                 // class org/eclipse/jgit/api/Git
      12: dup           
      13: aload_0       
      14: getfield      #28                 // Field db:Lorg/eclipse/jgit/lib/Repository;
      17: invokespecial #42                 // Method org/eclipse/jgit/api/Git."<init>":(Lorg/eclipse/jgit/lib/Repository;)V
      20: astore_1      
      21: aload_1       
      22: invokevirtual #45                 // Method org/eclipse/jgit/api/Git.add:()Lorg/eclipse/jgit/api/AddCommand;
      25: ldc           #32                 // String a.txt
      27: invokevirtual #49                 // Method org/eclipse/jgit/api/AddCommand.addFilepattern:(Ljava/lang/String;)Lorg/eclipse/jgit/api/AddCommand;
      30: invokevirtual #55                 // Method org/eclipse/jgit/api/AddCommand.call:()Lorg/eclipse/jgit/dircache/DirCache;
      33: pop           
      34: aload_1       
      35: invokevirtual #59                 // Method org/eclipse/jgit/api/Git.commit:()Lorg/eclipse/jgit/api/CommitCommand;
      38: ldc           #63                 // String initial commit
      40: invokevirtual #65                 // Method org/eclipse/jgit/api/CommitCommand.setMessage:(Ljava/lang/String;)Lorg/eclipse/jgit/api/CommitCommand;
      43: invokevirtual #71                 // Method org/eclipse/jgit/api/CommitCommand.call:()Lorg/eclipse/jgit/revwalk/RevCommit;
      46: astore_2      
      47: aconst_null   
      48: astore_3      
      49: aconst_null   
      50: astore        4
      52: new           #74                 // class org/eclipse/jgit/treewalk/TreeWalk
      55: dup           
      56: aload_0       
      57: getfield      #28                 // Field db:Lorg/eclipse/jgit/lib/Repository;
      60: invokespecial #76                 // Method org/eclipse/jgit/treewalk/TreeWalk."<init>":(Lorg/eclipse/jgit/lib/Repository;)V
      63: astore        5
      65: aload         5
      67: aload_2       
      68: invokevirtual #77                 // Method org/eclipse/jgit/revwalk/RevCommit.getTree:()Lorg/eclipse/jgit/revwalk/RevTree;
      71: invokevirtual #83                 // Method org/eclipse/jgit/treewalk/TreeWalk.addTree:(Lorg/eclipse/jgit/lib/AnyObjectId;)I
      74: pop           
      75: aload         5
      77: aload_2       
      78: invokevirtual #77                 // Method org/eclipse/jgit/revwalk/RevCommit.getTree:()Lorg/eclipse/jgit/revwalk/RevTree;
      81: invokevirtual #83                 // Method org/eclipse/jgit/treewalk/TreeWalk.addTree:(Lorg/eclipse/jgit/lib/AnyObjectId;)I
      84: pop           
      85: aload         5
      87: new           #87                 // class org/eclipse/jgit/treewalk/EmptyTreeIterator
      90: dup           
      91: invokespecial #89                 // Method org/eclipse/jgit/treewalk/EmptyTreeIterator."<init>":()V
      94: invokevirtual #90                 // Method org/eclipse/jgit/treewalk/TreeWalk.addTree:(Lorg/eclipse/jgit/treewalk/AbstractTreeIterator;)I
      97: pop           
      98: aload         5
     100: invokestatic  #93                 // Method org/eclipse/egit/core/synchronize/ThreeWayDiffEntry.scan:(Lorg/eclipse/jgit/treewalk/TreeWalk;)Ljava/util/List;
     103: astore        6
     105: aload         6
     107: invokestatic  #99                 // Method org/hamcrest/CoreMatchers.notNullValue:()Lorg/hamcrest/Matcher;
     110: invokestatic  #105                // Method org/junit/Assert.assertThat:(Ljava/lang/Object;Lorg/hamcrest/Matcher;)V
     113: aload         6
     115: invokeinterface #111,  1          // InterfaceMethod java/util/List.size:()I
     120: invokestatic  #117                // Method java/lang/Integer.valueOf:(I)Ljava/lang/Integer;
     123: iconst_1      
     124: invokestatic  #117                // Method java/lang/Integer.valueOf:(I)Ljava/lang/Integer;
     127: invokestatic  #123                // Method org/hamcrest/CoreMatchers.is:(Ljava/lang/Object;)Lorg/hamcrest/Matcher;
     130: invokestatic  #105                // Method org/junit/Assert.assertThat:(Ljava/lang/Object;Lorg/hamcrest/Matcher;)V
     133: aload         6
     135: iconst_0      
     136: invokeinterface #127,  2          // InterfaceMethod java/util/List.get:(I)Ljava/lang/Object;
     141: checkcast     #94                 // class org/eclipse/egit/core/synchronize/ThreeWayDiffEntry
     144: astore        7
     146: aload         7
     148: invokevirtual #131                // Method org/eclipse/egit/core/synchronize/ThreeWayDiffEntry.getDirection:()Lorg/eclipse/egit/core/synchronize/ThreeWayDiffEntry$Direction;
     151: getstatic     #178                // Field org/eclipse/egit/core/synchronize/ThreeWayDiffEntry$Direction.INCOMING:Lorg/eclipse/egit/core/synchronize/ThreeWayDiffEntry$Direction;
     154: invokestatic  #123                // Method org/hamcrest/CoreMatchers.is:(Ljava/lang/Object;)Lorg/hamcrest/Matcher;
     157: invokestatic  #105                // Method org/junit/Assert.assertThat:(Ljava/lang/Object;Lorg/hamcrest/Matcher;)V
     160: aload         7
     162: invokevirtual #141                // Method org/eclipse/egit/core/synchronize/ThreeWayDiffEntry.getChangeType:()Lorg/eclipse/egit/core/synchronize/ThreeWayDiffEntry$ChangeType;
     165: getstatic     #182                // Field org/eclipse/egit/core/synchronize/ThreeWayDiffEntry$ChangeType.DELETE:Lorg/eclipse/egit/core/synchronize/ThreeWayDiffEntry$ChangeType;
     168: invokestatic  #123                // Method org/hamcrest/CoreMatchers.is:(Ljava/lang/Object;)Lorg/hamcrest/Matcher;
     171: invokestatic  #105                // Method org/junit/Assert.assertThat:(Ljava/lang/Object;Lorg/hamcrest/Matcher;)V
     174: aload         7
     176: invokevirtual #151                // Method org/eclipse/egit/core/synchronize/ThreeWayDiffEntry.getPath:()Ljava/lang/String;
     179: ldc           #32                 // String a.txt
     181: invokestatic  #123                // Method org/hamcrest/CoreMatchers.is:(Ljava/lang/Object;)Lorg/hamcrest/Matcher;
     184: invokestatic  #105                // Method org/junit/Assert.assertThat:(Ljava/lang/Object;Lorg/hamcrest/Matcher;)V
     187: aload         5
     189: ifnull        239
     192: aload         5
     194: invokevirtual #155                // Method org/eclipse/jgit/treewalk/TreeWalk.close:()V
     197: goto          239
     200: astore_3      
     201: aload         5
     203: ifnull        211
     206: aload         5
     208: invokevirtual #155                // Method org/eclipse/jgit/treewalk/TreeWalk.close:()V
     211: aload_3       
     212: athrow        
     213: astore        4
     215: aload_3       
     216: ifnonnull     225
     219: aload         4
     221: astore_3      
     222: goto          237
     225: aload_3       
     226: aload         4
     228: if_acmpeq     237
     231: aload_3       
     232: aload         4
     234: invokevirtual #158                // Method java/lang/Throwable.addSuppressed:(Ljava/lang/Throwable;)V
     237: aload_3       
     238: athrow        
     239: return        
    Exception table:
       from    to  target type
          65   187   200   any
          52   213   213   any

  public void testShouldListConflictingChange() throws java.lang.Exception;
    Code:
       0: aload_0       
       1: ldc           #32                 // String a.txt
       3: ldc           #34                 // String content
       5: invokespecial #36                 // Method writeTrashFile:(Ljava/lang/String;Ljava/lang/String;)Ljava/io/File;
       8: pop           
       9: new           #40                 // class org/eclipse/jgit/api/Git
      12: dup           
      13: aload_0       
      14: getfield      #28                 // Field db:Lorg/eclipse/jgit/lib/Repository;
      17: invokespecial #42                 // Method org/eclipse/jgit/api/Git."<init>":(Lorg/eclipse/jgit/lib/Repository;)V
      20: astore_1      
      21: aload_1       
      22: invokevirtual #45                 // Method org/eclipse/jgit/api/Git.add:()Lorg/eclipse/jgit/api/AddCommand;
      25: ldc           #32                 // String a.txt
      27: invokevirtual #49                 // Method org/eclipse/jgit/api/AddCommand.addFilepattern:(Ljava/lang/String;)Lorg/eclipse/jgit/api/AddCommand;
      30: invokevirtual #55                 // Method org/eclipse/jgit/api/AddCommand.call:()Lorg/eclipse/jgit/dircache/DirCache;
      33: pop           
      34: aload_1       
      35: invokevirtual #59                 // Method org/eclipse/jgit/api/Git.commit:()Lorg/eclipse/jgit/api/CommitCommand;
      38: ldc           #63                 // String initial commit
      40: invokevirtual #65                 // Method org/eclipse/jgit/api/CommitCommand.setMessage:(Ljava/lang/String;)Lorg/eclipse/jgit/api/CommitCommand;
      43: invokevirtual #71                 // Method org/eclipse/jgit/api/CommitCommand.call:()Lorg/eclipse/jgit/revwalk/RevCommit;
      46: astore_2      
      47: aconst_null   
      48: astore_3      
      49: aconst_null   
      50: astore        4
      52: new           #74                 // class org/eclipse/jgit/treewalk/TreeWalk
      55: dup           
      56: aload_0       
      57: getfield      #28                 // Field db:Lorg/eclipse/jgit/lib/Repository;
      60: invokespecial #76                 // Method org/eclipse/jgit/treewalk/TreeWalk."<init>":(Lorg/eclipse/jgit/lib/Repository;)V
      63: astore        5
      65: aload         5
      67: new           #87                 // class org/eclipse/jgit/treewalk/EmptyTreeIterator
      70: dup           
      71: invokespecial #89                 // Method org/eclipse/jgit/treewalk/EmptyTreeIterator."<init>":()V
      74: invokevirtual #90                 // Method org/eclipse/jgit/treewalk/TreeWalk.addTree:(Lorg/eclipse/jgit/treewalk/AbstractTreeIterator;)I
      77: pop           
      78: aload         5
      80: aload_2       
      81: invokevirtual #77                 // Method org/eclipse/jgit/revwalk/RevCommit.getTree:()Lorg/eclipse/jgit/revwalk/RevTree;
      84: invokevirtual #83                 // Method org/eclipse/jgit/treewalk/TreeWalk.addTree:(Lorg/eclipse/jgit/lib/AnyObjectId;)I
      87: pop           
      88: aload         5
      90: new           #87                 // class org/eclipse/jgit/treewalk/EmptyTreeIterator
      93: dup           
      94: invokespecial #89                 // Method org/eclipse/jgit/treewalk/EmptyTreeIterator."<init>":()V
      97: invokevirtual #90                 // Method org/eclipse/jgit/treewalk/TreeWalk.addTree:(Lorg/eclipse/jgit/treewalk/AbstractTreeIterator;)I
     100: pop           
     101: aload         5
     103: invokestatic  #93                 // Method org/eclipse/egit/core/synchronize/ThreeWayDiffEntry.scan:(Lorg/eclipse/jgit/treewalk/TreeWalk;)Ljava/util/List;
     106: astore        6
     108: aload         6
     110: invokestatic  #99                 // Method org/hamcrest/CoreMatchers.notNullValue:()Lorg/hamcrest/Matcher;
     113: invokestatic  #105                // Method org/junit/Assert.assertThat:(Ljava/lang/Object;Lorg/hamcrest/Matcher;)V
     116: aload         6
     118: invokeinterface #111,  1          // InterfaceMethod java/util/List.size:()I
     123: invokestatic  #117                // Method java/lang/Integer.valueOf:(I)Ljava/lang/Integer;
     126: iconst_1      
     127: invokestatic  #117                // Method java/lang/Integer.valueOf:(I)Ljava/lang/Integer;
     130: invokestatic  #123                // Method org/hamcrest/CoreMatchers.is:(Ljava/lang/Object;)Lorg/hamcrest/Matcher;
     133: invokestatic  #105                // Method org/junit/Assert.assertThat:(Ljava/lang/Object;Lorg/hamcrest/Matcher;)V
     136: aload         6
     138: iconst_0      
     139: invokeinterface #127,  2          // InterfaceMethod java/util/List.get:(I)Ljava/lang/Object;
     144: checkcast     #94                 // class org/eclipse/egit/core/synchronize/ThreeWayDiffEntry
     147: astore        7
     149: aload         7
     151: invokevirtual #131                // Method org/eclipse/egit/core/synchronize/ThreeWayDiffEntry.getDirection:()Lorg/eclipse/egit/core/synchronize/ThreeWayDiffEntry$Direction;
     154: getstatic     #187                // Field org/eclipse/egit/core/synchronize/ThreeWayDiffEntry$Direction.CONFLICTING:Lorg/eclipse/egit/core/synchronize/ThreeWayDiffEntry$Direction;
     157: invokestatic  #123                // Method org/hamcrest/CoreMatchers.is:(Ljava/lang/Object;)Lorg/hamcrest/Matcher;
     160: invokestatic  #105                // Method org/junit/Assert.assertThat:(Ljava/lang/Object;Lorg/hamcrest/Matcher;)V
     163: aload         7
     165: invokevirtual #141                // Method org/eclipse/egit/core/synchronize/ThreeWayDiffEntry.getChangeType:()Lorg/eclipse/egit/core/synchronize/ThreeWayDiffEntry$ChangeType;
     168: getstatic     #190                // Field org/eclipse/egit/core/synchronize/ThreeWayDiffEntry$ChangeType.MODIFY:Lorg/eclipse/egit/core/synchronize/ThreeWayDiffEntry$ChangeType;
     171: invokestatic  #123                // Method org/hamcrest/CoreMatchers.is:(Ljava/lang/Object;)Lorg/hamcrest/Matcher;
     174: invokestatic  #105                // Method org/junit/Assert.assertThat:(Ljava/lang/Object;Lorg/hamcrest/Matcher;)V
     177: aload         5
     179: ifnull        229
     182: aload         5
     184: invokevirtual #155                // Method org/eclipse/jgit/treewalk/TreeWalk.close:()V
     187: goto          229
     190: astore_3      
     191: aload         5
     193: ifnull        201
     196: aload         5
     198: invokevirtual #155                // Method org/eclipse/jgit/treewalk/TreeWalk.close:()V
     201: aload_3       
     202: athrow        
     203: astore        4
     205: aload_3       
     206: ifnonnull     215
     209: aload         4
     211: astore_3      
     212: goto          227
     215: aload_3       
     216: aload         4
     218: if_acmpeq     227
     221: aload_3       
     222: aload         4
     224: invokevirtual #158                // Method java/lang/Throwable.addSuppressed:(Ljava/lang/Throwable;)V
     227: aload_3       
     228: athrow        
     229: return        
    Exception table:
       from    to  target type
          65   177   190   any
          52   203   203   any

  public void testShouldListConflictingChange2() throws java.lang.Exception;
    Code:
       0: aload_0       
       1: ldc           #32                 // String a.txt
       3: ldc           #34                 // String content
       5: invokespecial #36                 // Method writeTrashFile:(Ljava/lang/String;Ljava/lang/String;)Ljava/io/File;
       8: pop           
       9: new           #40                 // class org/eclipse/jgit/api/Git
      12: dup           
      13: aload_0       
      14: getfield      #28                 // Field db:Lorg/eclipse/jgit/lib/Repository;
      17: invokespecial #42                 // Method org/eclipse/jgit/api/Git."<init>":(Lorg/eclipse/jgit/lib/Repository;)V
      20: astore_1      
      21: aload_1       
      22: invokevirtual #45                 // Method org/eclipse/jgit/api/Git.add:()Lorg/eclipse/jgit/api/AddCommand;
      25: ldc           #32                 // String a.txt
      27: invokevirtual #49                 // Method org/eclipse/jgit/api/AddCommand.addFilepattern:(Ljava/lang/String;)Lorg/eclipse/jgit/api/AddCommand;
      30: invokevirtual #55                 // Method org/eclipse/jgit/api/AddCommand.call:()Lorg/eclipse/jgit/dircache/DirCache;
      33: pop           
      34: aload_1       
      35: invokevirtual #59                 // Method org/eclipse/jgit/api/Git.commit:()Lorg/eclipse/jgit/api/CommitCommand;
      38: ldc           #63                 // String initial commit
      40: invokevirtual #65                 // Method org/eclipse/jgit/api/CommitCommand.setMessage:(Ljava/lang/String;)Lorg/eclipse/jgit/api/CommitCommand;
      43: invokevirtual #71                 // Method org/eclipse/jgit/api/CommitCommand.call:()Lorg/eclipse/jgit/revwalk/RevCommit;
      46: astore_2      
      47: aconst_null   
      48: astore_3      
      49: aconst_null   
      50: astore        4
      52: new           #74                 // class org/eclipse/jgit/treewalk/TreeWalk
      55: dup           
      56: aload_0       
      57: getfield      #28                 // Field db:Lorg/eclipse/jgit/lib/Repository;
      60: invokespecial #76                 // Method org/eclipse/jgit/treewalk/TreeWalk."<init>":(Lorg/eclipse/jgit/lib/Repository;)V
      63: astore        5
      65: aload         5
      67: aload_2       
      68: invokevirtual #77                 // Method org/eclipse/jgit/revwalk/RevCommit.getTree:()Lorg/eclipse/jgit/revwalk/RevTree;
      71: invokevirtual #83                 // Method org/eclipse/jgit/treewalk/TreeWalk.addTree:(Lorg/eclipse/jgit/lib/AnyObjectId;)I
      74: pop           
      75: aload         5
      77: new           #87                 // class org/eclipse/jgit/treewalk/EmptyTreeIterator
      80: dup           
      81: invokespecial #89                 // Method org/eclipse/jgit/treewalk/EmptyTreeIterator."<init>":()V
      84: invokevirtual #90                 // Method org/eclipse/jgit/treewalk/TreeWalk.addTree:(Lorg/eclipse/jgit/treewalk/AbstractTreeIterator;)I
      87: pop           
      88: aload         5
      90: aload_2       
      91: invokevirtual #77                 // Method org/eclipse/jgit/revwalk/RevCommit.getTree:()Lorg/eclipse/jgit/revwalk/RevTree;
      94: invokevirtual #83                 // Method org/eclipse/jgit/treewalk/TreeWalk.addTree:(Lorg/eclipse/jgit/lib/AnyObjectId;)I
      97: pop           
      98: aload         5
     100: invokestatic  #93                 // Method org/eclipse/egit/core/synchronize/ThreeWayDiffEntry.scan:(Lorg/eclipse/jgit/treewalk/TreeWalk;)Ljava/util/List;
     103: astore        6
     105: aload         6
     107: invokestatic  #99                 // Method org/hamcrest/CoreMatchers.notNullValue:()Lorg/hamcrest/Matcher;
     110: invokestatic  #105                // Method org/junit/Assert.assertThat:(Ljava/lang/Object;Lorg/hamcrest/Matcher;)V
     113: aload         6
     115: invokeinterface #111,  1          // InterfaceMethod java/util/List.size:()I
     120: invokestatic  #117                // Method java/lang/Integer.valueOf:(I)Ljava/lang/Integer;
     123: iconst_1      
     124: invokestatic  #117                // Method java/lang/Integer.valueOf:(I)Ljava/lang/Integer;
     127: invokestatic  #123                // Method org/hamcrest/CoreMatchers.is:(Ljava/lang/Object;)Lorg/hamcrest/Matcher;
     130: invokestatic  #105                // Method org/junit/Assert.assertThat:(Ljava/lang/Object;Lorg/hamcrest/Matcher;)V
     133: aload         6
     135: iconst_0      
     136: invokeinterface #127,  2          // InterfaceMethod java/util/List.get:(I)Ljava/lang/Object;
     141: checkcast     #94                 // class org/eclipse/egit/core/synchronize/ThreeWayDiffEntry
     144: astore        7
     146: aload         7
     148: invokevirtual #131                // Method org/eclipse/egit/core/synchronize/ThreeWayDiffEntry.getDirection:()Lorg/eclipse/egit/core/synchronize/ThreeWayDiffEntry$Direction;
     151: getstatic     #187                // Field org/eclipse/egit/core/synchronize/ThreeWayDiffEntry$Direction.CONFLICTING:Lorg/eclipse/egit/core/synchronize/ThreeWayDiffEntry$Direction;
     154: invokestatic  #123                // Method org/hamcrest/CoreMatchers.is:(Ljava/lang/Object;)Lorg/hamcrest/Matcher;
     157: invokestatic  #105                // Method org/junit/Assert.assertThat:(Ljava/lang/Object;Lorg/hamcrest/Matcher;)V
     160: aload         7
     162: invokevirtual #141                // Method org/eclipse/egit/core/synchronize/ThreeWayDiffEntry.getChangeType:()Lorg/eclipse/egit/core/synchronize/ThreeWayDiffEntry$ChangeType;
     165: getstatic     #190                // Field org/eclipse/egit/core/synchronize/ThreeWayDiffEntry$ChangeType.MODIFY:Lorg/eclipse/egit/core/synchronize/ThreeWayDiffEntry$ChangeType;
     168: invokestatic  #123                // Method org/hamcrest/CoreMatchers.is:(Ljava/lang/Object;)Lorg/hamcrest/Matcher;
     171: invokestatic  #105                // Method org/junit/Assert.assertThat:(Ljava/lang/Object;Lorg/hamcrest/Matcher;)V
     174: aload         7
     176: invokevirtual #151                // Method org/eclipse/egit/core/synchronize/ThreeWayDiffEntry.getPath:()Ljava/lang/String;
     179: ldc           #32                 // String a.txt
     181: invokestatic  #123                // Method org/hamcrest/CoreMatchers.is:(Ljava/lang/Object;)Lorg/hamcrest/Matcher;
     184: invokestatic  #105                // Method org/junit/Assert.assertThat:(Ljava/lang/Object;Lorg/hamcrest/Matcher;)V
     187: aload         5
     189: ifnull        239
     192: aload         5
     194: invokevirtual #155                // Method org/eclipse/jgit/treewalk/TreeWalk.close:()V
     197: goto          239
     200: astore_3      
     201: aload         5
     203: ifnull        211
     206: aload         5
     208: invokevirtual #155                // Method org/eclipse/jgit/treewalk/TreeWalk.close:()V
     211: aload_3       
     212: athrow        
     213: astore        4
     215: aload_3       
     216: ifnonnull     225
     219: aload         4
     221: astore_3      
     222: goto          237
     225: aload_3       
     226: aload         4
     228: if_acmpeq     237
     231: aload_3       
     232: aload         4
     234: invokevirtual #158                // Method java/lang/Throwable.addSuppressed:(Ljava/lang/Throwable;)V
     237: aload_3       
     238: athrow        
     239: return        
    Exception table:
       from    to  target type
          65   187   200   any
          52   213   213   any

  public void testShouldListIncomingModify() throws java.lang.Exception;
    Code:
       0: aload_0       
       1: ldc           #32                 // String a.txt
       3: ldc           #34                 // String content
       5: invokespecial #36                 // Method writeTrashFile:(Ljava/lang/String;Ljava/lang/String;)Ljava/io/File;
       8: pop           
       9: new           #40                 // class org/eclipse/jgit/api/Git
      12: dup           
      13: aload_0       
      14: getfield      #28                 // Field db:Lorg/eclipse/jgit/lib/Repository;
      17: invokespecial #42                 // Method org/eclipse/jgit/api/Git."<init>":(Lorg/eclipse/jgit/lib/Repository;)V
      20: astore_1      
      21: aload_1       
      22: invokevirtual #45                 // Method org/eclipse/jgit/api/Git.add:()Lorg/eclipse/jgit/api/AddCommand;
      25: ldc           #32                 // String a.txt
      27: invokevirtual #49                 // Method org/eclipse/jgit/api/AddCommand.addFilepattern:(Ljava/lang/String;)Lorg/eclipse/jgit/api/AddCommand;
      30: invokevirtual #55                 // Method org/eclipse/jgit/api/AddCommand.call:()Lorg/eclipse/jgit/dircache/DirCache;
      33: pop           
      34: aload_1       
      35: invokevirtual #59                 // Method org/eclipse/jgit/api/Git.commit:()Lorg/eclipse/jgit/api/CommitCommand;
      38: ldc           #63                 // String initial commit
      40: invokevirtual #65                 // Method org/eclipse/jgit/api/CommitCommand.setMessage:(Ljava/lang/String;)Lorg/eclipse/jgit/api/CommitCommand;
      43: invokevirtual #71                 // Method org/eclipse/jgit/api/CommitCommand.call:()Lorg/eclipse/jgit/revwalk/RevCommit;
      46: astore_2      
      47: aload_0       
      48: ldc           #32                 // String a.txt
      50: ldc           #195                // String new line
      52: invokespecial #36                 // Method writeTrashFile:(Ljava/lang/String;Ljava/lang/String;)Ljava/io/File;
      55: pop           
      56: aload_1       
      57: invokevirtual #59                 // Method org/eclipse/jgit/api/Git.commit:()Lorg/eclipse/jgit/api/CommitCommand;
      60: iconst_1      
      61: invokevirtual #197                // Method org/eclipse/jgit/api/CommitCommand.setAll:(Z)Lorg/eclipse/jgit/api/CommitCommand;
      64: ldc           #201                // String second commit
      66: invokevirtual #65                 // Method org/eclipse/jgit/api/CommitCommand.setMessage:(Ljava/lang/String;)Lorg/eclipse/jgit/api/CommitCommand;
      69: invokevirtual #71                 // Method org/eclipse/jgit/api/CommitCommand.call:()Lorg/eclipse/jgit/revwalk/RevCommit;
      72: astore_3      
      73: aconst_null   
      74: astore        4
      76: aconst_null   
      77: astore        5
      79: new           #74                 // class org/eclipse/jgit/treewalk/TreeWalk
      82: dup           
      83: aload_0       
      84: getfield      #28                 // Field db:Lorg/eclipse/jgit/lib/Repository;
      87: invokespecial #76                 // Method org/eclipse/jgit/treewalk/TreeWalk."<init>":(Lorg/eclipse/jgit/lib/Repository;)V
      90: astore        6
      92: aload         6
      94: aload_2       
      95: invokevirtual #77                 // Method org/eclipse/jgit/revwalk/RevCommit.getTree:()Lorg/eclipse/jgit/revwalk/RevTree;
      98: invokevirtual #83                 // Method org/eclipse/jgit/treewalk/TreeWalk.addTree:(Lorg/eclipse/jgit/lib/AnyObjectId;)I
     101: pop           
     102: aload         6
     104: aload_2       
     105: invokevirtual #77                 // Method org/eclipse/jgit/revwalk/RevCommit.getTree:()Lorg/eclipse/jgit/revwalk/RevTree;
     108: invokevirtual #83                 // Method org/eclipse/jgit/treewalk/TreeWalk.addTree:(Lorg/eclipse/jgit/lib/AnyObjectId;)I
     111: pop           
     112: aload         6
     114: aload_3       
     115: invokevirtual #77                 // Method org/eclipse/jgit/revwalk/RevCommit.getTree:()Lorg/eclipse/jgit/revwalk/RevTree;
     118: invokevirtual #83                 // Method org/eclipse/jgit/treewalk/TreeWalk.addTree:(Lorg/eclipse/jgit/lib/AnyObjectId;)I
     121: pop           
     122: aload         6
     124: invokestatic  #93                 // Method org/eclipse/egit/core/synchronize/ThreeWayDiffEntry.scan:(Lorg/eclipse/jgit/treewalk/TreeWalk;)Ljava/util/List;
     127: astore        7
     129: aload         7
     131: invokestatic  #99                 // Method org/hamcrest/CoreMatchers.notNullValue:()Lorg/hamcrest/Matcher;
     134: invokestatic  #105                // Method org/junit/Assert.assertThat:(Ljava/lang/Object;Lorg/hamcrest/Matcher;)V
     137: aload         7
     139: invokeinterface #111,  1          // InterfaceMethod java/util/List.size:()I
     144: invokestatic  #117                // Method java/lang/Integer.valueOf:(I)Ljava/lang/Integer;
     147: iconst_1      
     148: invokestatic  #117                // Method java/lang/Integer.valueOf:(I)Ljava/lang/Integer;
     151: invokestatic  #123                // Method org/hamcrest/CoreMatchers.is:(Ljava/lang/Object;)Lorg/hamcrest/Matcher;
     154: invokestatic  #105                // Method org/junit/Assert.assertThat:(Ljava/lang/Object;Lorg/hamcrest/Matcher;)V
     157: aload         7
     159: iconst_0      
     160: invokeinterface #127,  2          // InterfaceMethod java/util/List.get:(I)Ljava/lang/Object;
     165: checkcast     #94                 // class org/eclipse/egit/core/synchronize/ThreeWayDiffEntry
     168: astore        8
     170: aload         8
     172: invokevirtual #131                // Method org/eclipse/egit/core/synchronize/ThreeWayDiffEntry.getDirection:()Lorg/eclipse/egit/core/synchronize/ThreeWayDiffEntry$Direction;
     175: getstatic     #178                // Field org/eclipse/egit/core/synchronize/ThreeWayDiffEntry$Direction.INCOMING:Lorg/eclipse/egit/core/synchronize/ThreeWayDiffEntry$Direction;
     178: invokestatic  #123                // Method org/hamcrest/CoreMatchers.is:(Ljava/lang/Object;)Lorg/hamcrest/Matcher;
     181: invokestatic  #105                // Method org/junit/Assert.assertThat:(Ljava/lang/Object;Lorg/hamcrest/Matcher;)V
     184: aload         8
     186: invokevirtual #141                // Method org/eclipse/egit/core/synchronize/ThreeWayDiffEntry.getChangeType:()Lorg/eclipse/egit/core/synchronize/ThreeWayDiffEntry$ChangeType;
     189: getstatic     #190                // Field org/eclipse/egit/core/synchronize/ThreeWayDiffEntry$ChangeType.MODIFY:Lorg/eclipse/egit/core/synchronize/ThreeWayDiffEntry$ChangeType;
     192: invokestatic  #123                // Method org/hamcrest/CoreMatchers.is:(Ljava/lang/Object;)Lorg/hamcrest/Matcher;
     195: invokestatic  #105                // Method org/junit/Assert.assertThat:(Ljava/lang/Object;Lorg/hamcrest/Matcher;)V
     198: aload         8
     200: invokevirtual #151                // Method org/eclipse/egit/core/synchronize/ThreeWayDiffEntry.getPath:()Ljava/lang/String;
     203: ldc           #32                 // String a.txt
     205: invokestatic  #123                // Method org/hamcrest/CoreMatchers.is:(Ljava/lang/Object;)Lorg/hamcrest/Matcher;
     208: invokestatic  #105                // Method org/junit/Assert.assertThat:(Ljava/lang/Object;Lorg/hamcrest/Matcher;)V
     211: aload         6
     213: ifnull        270
     216: aload         6
     218: invokevirtual #155                // Method org/eclipse/jgit/treewalk/TreeWalk.close:()V
     221: goto          270
     224: astore        4
     226: aload         6
     228: ifnull        236
     231: aload         6
     233: invokevirtual #155                // Method org/eclipse/jgit/treewalk/TreeWalk.close:()V
     236: aload         4
     238: athrow        
     239: astore        5
     241: aload         4
     243: ifnonnull     253
     246: aload         5
     248: astore        4
     250: goto          267
     253: aload         4
     255: aload         5
     257: if_acmpeq     267
     260: aload         4
     262: aload         5
     264: invokevirtual #158                // Method java/lang/Throwable.addSuppressed:(Ljava/lang/Throwable;)V
     267: aload         4
     269: athrow        
     270: return        
    Exception table:
       from    to  target type
          92   211   224   any
          79   239   239   any

  public void testShouldListOutgoingModify() throws java.lang.Exception;
    Code:
       0: aload_0       
       1: ldc           #32                 // String a.txt
       3: ldc           #34                 // String content
       5: invokespecial #36                 // Method writeTrashFile:(Ljava/lang/String;Ljava/lang/String;)Ljava/io/File;
       8: pop           
       9: new           #40                 // class org/eclipse/jgit/api/Git
      12: dup           
      13: aload_0       
      14: getfield      #28                 // Field db:Lorg/eclipse/jgit/lib/Repository;
      17: invokespecial #42                 // Method org/eclipse/jgit/api/Git."<init>":(Lorg/eclipse/jgit/lib/Repository;)V
      20: astore_1      
      21: aload_1       
      22: invokevirtual #45                 // Method org/eclipse/jgit/api/Git.add:()Lorg/eclipse/jgit/api/AddCommand;
      25: ldc           #32                 // String a.txt
      27: invokevirtual #49                 // Method org/eclipse/jgit/api/AddCommand.addFilepattern:(Ljava/lang/String;)Lorg/eclipse/jgit/api/AddCommand;
      30: invokevirtual #55                 // Method org/eclipse/jgit/api/AddCommand.call:()Lorg/eclipse/jgit/dircache/DirCache;
      33: pop           
      34: aload_1       
      35: invokevirtual #59                 // Method org/eclipse/jgit/api/Git.commit:()Lorg/eclipse/jgit/api/CommitCommand;
      38: ldc           #63                 // String initial commit
      40: invokevirtual #65                 // Method org/eclipse/jgit/api/CommitCommand.setMessage:(Ljava/lang/String;)Lorg/eclipse/jgit/api/CommitCommand;
      43: invokevirtual #71                 // Method org/eclipse/jgit/api/CommitCommand.call:()Lorg/eclipse/jgit/revwalk/RevCommit;
      46: astore_2      
      47: aload_0       
      48: ldc           #32                 // String a.txt
      50: ldc           #205                // String newe line
      52: invokespecial #36                 // Method writeTrashFile:(Ljava/lang/String;Ljava/lang/String;)Ljava/io/File;
      55: pop           
      56: aload_1       
      57: invokevirtual #59                 // Method org/eclipse/jgit/api/Git.commit:()Lorg/eclipse/jgit/api/CommitCommand;
      60: iconst_1      
      61: invokevirtual #197                // Method org/eclipse/jgit/api/CommitCommand.setAll:(Z)Lorg/eclipse/jgit/api/CommitCommand;
      64: ldc           #201                // String second commit
      66: invokevirtual #65                 // Method org/eclipse/jgit/api/CommitCommand.setMessage:(Ljava/lang/String;)Lorg/eclipse/jgit/api/CommitCommand;
      69: invokevirtual #71                 // Method org/eclipse/jgit/api/CommitCommand.call:()Lorg/eclipse/jgit/revwalk/RevCommit;
      72: astore_3      
      73: aconst_null   
      74: astore        4
      76: aconst_null   
      77: astore        5
      79: new           #74                 // class org/eclipse/jgit/treewalk/TreeWalk
      82: dup           
      83: aload_0       
      84: getfield      #28                 // Field db:Lorg/eclipse/jgit/lib/Repository;
      87: invokespecial #76                 // Method org/eclipse/jgit/treewalk/TreeWalk."<init>":(Lorg/eclipse/jgit/lib/Repository;)V
      90: astore        6
      92: aload         6
      94: aload_3       
      95: invokevirtual #77                 // Method org/eclipse/jgit/revwalk/RevCommit.getTree:()Lorg/eclipse/jgit/revwalk/RevTree;
      98: invokevirtual #83                 // Method org/eclipse/jgit/treewalk/TreeWalk.addTree:(Lorg/eclipse/jgit/lib/AnyObjectId;)I
     101: pop           
     102: aload         6
     104: aload_2       
     105: invokevirtual #77                 // Method org/eclipse/jgit/revwalk/RevCommit.getTree:()Lorg/eclipse/jgit/revwalk/RevTree;
     108: invokevirtual #83                 // Method org/eclipse/jgit/treewalk/TreeWalk.addTree:(Lorg/eclipse/jgit/lib/AnyObjectId;)I
     111: pop           
     112: aload         6
     114: aload_2       
     115: invokevirtual #77                 // Method org/eclipse/jgit/revwalk/RevCommit.getTree:()Lorg/eclipse/jgit/revwalk/RevTree;
     118: invokevirtual #83                 // Method org/eclipse/jgit/treewalk/TreeWalk.addTree:(Lorg/eclipse/jgit/lib/AnyObjectId;)I
     121: pop           
     122: aload         6
     124: invokestatic  #93                 // Method org/eclipse/egit/core/synchronize/ThreeWayDiffEntry.scan:(Lorg/eclipse/jgit/treewalk/TreeWalk;)Ljava/util/List;
     127: astore        7
     129: aload         7
     131: invokestatic  #99                 // Method org/hamcrest/CoreMatchers.notNullValue:()Lorg/hamcrest/Matcher;
     134: invokestatic  #105                // Method org/junit/Assert.assertThat:(Ljava/lang/Object;Lorg/hamcrest/Matcher;)V
     137: aload         7
     139: invokeinterface #111,  1          // InterfaceMethod java/util/List.size:()I
     144: invokestatic  #117                // Method java/lang/Integer.valueOf:(I)Ljava/lang/Integer;
     147: iconst_1      
     148: invokestatic  #117                // Method java/lang/Integer.valueOf:(I)Ljava/lang/Integer;
     151: invokestatic  #123                // Method org/hamcrest/CoreMatchers.is:(Ljava/lang/Object;)Lorg/hamcrest/Matcher;
     154: invokestatic  #105                // Method org/junit/Assert.assertThat:(Ljava/lang/Object;Lorg/hamcrest/Matcher;)V
     157: aload         7
     159: iconst_0      
     160: invokeinterface #127,  2          // InterfaceMethod java/util/List.get:(I)Ljava/lang/Object;
     165: checkcast     #94                 // class org/eclipse/egit/core/synchronize/ThreeWayDiffEntry
     168: astore        8
     170: aload         8
     172: invokevirtual #131                // Method org/eclipse/egit/core/synchronize/ThreeWayDiffEntry.getDirection:()Lorg/eclipse/egit/core/synchronize/ThreeWayDiffEntry$Direction;
     175: getstatic     #135                // Field org/eclipse/egit/core/synchronize/ThreeWayDiffEntry$Direction.OUTGOING:Lorg/eclipse/egit/core/synchronize/ThreeWayDiffEntry$Direction;
     178: invokestatic  #123                // Method org/hamcrest/CoreMatchers.is:(Ljava/lang/Object;)Lorg/hamcrest/Matcher;
     181: invokestatic  #105                // Method org/junit/Assert.assertThat:(Ljava/lang/Object;Lorg/hamcrest/Matcher;)V
     184: aload         8
     186: invokevirtual #141                // Method org/eclipse/egit/core/synchronize/ThreeWayDiffEntry.getChangeType:()Lorg/eclipse/egit/core/synchronize/ThreeWayDiffEntry$ChangeType;
     189: getstatic     #190                // Field org/eclipse/egit/core/synchronize/ThreeWayDiffEntry$ChangeType.MODIFY:Lorg/eclipse/egit/core/synchronize/ThreeWayDiffEntry$ChangeType;
     192: invokestatic  #123                // Method org/hamcrest/CoreMatchers.is:(Ljava/lang/Object;)Lorg/hamcrest/Matcher;
     195: invokestatic  #105                // Method org/junit/Assert.assertThat:(Ljava/lang/Object;Lorg/hamcrest/Matcher;)V
     198: aload         8
     200: invokevirtual #151                // Method org/eclipse/egit/core/synchronize/ThreeWayDiffEntry.getPath:()Ljava/lang/String;
     203: ldc           #32                 // String a.txt
     205: invokestatic  #123                // Method org/hamcrest/CoreMatchers.is:(Ljava/lang/Object;)Lorg/hamcrest/Matcher;
     208: invokestatic  #105                // Method org/junit/Assert.assertThat:(Ljava/lang/Object;Lorg/hamcrest/Matcher;)V
     211: aload         6
     213: ifnull        270
     216: aload         6
     218: invokevirtual #155                // Method org/eclipse/jgit/treewalk/TreeWalk.close:()V
     221: goto          270
     224: astore        4
     226: aload         6
     228: ifnull        236
     231: aload         6
     233: invokevirtual #155                // Method org/eclipse/jgit/treewalk/TreeWalk.close:()V
     236: aload         4
     238: athrow        
     239: astore        5
     241: aload         4
     243: ifnonnull     253
     246: aload         5
     248: astore        4
     250: goto          267
     253: aload         4
     255: aload         5
     257: if_acmpeq     267
     260: aload         4
     262: aload         5
     264: invokevirtual #158                // Method java/lang/Throwable.addSuppressed:(Ljava/lang/Throwable;)V
     267: aload         4
     269: athrow        
     270: return        
    Exception table:
       from    to  target type
          92   211   224   any
          79   239   239   any

  public void testShouldListConflictingModify() throws java.lang.Exception;
    Code:
       0: aload_0       
       1: ldc           #32                 // String a.txt
       3: ldc           #34                 // String content
       5: invokespecial #36                 // Method writeTrashFile:(Ljava/lang/String;Ljava/lang/String;)Ljava/io/File;
       8: pop           
       9: new           #40                 // class org/eclipse/jgit/api/Git
      12: dup           
      13: aload_0       
      14: getfield      #28                 // Field db:Lorg/eclipse/jgit/lib/Repository;
      17: invokespecial #42                 // Method org/eclipse/jgit/api/Git."<init>":(Lorg/eclipse/jgit/lib/Repository;)V
      20: astore_1      
      21: aload_1       
      22: invokevirtual #45                 // Method org/eclipse/jgit/api/Git.add:()Lorg/eclipse/jgit/api/AddCommand;
      25: ldc           #32                 // String a.txt
      27: invokevirtual #49                 // Method org/eclipse/jgit/api/AddCommand.addFilepattern:(Ljava/lang/String;)Lorg/eclipse/jgit/api/AddCommand;
      30: invokevirtual #55                 // Method org/eclipse/jgit/api/AddCommand.call:()Lorg/eclipse/jgit/dircache/DirCache;
      33: pop           
      34: aload_1       
      35: invokevirtual #59                 // Method org/eclipse/jgit/api/Git.commit:()Lorg/eclipse/jgit/api/CommitCommand;
      38: ldc           #63                 // String initial commit
      40: invokevirtual #65                 // Method org/eclipse/jgit/api/CommitCommand.setMessage:(Ljava/lang/String;)Lorg/eclipse/jgit/api/CommitCommand;
      43: invokevirtual #71                 // Method org/eclipse/jgit/api/CommitCommand.call:()Lorg/eclipse/jgit/revwalk/RevCommit;
      46: astore_2      
      47: aload_0       
      48: ldc           #32                 // String a.txt
      50: ldc           #195                // String new line
      52: invokespecial #36                 // Method writeTrashFile:(Ljava/lang/String;Ljava/lang/String;)Ljava/io/File;
      55: pop           
      56: aload_1       
      57: invokevirtual #59                 // Method org/eclipse/jgit/api/Git.commit:()Lorg/eclipse/jgit/api/CommitCommand;
      60: iconst_1      
      61: invokevirtual #197                // Method org/eclipse/jgit/api/CommitCommand.setAll:(Z)Lorg/eclipse/jgit/api/CommitCommand;
      64: ldc           #201                // String second commit
      66: invokevirtual #65                 // Method org/eclipse/jgit/api/CommitCommand.setMessage:(Ljava/lang/String;)Lorg/eclipse/jgit/api/CommitCommand;
      69: invokevirtual #71                 // Method org/eclipse/jgit/api/CommitCommand.call:()Lorg/eclipse/jgit/revwalk/RevCommit;
      72: astore_3      
      73: aconst_null   
      74: astore        4
      76: aconst_null   
      77: astore        5
      79: new           #74                 // class org/eclipse/jgit/treewalk/TreeWalk
      82: dup           
      83: aload_0       
      84: getfield      #28                 // Field db:Lorg/eclipse/jgit/lib/Repository;
      87: invokespecial #76                 // Method org/eclipse/jgit/treewalk/TreeWalk."<init>":(Lorg/eclipse/jgit/lib/Repository;)V
      90: astore        6
      92: aload         6
      94: aload_3       
      95: invokevirtual #77                 // Method org/eclipse/jgit/revwalk/RevCommit.getTree:()Lorg/eclipse/jgit/revwalk/RevTree;
      98: invokevirtual #83                 // Method org/eclipse/jgit/treewalk/TreeWalk.addTree:(Lorg/eclipse/jgit/lib/AnyObjectId;)I
     101: pop           
     102: aload         6
     104: aload_2       
     105: invokevirtual #77                 // Method org/eclipse/jgit/revwalk/RevCommit.getTree:()Lorg/eclipse/jgit/revwalk/RevTree;
     108: invokevirtual #83                 // Method org/eclipse/jgit/treewalk/TreeWalk.addTree:(Lorg/eclipse/jgit/lib/AnyObjectId;)I
     111: pop           
     112: aload         6
     114: aload_3       
     115: invokevirtual #77                 // Method org/eclipse/jgit/revwalk/RevCommit.getTree:()Lorg/eclipse/jgit/revwalk/RevTree;
     118: invokevirtual #83                 // Method org/eclipse/jgit/treewalk/TreeWalk.addTree:(Lorg/eclipse/jgit/lib/AnyObjectId;)I
     121: pop           
     122: aload         6
     124: invokestatic  #93                 // Method org/eclipse/egit/core/synchronize/ThreeWayDiffEntry.scan:(Lorg/eclipse/jgit/treewalk/TreeWalk;)Ljava/util/List;
     127: astore        7
     129: aload         7
     131: invokestatic  #99                 // Method org/hamcrest/CoreMatchers.notNullValue:()Lorg/hamcrest/Matcher;
     134: invokestatic  #105                // Method org/junit/Assert.assertThat:(Ljava/lang/Object;Lorg/hamcrest/Matcher;)V
     137: aload         7
     139: invokeinterface #111,  1          // InterfaceMethod java/util/List.size:()I
     144: invokestatic  #117                // Method java/lang/Integer.valueOf:(I)Ljava/lang/Integer;
     147: iconst_1      
     148: invokestatic  #117                // Method java/lang/Integer.valueOf:(I)Ljava/lang/Integer;
     151: invokestatic  #123                // Method org/hamcrest/CoreMatchers.is:(Ljava/lang/Object;)Lorg/hamcrest/Matcher;
     154: invokestatic  #105                // Method org/junit/Assert.assertThat:(Ljava/lang/Object;Lorg/hamcrest/Matcher;)V
     157: aload         7
     159: iconst_0      
     160: invokeinterface #127,  2          // InterfaceMethod java/util/List.get:(I)Ljava/lang/Object;
     165: checkcast     #94                 // class org/eclipse/egit/core/synchronize/ThreeWayDiffEntry
     168: astore        8
     170: aload         8
     172: invokevirtual #131                // Method org/eclipse/egit/core/synchronize/ThreeWayDiffEntry.getDirection:()Lorg/eclipse/egit/core/synchronize/ThreeWayDiffEntry$Direction;
     175: getstatic     #187                // Field org/eclipse/egit/core/synchronize/ThreeWayDiffEntry$Direction.CONFLICTING:Lorg/eclipse/egit/core/synchronize/ThreeWayDiffEntry$Direction;
     178: invokestatic  #123                // Method org/hamcrest/CoreMatchers.is:(Ljava/lang/Object;)Lorg/hamcrest/Matcher;
     181: invokestatic  #105                // Method org/junit/Assert.assertThat:(Ljava/lang/Object;Lorg/hamcrest/Matcher;)V
     184: aload         8
     186: invokevirtual #141                // Method org/eclipse/egit/core/synchronize/ThreeWayDiffEntry.getChangeType:()Lorg/eclipse/egit/core/synchronize/ThreeWayDiffEntry$ChangeType;
     189: getstatic     #190                // Field org/eclipse/egit/core/synchronize/ThreeWayDiffEntry$ChangeType.MODIFY:Lorg/eclipse/egit/core/synchronize/ThreeWayDiffEntry$ChangeType;
     192: invokestatic  #123                // Method org/hamcrest/CoreMatchers.is:(Ljava/lang/Object;)Lorg/hamcrest/Matcher;
     195: invokestatic  #105                // Method org/junit/Assert.assertThat:(Ljava/lang/Object;Lorg/hamcrest/Matcher;)V
     198: aload         8
     200: invokevirtual #151                // Method org/eclipse/egit/core/synchronize/ThreeWayDiffEntry.getPath:()Ljava/lang/String;
     203: ldc           #32                 // String a.txt
     205: invokestatic  #123                // Method org/hamcrest/CoreMatchers.is:(Ljava/lang/Object;)Lorg/hamcrest/Matcher;
     208: invokestatic  #105                // Method org/junit/Assert.assertThat:(Ljava/lang/Object;Lorg/hamcrest/Matcher;)V
     211: aload         6
     213: ifnull        270
     216: aload         6
     218: invokevirtual #155                // Method org/eclipse/jgit/treewalk/TreeWalk.close:()V
     221: goto          270
     224: astore        4
     226: aload         6
     228: ifnull        236
     231: aload         6
     233: invokevirtual #155                // Method org/eclipse/jgit/treewalk/TreeWalk.close:()V
     236: aload         4
     238: athrow        
     239: astore        5
     241: aload         4
     243: ifnonnull     253
     246: aload         5
     248: astore        4
     250: goto          267
     253: aload         4
     255: aload         5
     257: if_acmpeq     267
     260: aload         4
     262: aload         5
     264: invokevirtual #158                // Method java/lang/Throwable.addSuppressed:(Ljava/lang/Throwable;)V
     267: aload         4
     269: athrow        
     270: return        
    Exception table:
       from    to  target type
          92   211   224   any
          79   239   239   any

  private java.io.File writeTrashFile(java.lang.String, java.lang.String) throws java.io.IOException;
    Code:
       0: new           #210                // class java/io/File
       3: dup           
       4: aload_0       
       5: getfield      #28                 // Field db:Lorg/eclipse/jgit/lib/Repository;
       8: invokevirtual #212                // Method org/eclipse/jgit/lib/Repository.getWorkTree:()Ljava/io/File;
      11: aload_1       
      12: invokespecial #218                // Method java/io/File."<init>":(Ljava/io/File;Ljava/lang/String;)V
      15: astore_3      
      16: aload_0       
      17: aload_3       
      18: aload_2       
      19: invokevirtual #221                // Method write:(Ljava/io/File;Ljava/lang/String;)V
      22: aload_3       
      23: areturn       
}
